Workbook

Sheet Dashboard
A1: 📊 Sales Pipeline Dashboard
B6: 🎯 KEY PERFORMANCE METRICS
B8: 📊 TOTAL PROJECTS | D8: 🟢 IN HAND | F8: 🟡 TENDER | H8: 💰 PIPELINE VALUE
B9: =D9+F9 -> 22 | D9: =COUNTIF('Projects Follow UP'!G:G,"in hand") -> 16 | F9: =COUNTIF('Projects Follow UP'!G:G,"Tender") -> 6 | H9: =SUM('Projects Follow UP'!O:O) -> 73877915
B10: Active Pipeline | D10: Confirmed Deals | F10: Pending Bids | H10: Total Estimated
C12: 📊 | D12: =SUMIF('Projects Follow UP'!G:G,"In Hand",'Projects Follow UP'!O:O) -> 18947100 | E12: 📋 | F12: =SUMIF('Projects Follow UP'!G:G,"Tender",'Projects Follow UP'!O:O) -> 54930815
B13: 🔥 HOT LEADS (7 DAYS) | D13: ✅ WON DEALS | F13: ❌ LOST DEALS | H13: ⚡ DUE TODAY
B14: =COUNTIFS('Hot Leads'!H:H,">="&(TODAY()-7),'Hot Leads'!H:H,"<="&TODAY()) -> 0 | D14: =COUNTIF('Projects Follow UP'!I:I,"Won") -> 0 | E14: = | F14: =COUNTIF('Projects Follow UP'!I:I,"Lost") -> 1 | H14: =COUNTIF('Hot Leads'!K:K,"<="&TODAY())+COUNTIF('Projects Follow UP'!N:N,"<="&TODAY()) -> 10
B15: New Contacts | D15: Closed Successfully | E15: =SUM('Won Deals'!G2:G176) -> 15962 | F15: Not Converted | H15: Actions Required
B17: 📈 HIT RATE | C17: =IFERROR(D14/(D14+F14),0) -> 0
B18: 📈 ANALYTICS & INSIGHTS
B20: 📊 Pipeline by Stage | D20: 📍 Projects by Location | F20: 📋 Projects by Status
B21: Stage | C21: Count | D21: Location | E21: Count | F21: Status | G21: Count
B22: In Hand | C22: =COUNTIF('Projects Follow UP'!G:G,"In Hand") -> 16 | D22: Jeddah | E22: =COUNTIF('Projects Follow UP'!H:H,"Jeddah") -> 10 | F22: RFQ Processing | G22: =COUNTIF('Projects Follow UP'!I:I,"*RFQ*") -> 5
B23: Tender | C23: =COUNTIF('Projects Follow UP'!G:G,"Tender") -> 6 | D23: Makkah | E23: =COUNTIF('Projects Follow UP'!H:H,"Makkah") -> 6 | F23: Negotiation | G23: =COUNTIF('Projects Follow UP'!I:I,"Negotiation") -> 1
B24: Won | C24: =COUNTIF('Projects Follow UP'!G:G,"Won") -> 0 | D24: Madinah | E24: =COUNTIF('Projects Follow UP'!H:H,"Madinah")+COUNTIF('Projects Follow UP'!H:H,"Madena") -> 0 | F24: Gather Info | G24: =COUNTIF('Projects Follow UP'!I:I,"*Gather*") -> 2
B25: Lost | C25: =COUNTIF('Projects Follow UP'!G:G,"Lost") -> 0 | D25: Riyadh | E25: =COUNTIF('Projects Follow UP'!H:H,"Riyadh") -> 4 | F25: Send to Client | G25: =COUNTIF('Projects Follow UP'!I:I,"*Send*") -> 11
D26: Khobar | E26: =COUNTIF('Projects Follow UP'!H:H,"Khobar")+COUNTIF('Projects Follow UP'!H:H,"Dammam") -> 1 | F26: Closed | G26: =COUNTIF('Projects Follow UP'!I:I,"*Closed*") -> 0
D27: Other | E27: =B9-SUM(E22:E26) -> 1
B40: 🎯 ACTION CENTER - Tasks Requiring Immediate Attention
B42: 🔥 HOT LEADS - Follow Up Required | I42: ⚡ QUICK UPDATE - Edit Action / Date
B43: Name | C43: Company | D43: Phone | E43: Position | F43: Action Required | G43: Action Date | H43: Days | I43: Client | J43: New Action Required | K43: New Action Date | L43: Status
B44: {=_xlfn.LET(_xlpm.data,_xlfn._xlws.FILTER(_xlfn.HSTACK(Hot_Leads[Name],Hot_Leads[Company],IF(Hot_Leads[Phone]<>"",TEXT(Hot_Leads[Phone],"0"),""),Hot_Leads[Position],Hot_Leads[Current Action Required],Hot_Leads[Current Action Date],TODAY()-Hot_Leads[Current Action Date]),(Hot_Leads[Current Action Date]>0)*(Hot_Leads[Current Action Date]<TODAY())*(Hot_Leads[Name]<>"")),IFERROR(_xlfn.TAKE(_xlfn._xlws.SORT(_xlpm.data,7,-1),15),"✓ No Hot Leads Due Today"))} -> ✓ No Hot Leads Due Today | I44: Mohamed Elkholy | J44: مفيش اخبار جديدة عنه | K44: 46243 | L44: =IF(AND(J44<>"",K44<>""),"✓ Synced","Add update") -> ✓ Synced | M44: 966541016847
I45: Mohamed Taqash | J45: Follow Up Next Week | K45: 46140 | L45: =IF(AND(J45<>"",K45<>""),"✓ Synced","Add update") -> ✓ Synced | M45: 966569972444
I46: Majdi I. Al-Zoubi | J46: ده خلاص مبقاش معايا مهندس عبدالرحمن قالي ان فيه حد مكمل معاه | K46: 46456 | L46: =IF(AND(J46<>"",K46<>""),"✓ Synced","Add update") -> ✓ Synced | M46: 966569548850
I47: Ashraf Gadallah | J47: في اجازة في مصر و هرجع يبعتلنا مشروع ديار الحرم عشان نخشه سوا | K47: 46265 | L47: =IF(AND(J47<>"",K47<>""),"✓ Synced","Add update") -> ✓ Synced | M47: 966562292293
I48: Yasser Bahussin | J48: قالي ان البرنامج هيرسى علينا و مستني بس موفقه الادارة | K48: 46250 | L48: =IF(AND(J48<>"",K48<>""),"✓ Synced","Add update") -> ✓ Synced | M48: 966506694282
I49: Sameh Saber | J49: Send Pre and follow up | K49: 46145 | L49: =IF(AND(J49<>"",K49<>""),"✓ Synced","Add update") -> ✓ Synced | M49: 966568061671
I50: Youssef Adwi | J50: عاوز رقم حد من المشتريات | K50: 46145 | L50: =IF(AND(J50<>"",K50<>""),"✓ Synced","Add update") -> ✓ Synced | M50: 966554711520
I51: Omar Alsaad | J51: هكلمه بكره تاني عشان اعرف التفاصيل الي قالي عليها | K51: 46145 | L51: =IF(AND(J51<>"",K51<>""),"✓ Synced","Add update") -> ✓ Synced | M51: 966549733284
I52: Ibrahim Ahmed | J52: هكلمه يوم الاتنين عشان اعرف التفاصيل الجديدة | K52: 46146 | L52: =IF(AND(J52<>"",K52<>""),"✓ Synced","Add update") -> ✓ Synced | M52: 966546468592
I53: Mohamed 3essa | J53: كلمته الاحد بس مردش عليا | K53: 46146 | L53: =IF(AND(J53<>"",K53<>""),"✓ Synced","Add update") -> ✓ Synced | M53: 966598803998
I54: Ibrahim Sabry | J54: مفيش جديد مش معاه مشاريع تانيه حاليا | K54: 46364 | L54: =IF(AND(J54<>"",K54<>""),"✓ Synced","Add update") -> ✓ Synced | M54: 201111448448
I55: Azazuddin Mohamed | J55: حدد معاه ميتنج يوم الثلاثاء 6/5/2026 | K55: 46148 | L55: =IF(AND(J55<>"",K55<>""),"✓ Synced","Add update") -> ✓ Synced | M55: 966505520073
I56: Mohamed Atef | J56: 0 | K56: 46149 | L56: =IF(AND(J56<>"",K56<>""),"✓ Synced","Add update") -> ✓ Synced | M56: 966544411842
I57: Ahmed Naserallah | J57: هتابع معاه الاسبوع الجي | K57: 46149 | L57: =IF(AND(J57<>"",K57<>""),"✓ Synced","Add update") -> ✓ Synced | M57: 966561333021
I58: Abo Sultan | J58: خد منه رقم حد من المهندسين او لوكيشن الشركة | K58: 46149 | L58: =IF(AND(J58<>"",K58<>""),"✓ Synced","Add update") -> ✓ Synced | M58: 966557077244
B59: 📋 PROJECTS - Follow Up Required | I59: ⚡ PROJECT QUICK UPDATE - Follow Up / Date
B60: Project # | C60: Opportunity | D60: Client | E60: Stage | F60: Action Required | G60: Action Date | H60: Days | I60: Project | J60: New Follow Up | K60: New Follow Up Date | L60: Status
B61: {=_xlfn.LET(_xlpm.data,_xlfn._xlws.FILTER(_xlfn.HSTACK('Projects Follow UP'!A5:A139,'Projects Follow UP'!B5:B139,'Projects Follow UP'!C5:C139,'Projects Follow UP'!G5:G139,'Projects Follow UP'!R5:R139,'Projects Follow UP'!S5:S139,TODAY()-'Projects Follow UP'!S5:S139),('Projects Follow UP'!S5:S139>0)*('Projects Follow UP'!S5:S139<TODAY())*('Projects Follow UP'!A5:A139<>"")),IFERROR(_xlfn.TAKE(_xlfn._xlws.SORT(_xlpm.data,7,-1),12),"✓ No Projects Due Today"))} -> ✓ No Projects Due Today | I61: PR1018 | J61: المشروع هيخلص اقصى حاجة يوم السبت و المشروع ده مهم جدا لابعد حد عشان نقدر ناخد الباكدج كاملة | K61: 46389 | L61: =IF(AND(J61<>"",K61<>""),"✓ Synced","Add update") -> ✓ Synced | M61: PR1018
I62: PR1017 | J62: لسة مفيش جديد عامله هول عشان عمر نفسه مش بيرد عليا لسة اول ما يرد كمل تسعير فالمشروع بلص ان مفيش تشانيل اصلا | K62: 46156 | L62: =IF(AND(J62<>"",K62<>""),"✓ Synced","Add update") -> ✓ Synced | M62: PR1017
I63: PR1023 | J63: اتواصل مع ايمن شوف المشاريع الجديدة الي معاه | K63: 46158 | L63: =IF(AND(J63<>"",K63<>""),"✓ Synced","Add update") -> ✓ Synced | M63: PR1023
I64: PR1014 | J64: كلمته و قالي مفيش اي ابديت جديد لسة مستنيه لما يقولي اخر الابديت و كلمته تاني انهاردة بس لسة مردش | K64: 46160 | L64: =IF(AND(J64<>"",K64<>""),"✓ Synced","Add update") -> ✓ Synced | M64: PR1014
I65: PR1007 | J65: No Updates | K65: 46223 | L65: =IF(AND(J65<>"",K65<>""),"✓ Synced","Add update") -> ✓ Synced | M65: PR1007
I66: PR1016 | J66: اتصلت بيه اكتر من مره و لسة مردش | K66: 46223 | L66: =IF(AND(J66<>"",K66<>""),"✓ Synced","Add update") -> ✓ Synced | M66: PR1016
I67: PR1027 | J67: QT | K67: 46228 | L67: =IF(AND(J67<>"",K67<>""),"✓ Synced","Add update") -> ✓ Synced | M67: PR1027
I68: PR1030 | J68: QT | K68: 46229 | L68: =IF(AND(J68<>"",K68<>""),"✓ Synced","Add update") -> ✓ Synced | M68: PR1030
I69: PR1021 | J69: قالي انه عامل للمشاريع هولد و مستني يفضى عشان يقارن الاسعار الي بعتنهاله | K69: 46231 | L69: =IF(AND(J69<>"",K69<>""),"✓ Synced","Add update") -> ✓ Synced | M69: PR1021
I70: PR1022 | J70: قالي انه عامل للمشاريع هولد و مستني يفضى عشان يقارن الاسعار الي بعتنهاله | K70: 46231 | L70: =IF(AND(J70<>"",K70<>""),"✓ Synced","Add update") -> ✓ Synced | M70: PR1022
I71: PR1025 | J71: QT | K71: 46231 | L71: =IF(AND(J71<>"",K71<>""),"✓ Synced","Add update") -> ✓ Synced | M71: PR1025
I72: PR1029 | J72: QT | K72: 46235 | L72: =IF(AND(J72<>"",K72<>""),"✓ Synced","Add update") -> ✓ Synced | M72: PR1029
B74: 📊 WEEKLY ACTIVITY TRACKER - Plan vs Actual
B76: Week | C76: Plan | D76: Actual | E76: Variance | F76: %
B77: ="Week "&WEEKNUM(TODAY()-7*(ROWS($B$77:$B$82)-ROWS($B$77:B77))) -> Week 33 | C77: =COUNTIFS('Master Plan (2)'!$A:$A,">="&(TODAY()-WEEKDAY(TODAY(),1)+1-7*(ROWS($B$77:$B$82)-ROWS($B$77:B77))),'Master Plan (2)'!$A:$A,"<"&(TODAY()-WEEKDAY(TODAY(),1)+8-7*(ROWS($B$77:$B$82)-ROWS($B$77:B77)))) -> 36 | D77: =COUNTIFS('Master Report'!$A:$A,">="&(TODAY()-WEEKDAY(TODAY(),1)+1-7*(ROWS($B$77:$B$82)-ROWS($B$77:B77))),'Master Report'!$A:$A,"<"&(TODAY()-WEEKDAY(TODAY(),1)+8-7*(ROWS($B$77:$B$82)-ROWS($B$77:B77)))) -> 33 | E77: =D77-C77 -> -3 | F77: =IFERROR(D77/C77,0) -> 0.91666667
B78: ="Week "&WEEKNUM(TODAY()-7*(ROWS($B$77:$B$82)-ROWS($B$77:B78))) -> Week 34 | C78: =COUNTIFS('Master Plan (2)'!$A:$A,">="&(TODAY()-WEEKDAY(TODAY(),1)+1-7*(ROWS($B$77:$B$82)-ROWS($B$77:B78))),'Master Plan (2)'!$A:$A,"<"&(TODAY()-WEEKDAY(TODAY(),1)+8-7*(ROWS($B$77:$B$82)-ROWS($B$77:B78)))) -> 36 | D78: =COUNTIFS('Master Report'!$A:$A,">="&(TODAY()-WEEKDAY(TODAY(),1)+1-7*(ROWS($B$77:$B$82)-ROWS($B$77:B78))),'Master Report'!$A:$A,"<"&(TODAY()-WEEKDAY(TODAY(),1)+8-7*(ROWS($B$77:$B$82)-ROWS($B$77:B78)))) -> 23 | E78: =D78-C78 -> -13 | F78: =IFERROR(D78/C78,0) -> 0.63888889
B79: ="Week "&WEEKNUM(TODAY()-7*(ROWS($B$77:$B$82)-ROWS($B$77:B79))) -> Week 35 | C79: =COUNTIFS('Master Plan (2)'!$A:$A,">="&(TODAY()-WEEKDAY(TODAY(),1)+1-7*(ROWS($B$77:$B$82)-ROWS($B$77:B79))),'Master Plan (2)'!$A:$A,"<"&(TODAY()-WEEKDAY(TODAY(),1)+8-7*(ROWS($B$77:$B$82)-ROWS($B$77:B79)))) -> 36 | D79: =COUNTIFS('Master Report'!$A:$A,">="&(TODAY()-WEEKDAY(TODAY(),1)+1-7*(ROWS($B$77:$B$82)-ROWS($B$77:B79))),'Master Report'!$A:$A,"<"&(TODAY()-WEEKDAY(TODAY(),1)+8-7*(ROWS($B$77:$B$82)-ROWS($B$77:B79)))) -> 22 | E79: =D79-C79 -> -14 | F79: =IFERROR(D79/C79,0) -> 0.61111111
B80: ="Week "&WEEKNUM(TODAY()-7*(ROWS($B$77:$B$82)-ROWS($B$77:B80))) -> Week 36 | C80: =COUNTIFS('Master Plan (2)'!$A:$A,">="&(TODAY()-WEEKDAY(TODAY(),1)+1-7*(ROWS($B$77:$B$82)-ROWS($B$77:B80))),'Master Plan (2)'!$A:$A,"<"&(TODAY()-WEEKDAY(TODAY(),1)+8-7*(ROWS($B$77:$B$82)-ROWS($B$77:B80)))) -> 37 | D80: =COUNTIFS('Master Report'!$A:$A,">="&(TODAY()-WEEKDAY(TODAY(),1)+1-7*(ROWS($B$77:$B$82)-ROWS($B$77:B80))),'Master Report'!$A:$A,"<"&(TODAY()-WEEKDAY(TODAY(),1)+8-7*(ROWS($B$77:$B$82)-ROWS($B$77:B80)))) -> 26 | E80: =D80-C80 -> -11 | F80: =IFERROR(D80/C80,0) -> 0.7027027
B81: ="Week "&WEEKNUM(TODAY()-7*(ROWS($B$77:$B$82)-ROWS($B$77:B81))) -> Week 37 | C81: =COUNTIFS('Master Plan (2)'!$A:$A,">="&(TODAY()-WEEKDAY(TODAY(),1)+1-7*(ROWS($B$77:$B$82)-ROWS($B$77:B81))),'Master Plan (2)'!$A:$A,"<"&(TODAY()-WEEKDAY(TODAY(),1)+8-7*(ROWS($B$77:$B$82)-ROWS($B$77:B81)))) -> 34 | D81: =COUNTIFS('Master Report'!$A:$A,">="&(TODAY()-WEEKDAY(TODAY(),1)+1-7*(ROWS($B$77:$B$82)-ROWS($B$77:B81))),'Master Report'!$A:$A,"<"&(TODAY()-WEEKDAY(TODAY(),1)+8-7*(ROWS($B$77:$B$82)-ROWS($B$77:B81)))) -> 16 | E81: =D81-C81 -> -18 | F81: =IFERROR(D81/C81,0) -> 0.47058824
B82: ="Week "&WEEKNUM(TODAY()-7*(ROWS($B$77:$B$82)-ROWS($B$77:B82))) -> Week 38 | C82: =COUNTIFS('Master Plan (2)'!$A:$A,">="&(TODAY()-WEEKDAY(TODAY(),1)+1-7*(ROWS($B$77:$B$82)-ROWS($B$77:B82))),'Master Plan (2)'!$A:$A,"<"&(TODAY()-WEEKDAY(TODAY(),1)+8-7*(ROWS($B$77:$B$82)-ROWS($B$77:B82)))) -> 0 | D82: =COUNTIFS('Master Report'!$A:$A,">="&(TODAY()-WEEKDAY(TODAY(),1)+1-7*(ROWS($B$77:$B$82)-ROWS($B$77:B82))),'Master Report'!$A:$A,"<"&(TODAY()-WEEKDAY(TODAY(),1)+8-7*(ROWS($B$77:$B$82)-ROWS($B$77:B82)))) -> 0 | E82: =D82-C82 -> 0 | F82: =IFERROR(D82/C82,0) -> 0
B88: ⏱️ TODAY'S PERFORMANCE
B90: 🚗 F2F Visits | D90: 📞 Calls Today | F90: 🆕 New Leads (Week) | H90: 💵 Weekly Quote Value
B91: =COUNTIFS('Master Report'!A:A,TODAY(),'Master Report'!F:F,"F2F Meeting") -> 0 | D91: =COUNTIFS('Master Report'!A:A,TODAY(),'Master Report'!F:F,"Call") -> 0 | F91: =COUNTIFS('Hot Leads'!H:H,">="&(TODAY()-WEEKDAY(TODAY(),2)+1),'Hot Leads'!H:H,"<="&TODAY()) -> 0 | H91: =SUMIFS('Projects Follow UP'!O:O,'Projects Follow UP'!L:L,">="&(TODAY()-WEEKDAY(TODAY(),2)+1),'Projects Follow UP'!L:L,"<="&TODAY()) -> 0
B92: Target: 3/day | D92: Target: 12/day | F92: Target: 5/week | H92: Target: 2M SAR

Sheet Search
B2: 🔍 Search Engine
B4: 📅 SELECT PERIOD
B5: 📆 Date | C5: 📅 Week # | D5: 🗓️ Month | E5: 📊 Quarter
B6: 46144 | C6: =WEEKNUM(B6) -> 18 | D6: =MONTH(B6) -> 5 | E6: =ROUNDUP(MONTH(B6)/3,0) -> 2
B8: 📊 KPI DASHBOARD
B9: 🚗 F2F Visits (Daily) | C9: 📞 Calls (Daily) | D9: 🏢 New Accounts (Weekly) | E9: 💰 Quote Value (Weekly)
B10: =COUNTIFS('Master Report'!A:A,B6,'Master Report'!F:F,"F2F Meeting") -> 0 | C10: =COUNTIFS('Master Report'!A:A,B6,'Master Report'!F:F,"Call") -> 11 | D10: =COUNTIFS('Hot Leads'!H:H,">="&(B6-WEEKDAY(B6,2)+1),'Hot Leads'!H:H,"<="&B6) -> 26 | E10: =SUMIFS('Projects Follow UP'!O:O,'Projects Follow UP'!L:L,">="&(B6-WEEKDAY(B6,2)+1),'Projects Follow UP'!L:L,"<="&B6) -> 0
B11: Target: 3 | C11: Target: 12 | D11: Target: 5 | E11: Target: 2M SAR
B13: 📋 Tech Submittals (Monthly) | C13: 🔍 In-Hand Review (Monthly) | D13: 📝 Tender Review (Monthly) | E13: 🏆 Total Projects (Quarter)
B14: =COUNTIFS('Projects Follow UP'!L:L,">="&DATE(YEAR(B6),MONTH(B6),1),'Projects Follow UP'!L:L,"<="&EOMONTH(B6,0),'Projects Follow UP'!I:I,"*technical*") -> 0 | C14: =COUNTIFS('Projects Follow UP'!G:G,"In Hand") -> 16 | D14: =COUNTIFS('Projects Follow UP'!G:G,"Tender") -> 6 | E14: =COUNTIF('Projects Follow UP'!A5:A139,"<>") -> 135
B15: Target: 4 | C15: Target: 4 | D15: Target: 2 | E15: Pipeline Total
B17: 🔍 SEARCH ENGINE
B18: 🔎 Name / Company | C18: 📞 Phone Number | D18: 🏗️ Project Name | E18: 📍 Location
B19: sameh saber
B20: Search in: | C20: All
B22: 📋 Contact / Account RESULTS
B23: Name | C23: Company | D23: Phone | E23: Position / Status
B24: {=IFERROR( IF(B19<>"", _xlfn._xlws.FILTER(_xlfn.HSTACK('Hot Leads'!A:A,'Hot Leads'!C:C,'Hot Leads'!B:B,'Hot Leads'!G:G), (ISNUMBER(SEARCH(B19,'Hot Leads'!A:A))+ISNUMBER(SEARCH(B19,'Hot Leads'!C:C))) *('Hot Leads'!A:A<>"Name")*('Hot Leads'!A:A<>"")), IF(C19<>"", _xlfn._xlws.FILTER(_xlfn.HSTACK('Hot Leads'!A:A,'Hot Leads'!C:C,'Hot Leads'!B:B,'Hot Leads'!G:G), (ISNUMBER(SEARCH(C19,'Hot Leads'!B:B))) *('Hot Leads'!A:A<>"Name")*('Hot Leads'!A:A<>"")), IF(E19<>"", _xlfn._xlws.FILTER(_xlfn.HSTACK('Hot Leads'!A:A,'Hot Leads'!C:C,'Hot Leads'!B:B,'Hot Leads'!G:G), (ISNUMBER(SEARCH(E19,'Hot Leads'!E:E))) *('Hot Leads'!A:A<>"Name")*('Hot Leads'!A:A<>"")), "Enter search term above..."))), "No results found")} -> No results found
B36: 🏗️ PROJECT SEARCH
B37: Project # | C37: Opportunity | D37: Client Name | E37: Stage / Status
B38: {=IFERROR( IF(D19<>"", _xlfn._xlws.FILTER(_xlfn.HSTACK('Projects Follow UP'!A5:A139,'Projects Follow UP'!B5:B139,'Projects Follow UP'!C5:C139,'Projects Follow UP'!G5:G139), (ISNUMBER(SEARCH(D19,'Projects Follow UP'!B5:B139))+ISNUMBER(SEARCH(D19,'Projects Follow UP'!C5:C139))) *('Projects Follow UP'!A5:A139<>"")), IF(B19<>"", _xlfn._xlws.FILTER(_xlfn.HSTACK('Projects Follow UP'!A5:A139,'Projects Follow UP'!B5:B139,'Projects Follow UP'!C5:C139,'Projects Follow UP'!G5:G139), (ISNUMBER(SEARCH(B19,'Projects Follow UP'!C5:C139))+ISNUMBER(SEARCH(B19,'Projects Follow UP'!E5:E139))) *('Projects Follow UP'!A5:A139<>"")), IF(E19<>"", _xlfn._xlws.FILTER(_xlfn.HSTACK('Projects Follow UP'!A5:A139,'Projects Follow UP'!B5:B139,'Projects Follow UP'!C5:C139,'Projects Follow UP'!G5:G139), (ISNUMBER(SEARCH(E19,'Projects Follow UP'!H5:H139))) *('Projects Follow UP'!A5:A139<>"")), "Enter search term above..."))), "No projects found")} -> No projects found
B50: 📊 QUICK STATS & DATE RANGE
B51: ="Total: "&COUNTIF('Projects Follow UP'!A5:A139,"<>")&" Projects" -> Total: 135 Projects | C51: ="Hot Leads: "&COUNTIF('Hot Leads'!A2:A155,"<>") -> Hot Leads: 150 | D51: ="Pipeline: "&TEXT(SUM('Projects Follow UP'!O:O),"#,##0")&" SAR" -> Pipeline: 73,877,915 SAR | E51: ="Due Today: "&COUNTIFS('Hot Leads'!K:K,"<="&TODAY(),'Hot Leads'!K:K,"<>") -> Due Today: 0
B53: TECHNICAL SUBMITTALS TRACKER & SEARCH
B55: SEARCH BY PERIOD
B56: Week # | C56: Month | D56: Quarter | E56: Year
B57: 17 | C57: 4 | D57: 2 | E57: 2026
B59: SUBMITTALS COUNT RESULTS
B60: By Week | C60: By Month | D60: By Quarter | E60: By Year
B61: {=SUMPRODUCT((('Projects Follow UP'!$I$5:$I$139="Technical Submission")+('Projects Follow UP'!$I$5:$I$139="Technically Approved"))*(_xlfn.ISOWEEKNUM('Projects Follow UP'!$L$5:$L$139)=B57)*(YEAR('Projects Follow UP'!$L$5:$L$139)=E57))} -> 0 | C61: {=SUMPRODUCT((('Projects Follow UP'!$I$5:$I$139="Technical Submission")+('Projects Follow UP'!$I$5:$I$139="Technically Approved"))*(MONTH('Projects Follow UP'!$L$5:$L$139)=C57)*(YEAR('Projects Follow UP'!$L$5:$L$139)=E57))} -> 0 | D61: {=SUMPRODUCT((('Projects Follow UP'!$I$5:$I$139="Technical Submission")+('Projects Follow UP'!$I$5:$I$139="Technically Approved"))*(INT((MONTH('Projects Follow UP'!$L$5:$L$139)-1)/3)+1=D57)*(YEAR('Projects Follow UP'!$L$5:$L$139)=E57))} -> 0 | E61: {=SUMPRODUCT((('Projects Follow UP'!$I$5:$I$139="Technical Submission")+('Projects Follow UP'!$I$5:$I$139="Technically Approved"))*(YEAR('Projects Follow UP'!$L$5:$L$139)=E57))} -> 0
B63: OVERALL SUBMITTALS STATUS
B64: Tech Submission | C64: Tech Approved | D64: Total All Time | E64: Monthly Target
B65: =COUNTIF('Projects Follow UP'!$I:$I,"*Technical Submission*") -> 0 | C65: =COUNTIF('Projects Follow UP'!$I:$I,"*Technically Approved*") -> 0 | D65: =B65+C65 -> 0 | E65: 4
B67: Status: | C67: =IF(C61>=E65,"Target Met! ("&C61&"/"&E65&")","Need "&(E65-C61)&" more this month") -> Need 4 more this month
B69: TIP: Update Status in 'Projects Follow UP' (Col I) to 'Technical Submission' or 'Technically Approved' to track
B70: Current Status Values: Lost, Send to Client, RFQ Processing, Gather Information, Hold

Sheet Projects Follow UP
D1: No. In Hand Projects | E1: =COUNTIF(G5:G139, "In Hand") -> 16 | F1: Total Projects = | G1: =E1+E2 -> 22 | H1: Hit Rate % | I1: =COUNTIF(I5:I139, "Won") / COUNTA(I5:I139) -> 0 | J1: Total Amount | K1: =SUM(J5:J139) -> 73877915
D2: No. Tender Projects | E2: =COUNTIF(G5:G139, "Tender") -> 6
D3: Quality= | E3: =IF(COUNTIF(G5:G139,"In Hand")/(COUNTIF(G5:G139,"In Hand")+COUNTIF(G5:G139,"Tender"))>=0.7, "Excellent Quality ✅", IF(COUNTIF(G5:G139,"In Hand")/(COUNTIF(G5:G139,"In Hand")+COUNTIF(G5:G139,"Tender"))>=0.5, "Stable ⚖️", "Below Target ⚠️")) -> Excellent Quality ✅
A4: #PR | B4: Opportunity | C4: Client Name | D4: Client Phone Number | E4: Company Name | F4: Client Email | G4: Project Stage | H4: Project Location | I4: Status | J4: Est. value | K4: Action Done | L4: Action Date | M4: Follow Up | N4: Follow Up Date | O4: Est. value (SAR) | P4: Gone To Referral ? | Q4: Column1 | R4: Current Follow Up | S4: Current Follow Up Date
A5: PR1004 | B5: KIX Futsal Complex | C5: Mohamed Hanifa | D5: 966540654038 | E5: MHM | F5: hanifa@almagamsi.com | G5: Tender | H5: Jeddah | I5: Send to Client | J5: 337489 | K5: بعت للعميل التسعير و مستني الرد | L5: 46126 | M5: رقمه مغلق حاليا و بعتله واتساب | O5: =IFERROR(VALUE(SUBSTITUTE(TRIM(SUBSTITUTE(Projects_Follow_UP[[#This Row],[Est. value]],"SAR","")),",","")),0) -> 337489 | R5: {=_xlfn.LET(_xlpm.x,_xlfn.XLOOKUP(A5,Dashboard!$M$61:$M$72,Dashboard!$J$61:$J$72,""),IF(_xlpm.x<>"",_xlpm.x,M5))} -> رقمه مغلق حاليا و بعتله واتساب | S5: {=_xlfn.LET(_xlpm.x,_xlfn.XLOOKUP(A5,Dashboard!$M$61:$M$72,Dashboard!$K$61:$K$72,""),_xlpm.orig,N5,IF(_xlpm.x<>"",_xlpm.x,IF(OR(_xlpm.orig="",_xlpm.orig=0),"",_xlpm.orig)))}
A6: PR1007 | B6: International Medical Center IMC Obhur Hospital Project | C6: Omar Abdallah - Mazen Abdelghany | D6: 966549733284 - 966547160894 | E6: Alsaad - Vision | F6: faisal.skeik@alsaad.com.sa | G6: Tender | H6: Jeddah | I6: Send to Client | J6: 9619000 | K6: المشروع ده بقى Shortlisted على شركة السعد و شركة حسن علام ( و الي ماسك الباكدج بتاعتنا هو Vision ) و كمان شركة بس لسة مش عارف اسمها و حاليا احنا مستنيين نشوف هيرسى على مين و يبعتولنا Phase 2 ---- الشركات هي فريسينيه و حسن علام و السعد و ACC و اخر تقديم ليهم يوم الاحد | L6: 46132 | M6: No Updates | O6: =IFERROR(VALUE(SUBSTITUTE(TRIM(SUBSTITUTE(Projects_Follow_UP[[#This Row],[Est. value]],"SAR","")),",","")),0) -> 9619000 | R6: {=_xlfn.LET(_xlpm.x,_xlfn.XLOOKUP(A6,Dashboard!$M$61:$M$72,Dashboard!$J$61:$J$72,""),IF(_xlpm.x<>"",_xlpm.x,M6))} -> No Updates | S6: {=_xlfn.LET(_xlpm.x,_xlfn.XLOOKUP(A6,Dashboard!$M$61:$M$72,Dashboard!$K$61:$K$72,""),_xlpm.orig,N6,IF(_xlpm.x<>"",_xlpm.x,IF(OR(_xlpm.orig="",_xlpm.orig=0),"",_xlpm.orig)))} -> 46223
A7: PR1008 | B7: Alsalama Hospital | C7: Yasser Bahussin | D7: 966506694282 | E7: Alsalama Hospital | F7: yasser.bahussain@alsalamahospital.com | G7: In Hand | H7: Jeddah | I7: Send to Client | J7: 33000 | K7: عنده سيستم PA ببراند Honeywell Pava x618 و محتاج في ال announcement يكون بشكل معين بعت الحاجة لتيم التكنيكال و مستني منهم الرد | L7: 46132 | M7: مديره رجع بس لسة بيظبط الدنيا معاه و حددت معاه ميتنج الاسبوع الجي عشان اقعد انا و هو نتكلم في الاسعار | O7: =IFERROR(VALUE(SUBSTITUTE(TRIM(SUBSTITUTE(Projects_Follow_UP[[#This Row],[Est. value]],"SAR","")),",","")),0) -> 33000 | R7: {=_xlfn.LET(_xlpm.x,_xlfn.XLOOKUP(A7,Dashboard!$M$61:$M$72,Dashboard!$J$61:$J$72,""),IF(_xlpm.x<>"",_xlpm.x,M7))} -> مديره رجع بس لسة بيظبط الدنيا معاه و حددت معاه ميتنج الاسبوع الجي عشان اقعد انا و هو نتكلم في الاسعار | S7: {=_xlfn.LET(_xlpm.x,_xlfn.XLOOKUP(A7,Dashboard!$M$61:$M$72,Dashboard!$K$61:$K$72,""),_xlpm.orig,N7,IF(_xlpm.x<>"",_xlpm.x,IF(OR(_xlpm.orig="",_xlpm.orig=0),"",_xlpm.orig)))}
A8: PR1014 | B8: Zedca منافذ حدودية | C8: Omar Alsaad | D8: =_xlfn.XLOOKUP(Projects_Follow_UP[[#This Row],[Client Name]],'Hot Leads'!A:A,'Hot Leads'!B:B,0,0) -> 966549733284 | E8: =_xlfn.XLOOKUP(Projects_Follow_UP[[#This Row],[Client Phone Number]],'Hot Leads'!B:B,'Hot Leads'!C:C,0,0) -> Alsaad Contracting | F8: =_xlfn.XLOOKUP(Projects_Follow_UP[[#This Row],[Client Name]],'Hot Leads'!A:A,'Hot Leads'!F:F, ,0) -> omar.abdullah@alsaad.com.sa | G8: In Hand | H8: RedSea | I8: Gather Info. | K8: مشروع هيبقى مع الشركة دي قريب جدا و هيمضوا العقد المشروع ده بقاله سنتين و نص و لسة هيبدأوا شغل فيه الايام الجاية دي بس رتمه بطيئ شوية | L8: 46144 | M8: كلمته و قالي مفيش اي ابديت جديد لسة مستنيه لما يقولي اخر الابديت و كلمته تاني انهاردة بس لسة مردش | N8: 46160 | O8: =IFERROR(VALUE(SUBSTITUTE(TRIM(SUBSTITUTE(Projects_Follow_UP[[#This Row],[Est. value]],"SAR","")),",","")),0) -> 0 | R8: {=_xlfn.LET(_xlpm.x,_xlfn.XLOOKUP(A8,Dashboard!$M$61:$M$72,Dashboard!$J$61:$J$72,""),IF(_xlpm.x<>"",_xlpm.x,M8))} -> كلمته و قالي مفيش اي ابديت جديد لسة مستنيه لما يقولي اخر الابديت و كلمته تاني انهاردة بس لسة مردش | S8: {=_xlfn.LET(_xlpm.x,_xlfn.XLOOKUP(A8,Dashboard!$M$61:$M$72,Dashboard!$K$61:$K$72,""),_xlpm.orig,N8,IF(_xlpm.x<>"",_xlpm.x,IF(OR(_xlpm.orig="",_xlpm.orig=0),"",_xlpm.orig)))} -> 46160
A9: PR1015 | B9: Bab Al Khair Hospital Q4 | C9: Youssef Adwi | D9: =_xlfn.XLOOKUP(Projects_Follow_UP[[#This Row],[Client Name]],'Hot Leads'!A:A,'Hot Leads'!B:B,0,0) -> 966554711520 | E9: =_xlfn.XLOOKUP(Projects_Follow_UP[[#This Row],[Client Phone Number]],'Hot Leads'!B:B,'Hot Leads'!C:C,0,0) -> IHCC | F9: =_xlfn.XLOOKUP(Projects_Follow_UP[[#This Row],[Client Name]],'Hot Leads'!A:A,'Hot Leads'!F:F, ,0) -> y.adwi@ihcc.sa | G9: In Hand | H9: Makkah | I9: Send to Client | J9: 450000 | K9: مشروع خيري و المشروع هيروح للشركة الاقل سعر في كل حاجة | L9: 46146 | M9: المشروع حصل عليه Hold من SGH عشان البدجت مش مناسبة و لسة بيعملوا Value Engineering | O9: =IFERROR(VALUE(SUBSTITUTE(TRIM(SUBSTITUTE(Projects_Follow_UP[[#This Row],[Est. value]],"SAR","")),",","")),0) -> 450000 | R9: {=_xlfn.LET(_xlpm.x,_xlfn.XLOOKUP(A9,Dashboard!$M$61:$M$72,Dashboard!$J$61:$J$72,""),IF(_xlpm.x<>"",_xlpm.x,M9))} -> المشروع حصل عليه Hold من SGH عشان البدجت مش مناسبة و لسة بيعملوا Value Engineering | S9: {=_xlfn.LET(_xlpm.x,_xlfn.XLOOKUP(A9,Dashboard!$M$61:$M$72,Dashboard!$K$61:$K$72,""),_xlpm.orig,N9,IF(_xlpm.x<>"",_xlpm.x,IF(OR(_xlpm.orig="",_xlpm.orig=0),"",_xlpm.orig)))}
A10: PR1016 | B10: Mini Market in KAUST Q4 | C10: Omar El Hanoun | D10: =_xlfn.XLOOKUP(Projects_Follow_UP[[#This Row],[Client Name]],'Hot Leads'!A:A,'Hot Leads'!B:B,0,0) -> 966531895117 | E10: =_xlfn.XLOOKUP(Projects_Follow_UP[[#This Row],[Client Phone Number]],'Hot Leads'!B:B,'Hot Leads'!C:C,0,0) -> MACC | F10: =_xlfn.XLOOKUP(Projects_Follow_UP[[#This Row],[Client Name]],'Hot Leads'!A:A,'Hot Leads'!F:F, ,0) -> omer.elhanoun@macc-fm.com | G10: In Hand | H10: Jeddah | I10: Send to Client | J10: 95000 | K10: مشروع مهم MACC و محتاجين فيه FA و يكون فيه امكانيه انه يتربط على ال KAUST في المستقبل | L10: 46147 | M10: اتصلت بيه اكتر من مره و لسة مردش | O10: =IFERROR(VALUE(SUBSTITUTE(TRIM(SUBSTITUTE(Projects_Follow_UP[[#This Row],[Est. value]],"SAR","")),",","")),0) -> 95000 | R10: {=_xlfn.LET(_xlpm.x,_xlfn.XLOOKUP(A10,Dashboard!$M$61:$M$72,Dashboard!$J$61:$J$72,""),IF(_xlpm.x<>"",_xlpm.x,M10))} -> اتصلت بيه اكتر من مره و لسة مردش | S10: {=_xlfn.LET(_xlpm.x,_xlfn.XLOOKUP(A10,Dashboard!$M$61:$M$72,Dashboard!$K$61:$K$72,""),_xlpm.orig,N10,IF(_xlpm.x<>"",_xlpm.x,IF(OR(_xlpm.orig="",_xlpm.orig=0),"",_xlpm.orig)))} -> 46223
A11: PR1017 | B11: Al-Mukhmal Resort | C11: Omar Alsaad | D11: =_xlfn.XLOOKUP(Projects_Follow_UP[[#This Row],[Client Name]],'Hot Leads'!A:A,'Hot Leads'!B:B,0,0) -> 966549733284 | E11: =_xlfn.XLOOKUP(Projects_Follow_UP[[#This Row],[Client Phone Number]],'Hot Leads'!B:B,'Hot Leads'!C:C,0,0) -> Alsaad Contracting | F11: =_xlfn.XLOOKUP(Projects_Follow_UP[[#This Row],[Client Name]],'Hot Leads'!A:A,'Hot Leads'!F:F, ,0) -> omar.abdullah@alsaad.com.sa | G11: Tender | H11: Jeddah | I11: Hold | K11: مستني المشروعات التانيه تخلص عشان نخش في المشروع بس لما يرد عليا الاول اصلا | L11: 46147 | M11: لسة مفيش جديد عامله هول عشان عمر نفسه مش بيرد عليا لسة اول ما يرد كمل تسعير فالمشروع بلص ان مفيش تشانيل اصلا | N11: 46156 | O11: =IFERROR(VALUE(SUBSTITUTE(TRIM(SUBSTITUTE(Projects_Follow_UP[[#This Row],[Est. value]],"SAR","")),",","")),0) -> 0 | R11: {=_xlfn.LET(_xlpm.x,_xlfn.XLOOKUP(A11,Dashboard!$M$61:$M$72,Dashboard!$J$61:$J$72,""),IF(_xlpm.x<>"",_xlpm.x,M11))} -> لسة مفيش جديد عامله هول عشان عمر نفسه مش بيرد عليا لسة اول ما يرد كمل تسعير فالمشروع بلص ان مفيش تشانيل اصلا | S11: {=_xlfn.LET(_xlpm.x,_xlfn.XLOOKUP(A11,Dashboard!$M$61:$M$72,Dashboard!$K$61:$K$72,""),_xlpm.orig,N11,IF(_xlpm.x<>"",_xlpm.x,IF(OR(_xlpm.orig="",_xlpm.orig=0),"",_xlpm.orig)))} -> 46156
A12: PR1018 | B12: Rosemond Hotel | C12: Khaled Hussain | D12: =_xlfn.XLOOKUP(Projects_Follow_UP[[#This Row],[Client Name]],'Hot Leads'!A:A,'Hot Leads'!B:B,0,0) -> 966537929837 | E12: =_xlfn.XLOOKUP(Projects_Follow_UP[[#This Row],[Client Phone Number]],'Hot Leads'!B:B,'Hot Leads'!C:C,0,0) -> Creet | F12: =_xlfn.XLOOKUP(Projects_Follow_UP[[#This Row],[Client Name]],'Hot Leads'!A:A,'Hot Leads'!F:F, ,0) -> 0 | G12: In Hand | H12: Jeddah | I12: Lost | J12: 2490000 | K12: المشروع ده من خالد نفسه الي شغال جوه شركة كريت و عاوز يخلصه من بره بره و نطلعله عمولته المشروع ده مش مع Creet ده مع خالد نفسه بس | L12: 46148 | M12: المشروع هيخلص اقصى حاجة يوم السبت و المشروع ده مهم جدا لابعد حد عشان نقدر ناخد الباكدج كاملة | N12: 46151 | O12: =IFERROR(VALUE(SUBSTITUTE(TRIM(SUBSTITUTE(Projects_Follow_UP[[#This Row],[Est. value]],"SAR","")),",","")),0) -> 2490000 | R12: {=_xlfn.LET(_xlpm.x,_xlfn.XLOOKUP(A12,Dashboard!$M$61:$M$72,Dashboard!$J$61:$J$72,""),IF(_xlpm.x<>"",_xlpm.x,M12))} -> المشروع هيخلص اقصى حاجة يوم السبت و المشروع ده مهم جدا لابعد حد عشان نقدر ناخد الباكدج كاملة | S12: {=_xlfn.LET(_xlpm.x,_xlfn.XLOOKUP(A12,Dashboard!$M$61:$M$72,Dashboard!$K$61:$K$72,""),_xlpm.orig,N12,IF(_xlpm.x<>"",_xlpm.x,IF(OR(_xlpm.orig="",_xlpm.orig=0),"",_xlpm.orig)))} -> 46389
A13: PR1021 | B13: GRC Villas | C13: Ehab GRC | D13: =_xlfn.XLOOKUP(Projects_Follow_UP[[#This Row],[Client Name]],'Hot Leads'!A:A,'Hot Leads'!B:B,0,0) -> 966582792050 | E13: =_xlfn.XLOOKUP(Projects_Follow_UP[[#This Row],[Client Phone Number]],'Hot Leads'!B:B,'Hot Leads'!C:C,0,0) -> GRC | F13: =_xlfn.XLOOKUP(Projects_Follow_UP[[#This Row],[Client Name]],'Hot Leads'!A:A,'Hot Leads'!F:F, ,0) -> 0 | G13: In Hand | H13: Riyadh | I13: Send to Client | J13: 206000 | K13: المشروع اتقسم بيني و بين عبدالرحمن و الكوتيشن طلعت و بعتناها للراجل | L13: 46148 | M13: قالي انه عامل للمشاريع هولد و مستني يفضى عشان يقارن الاسعار الي بعتنهاله | O13: =IFERROR(VALUE(SUBSTITUTE(TRIM(SUBSTITUTE(Projects_Follow_UP[[#This Row],[Est. value]],"SAR","")),",","")),0) -> 206000 | R13: {=_xlfn.LET(_xlpm.x,_xlfn.XLOOKUP(A13,Dashboard!$M$61:$M$72,Dashboard!$J$61:$J$72,""),IF(_xlpm.x<>"",_xlpm.x,M13))} -> قالي انه عامل للمشاريع هولد و مستني يفضى عشان يقارن الاسعار الي بعتنهاله | S13: {=_xlfn.LET(_xlpm.x,_xlfn.XLOOKUP(A13,Dashboard!$M$61:$M$72,Dashboard!$K$61:$K$72,""),_xlpm.orig,N13,IF(_xlpm.x<>"",_xlpm.x,IF(OR(_xlpm.orig="",_xlpm.orig=0),"",_xlpm.orig)))} -> 46231
A14: PR1022 | B14: Qiddya Project | C14: Ehab GRC | D14: =_xlfn.XLOOKUP(Projects_Follow_UP[[#This Row],[Client Name]],'Hot Leads'!A:A,'Hot Leads'!B:B,0,0) -> 966582792050 | E14: =_xlfn.XLOOKUP(Projects_Follow_UP[[#This Row],[Client Phone Number]],'Hot Leads'!B:B,'Hot Leads'!C:C,0,0) -> GRC | F14: =_xlfn.XLOOKUP(Projects_Follow_UP[[#This Row],[Client Name]],'Hot Leads'!A:A,'Hot Leads'!F:F, ,0) -> 0 | G14: In Hand | H14: Riyadh | I14: Send to Client | J14: 220000 | K14: المشروع مع نفس الراجل مكتبه في جدة و مكان المشروع في الرياض و شغالين عليه انا و عبدالرحمن | L14: 46148 | M14: قالي انه عامل للمشاريع هولد و مستني يفضى عشان يقارن الاسعار الي بعتنهاله | O14: =IFERROR(VALUE(SUBSTITUTE(TRIM(SUBSTITUTE(Projects_Follow_UP[[#This Row],[Est. value]],"SAR","")),",","")),0) -> 220000 | R14: {=_xlfn.LET(_xlpm.x,_xlfn.XLOOKUP(A14,Dashboard!$M$61:$M$72,Dashboard!$J$61:$J$72,""),IF(_xlpm.x<>"",_xlpm.x,M14))} -> قالي انه عامل للمشاريع هولد و مستني يفضى عشان يقارن الاسعار الي بعتنهاله | S14: {=_xlfn.LET(_xlpm.x,_xlfn.XLOOKUP(A14,Dashboard!$M$61:$M$72,Dashboard!$K$61:$K$72,""),_xlpm.orig,N14,IF(_xlpm.x<>"",_xlpm.x,IF(OR(_xlpm.orig="",_xlpm.orig=0),"",_xlpm.orig)))} -> 46231
A15: PR1023 | B15: Sukoon Care Hospital | C15: Ayman Aburub | D15: =_xlfn.XLOOKUP(Projects_Follow_UP[[#This Row],[Client Name]],'Hot Leads'!A:A,'Hot Leads'!B:B,0,0) -> 966581469699 | E15: =_xlfn.XLOOKUP(Projects_Follow_UP[[#This Row],[Client Phone Number]],'Hot Leads'!B:B,'Hot Leads'!C:C,0,0) -> KFOCO | F15: =_xlfn.XLOOKUP(Projects_Follow_UP[[#This Row],[Client Name]],'Hot Leads'!A:A,'Hot Leads'!F:F, ,0) -> ak@kfoco.com | G15: In Hand | H15: Jeddah | I15: Gather Info. | K15: المشروع لسة الداتا بتاعته مع مهندس عبدالرحمن القفاص لسة مستنيه يبعتهالي و المشروع ده مع صاحب المهندس عبدرالحمن و هيبعتلي التفاصيل و كده هو مش مع ايمن الي انت كاتبه | L15: 46153 | M15: اتواصل مع ايمن شوف المشاريع الجديدة الي معاه | N15: 46158 | O15: =IFERROR(VALUE(SUBSTITUTE(TRIM(SUBSTITUTE(Projects_Follow_UP[[#This Row],[Est. value]],"SAR","")),",","")),0) -> 0 | R15: {=_xlfn.LET(_xlpm.x,_xlfn.XLOOKUP(A15,Dashboard!$M$61:$M$72,Dashboard!$J$61:$J$72,""),IF(_xlpm.x<>"",_xlpm.x,M15))} -> اتواصل مع ايمن شوف المشاريع الجديدة الي معاه | S15: {=_xlfn.LET(_xlpm.x,_xlfn.XLOOKUP(A15,Dashboard!$M$61:$M$72,Dashboard!$K$61:$K$72,""),_xlpm.orig,N15,IF(_xlpm.x<>"",_xlpm.x,IF(OR(_xlpm.orig="",_xlpm.orig=0),"",_xlpm.orig)))} -> 46158
A16: PR1025 | B16: MARAFY ALAROUS Roshan Group | C16: Helmy Abdelrazeq | D16: =_xlfn.XLOOKUP(Projects_Follow_UP[[#This Row],[Client Name]],'Hot Leads'!A:A,'Hot Leads'!B:B,0,0) -> 966560374964 | E16: =_xlfn.XLOOKUP(Projects_Follow_UP[[#This Row],[Client Phone Number]],'Hot Leads'!B:B,'Hot Leads'!C:C,0,0) -> AlShamela | F16: =_xlfn.XLOOKUP(Projects_Follow_UP[[#This Row],[Client Name]],'Hot Leads'!A:A,'Hot Leads'!F:F, ,0) -> hemlyac@alshamela.com.sa | G16: Tender | H16: Jeddah | I16: Send to Client | J16: 27765033 | K16: بعتنا الكوتيشن يوم 12/8 | L16: 46223 | M16: هتابع مع العميل | N16: 46250 | O16: =IFERROR(VALUE(SUBSTITUTE(TRIM(SUBSTITUTE(Projects_Follow_UP[[#This Row],[Est. value]],"SAR","")),",","")),0) -> 27765033 | R16: {=_xlfn.LET(_xlpm.x,_xlfn.XLOOKUP(A16,Dashboard!$M$61:$M$72,Dashboard!$J$61:$J$72,""),IF(_xlpm.x<>"",_xlpm.x,M16))} -> QT | S16: {=_xlfn.LET(_xlpm.x,_xlfn.XLOOKUP(A16,Dashboard!$M$61:$M$72,Dashboard!$K$61:$K$72,""),_xlpm.orig,N16,IF(_xlpm.x<>"",_xlpm.x,IF(OR(_xlpm.orig="",_xlpm.orig=0),"",_xlpm.orig)))} -> 46231
A17: PR1027 | B17: مبنى الهيئة العامة | C17: Abdelaziz Hassan | D17: =_xlfn.XLOOKUP(Projects_Follow_UP[[#This Row],[Client Name]],'Hot Leads'!A:A,'Hot Leads'!B:B,0,0) -> 966592851015 | E17: =_xlfn.XLOOKUP(Projects_Follow_UP[[#This Row],[Client Phone Number]],'Hot Leads'!B:B,'Hot Leads'!C:C,0,0) -> MAG المجال العربي | F17: =_xlfn.XLOOKUP(Projects_Follow_UP[[#This Row],[Client Name]],'Hot Leads'!A:A,'Hot Leads'!F:F, ,0) -> a.alessa@mag-sa.com | G17: In Hand | H17: Makkah | I17: Send to Client | J17: 47000 | K17: بعتهاله و بحاول اظبط معاه ميتنج بس هو مشغول جدا هروحله اول الاسبوع الجي | L17: 46223 | M17: QT | N17: 46228 | O17: =IFERROR(VALUE(SUBSTITUTE(TRIM(SUBSTITUTE(Projects_Follow_UP[[#This Row],[Est. value]],"SAR","")),",","")),0) -> 47000 | R17: {=_xlfn.LET(_xlpm.x,_xlfn.XLOOKUP(A17,Dashboard!$M$61:$M$72,Dashboard!$J$61:$J$72,""),IF(_xlpm.x<>"",_xlpm.x,M17))} -> QT | S17: {=_xlfn.LET(_xlpm.x,_xlfn.XLOOKUP(A17,Dashboard!$M$61:$M$72,Dashboard!$K$61:$K$72,""),_xlpm.orig,N17,IF(_xlpm.x<>"",_xlpm.x,IF(OR(_xlpm.orig="",_xlpm.orig=0),"",_xlpm.orig)))} -> 46228
A18: PR1029 | B18: BOULEVARD RESIDENTIAL | C18: Youssef Adwi | D18: =_xlfn.XLOOKUP(Projects_Follow_UP[[#This Row],[Client Name]],'Hot Leads'!A:A,'Hot Leads'!B:B,0,0) -> 966554711520 | E18: =_xlfn.XLOOKUP(Projects_Follow_UP[[#This Row],[Client Phone Number]],'Hot Leads'!B:B,'Hot Leads'!C:C,0,0) -> IHCC | F18: =_xlfn.XLOOKUP(Projects_Follow_UP[[#This Row],[Client Name]],'Hot Leads'!A:A,'Hot Leads'!F:F, ,0) -> y.adwi@ihcc.sa | G18: Tender | H18: Riyadh | I18: RFQ Processing | J18: 1209293 | K18: مستني رده لسة المشروع تندر | L18: 46226 | M18: مستني باقي الكوتيشن | N18: 46257 | O18: =IFERROR(VALUE(SUBSTITUTE(TRIM(SUBSTITUTE(Projects_Follow_UP[[#This Row],[Est. value]],"SAR","")),",","")),0) -> 1209293 | R18: {=_xlfn.LET(_xlpm.x,_xlfn.XLOOKUP(A18,Dashboard!$M$61:$M$72,Dashboard!$J$61:$J$72,""),IF(_xlpm.x<>"",_xlpm.x,M18))} -> QT | S18: {=_xlfn.LET(_xlpm.x,_xlfn.XLOOKUP(A18,Dashboard!$M$61:$M$72,Dashboard!$K$61:$K$72,""),_xlpm.orig,N18,IF(_xlpm.x<>"",_xlpm.x,IF(OR(_xlpm.orig="",_xlpm.orig=0),"",_xlpm.orig)))} -> 46235
A19: PR1030 | B19: مشروع تيسر | C19: Mohamed Abdelatif | D19: =_xlfn.XLOOKUP(Projects_Follow_UP[[#This Row],[Client Name]],'Hot Leads'!A:A,'Hot Leads'!B:B,0,0) -> 966545150782 | E19: =_xlfn.XLOOKUP(Projects_Follow_UP[[#This Row],[Client Phone Number]],'Hot Leads'!B:B,'Hot Leads'!C:C,0,0) -> تيسر للتجارة | F19: =_xlfn.XLOOKUP(Projects_Follow_UP[[#This Row],[Client Name]],'Hot Leads'!A:A,'Hot Leads'!F:F, ,0) -> 0 | G19: In Hand | H19: Makkah | I19: Send to Client | J19: 5400000 | K19: هنغير الباكدج بتاعت المشروع و لسة مستنيها | L19: 46231 | M19: QT | N19: 46257 | O19: =IFERROR(VALUE(SUBSTITUTE(TRIM(SUBSTITUTE(Projects_Follow_UP[[#This Row],[Est. value]],"SAR","")),",","")),0) -> 5400000 | R19: {=_xlfn.LET(_xlpm.x,_xlfn.XLOOKUP(A19,Dashboard!$M$61:$M$72,Dashboard!$J$61:$J$72,""),IF(_xlpm.x<>"",_xlpm.x,M19))} -> QT | S19: {=_xlfn.LET(_xlpm.x,_xlfn.XLOOKUP(A19,Dashboard!$M$61:$M$72,Dashboard!$K$61:$K$72,""),_xlpm.orig,N19,IF(_xlpm.x<>"",_xlpm.x,IF(OR(_xlpm.orig="",_xlpm.orig=0),"",_xlpm.orig)))} -> 46229
A20: PR1031 | B20: Bn Dawood Al-Hamrah | C20: Mohamed | D20: =_xlfn.XLOOKUP(Projects_Follow_UP[[#This Row],[Client Name]],'Hot Leads'!A:A,'Hot Leads'!B:B,0,0) -> 966500810545 | E20: =_xlfn.XLOOKUP(Projects_Follow_UP[[#This Row],[Client Phone Number]],'Hot Leads'!B:B,'Hot Leads'!C:C,0,0) -> سعود الصاعدي | F20: =_xlfn.XLOOKUP(Projects_Follow_UP[[#This Row],[Client Name]],'Hot Leads'!A:A,'Hot Leads'!F:F, ,0) -> 0 | G20: In Hand | H20: Makkah | I20: RFQ Processing | K20: لسة شغالين عليه | L20: 46236 | M20: QT | N20: 46243 | O20: =IFERROR(VALUE(SUBSTITUTE(TRIM(SUBSTITUTE(Projects_Follow_UP[[#This Row],[Est. value]],"SAR","")),",","")),0) -> 0 | R20: {=_xlfn.LET(_xlpm.x,_xlfn.XLOOKUP(A20,Dashboard!$M$61:$M$72,Dashboard!$J$61:$J$72,""),IF(_xlpm.x<>"",_xlpm.x,M20))} -> QT | S20: {=_xlfn.LET(_xlpm.x,_xlfn.XLOOKUP(A20,Dashboard!$M$61:$M$72,Dashboard!$K$61:$K$72,""),_xlpm.orig,N20,IF(_xlpm.x<>"",_xlpm.x,IF(OR(_xlpm.orig="",_xlpm.orig=0),"",_xlpm.orig)))} -> 46243
A21: PR1034 | B21: MIRAF ONE | C21: Othman Mohamed | D21: =_xlfn.XLOOKUP(Projects_Follow_UP[[#This Row],[Client Name]],'Hot Leads'!A:A,'Hot Leads'!B:B,0,0) -> 966537964254 | E21: =_xlfn.XLOOKUP(Projects_Follow_UP[[#This Row],[Client Phone Number]],'Hot Leads'!B:B,'Hot Leads'!C:C,0,0) -> EMCO TECH Buna Sister Company | F21: =_xlfn.XLOOKUP(Projects_Follow_UP[[#This Row],[Client Name]],'Hot Leads'!A:A,'Hot Leads'!F:F, ,0) -> 0 | G21: In Hand | H21: Khobar | I21: Send to Client | J21: 8836100 | K21: اتكلمت مع امه لا اله الا الله و مفيش حد فيهم بيدي اي معلومة | L21: 46243 | M21: كلمت مهندس محمد عشان اتابع معاه | N21: 46267 | O21: =IFERROR(VALUE(SUBSTITUTE(TRIM(SUBSTITUTE(Projects_Follow_UP[[#This Row],[Est. value]],"SAR","")),",","")),0) -> 8836100 | R21: {=_xlfn.LET(_xlpm.x,_xlfn.XLOOKUP(A21,Dashboard!$M$61:$M$72,Dashboard!$J$61:$J$72,""),IF(_xlpm.x<>"",_xlpm.x,M21))} -> كلمت مهندس محمد عشان اتابع معاه | S21: {=_xlfn.LET(_xlpm.x,_xlfn.XLOOKUP(A21,Dashboard!$M$61:$M$72,Dashboard!$K$61:$K$72,""),_xlpm.orig,N21,IF(_xlpm.x<>"",_xlpm.x,IF(OR(_xlpm.orig="",_xlpm.orig=0),"",_xlpm.orig)))} -> 46267
A22: PR1036 | B22: Marriot Jeddah | D22: =_xlfn.XLOOKUP(Projects_Follow_UP[[#This Row],[Client Name]],'Hot Leads'!A:A,'Hot Leads'!B:B,0,0) -> 0 | E22: =_xlfn.XLOOKUP(Projects_Follow_UP[[#This Row],[Client Phone Number]],'Hot Leads'!B:B,'Hot Leads'!C:C,0,0) -> 0 | F22: =_xlfn.XLOOKUP(Projects_Follow_UP[[#This Row],[Client Name]],'Hot Leads'!A:A,'Hot Leads'!F:F, ,0) -> 0 | O22: =IFERROR(VALUE(SUBSTITUTE(TRIM(SUBSTITUTE(Projects_Follow_UP[[#This Row],[Est. value]],"SAR","")),",","")),0) -> 0 | R22: {=_xlfn.LET(_xlpm.x,_xlfn.XLOOKUP(A22,Dashboard!$M$61:$M$72,Dashboard!$J$61:$J$72,""),IF(_xlpm.x<>"",_xlpm.x,M22))} -> 0 | S22: {=_xlfn.LET(_xlpm.x,_xlfn.XLOOKUP(A22,Dashboard!$M$61:$M$72,Dashboard!$K$61:$K$72,""),_xlpm.orig,N22,IF(_xlpm.x<>"",_xlpm.x,IF(OR(_xlpm.orig="",_xlpm.orig=0),"",_xlpm.orig)))}
A23: PR1037 | B23: RUA Al Madinah Superblock 5 | C23: Mazen Vision | D23: =_xlfn.XLOOKUP(Projects_Follow_UP[[#This Row],[Client Name]],'Hot Leads'!A:A,'Hot Leads'!B:B,0,0) -> 966547160894 | E23: =_xlfn.XLOOKUP(Projects_Follow_UP[[#This Row],[Client Phone Number]],'Hot Leads'!B:B,'Hot Leads'!C:C,0,0) -> Vision Contracting | F23: =_xlfn.XLOOKUP(Projects_Follow_UP[[#This Row],[Client Name]],'Hot Leads'!A:A,'Hot Leads'!F:F, ,0) -> m.hassan@vision-cc.com | G23: Tender | H23: Riyadh | I23: RFQ Processing | J23: 16000000 | K23: مخلصين بس ال BMS و ال Lighting Control ب 16 مليون والباقي ميار شغاله عليه لسة | O23: =IFERROR(VALUE(SUBSTITUTE(TRIM(SUBSTITUTE(Projects_Follow_UP[[#This Row],[Est. value]],"SAR","")),",","")),0) -> 16000000 | R23: {=_xlfn.LET(_xlpm.x,_xlfn.XLOOKUP(A23,Dashboard!$M$61:$M$72,Dashboard!$J$61:$J$72,""),IF(_xlpm.x<>"",_xlpm.x,M23))} -> 0 | S23: {=_xlfn.LET(_xlpm.x,_xlfn.XLOOKUP(A23,Dashboard!$M$61:$M$72,Dashboard!$K$61:$K$72,""),_xlpm.orig,N23,IF(_xlpm.x<>"",_xlpm.x,IF(OR(_xlpm.orig="",_xlpm.orig=0),"",_xlpm.orig)))}
A24: PR1038 | B24: Roya Al Haram | D24: =_xlfn.XLOOKUP(Projects_Follow_UP[[#This Row],[Client Name]],'Hot Leads'!A:A,'Hot Leads'!B:B,0,0) -> 0 | E24: =_xlfn.XLOOKUP(Projects_Follow_UP[[#This Row],[Client Phone Number]],'Hot Leads'!B:B,'Hot Leads'!C:C,0,0) -> 0 | F24: =_xlfn.XLOOKUP(Projects_Follow_UP[[#This Row],[Client Name]],'Hot Leads'!A:A,'Hot Leads'!F:F, ,0) -> 0 | G24: In Hand | H24: Makkah | I24: RFQ Processing | J24: 950000 | K24: ال Lighting Control خلص و ال BMS خلص -- Send | L24: 46260 | O24: =IFERROR(VALUE(SUBSTITUTE(TRIM(SUBSTITUTE(Projects_Follow_UP[[#This Row],[Est. value]],"SAR","")),",","")),0) -> 950000 | R24: {=_xlfn.LET(_xlpm.x,_xlfn.XLOOKUP(A24,Dashboard!$M$61:$M$72,Dashboard!$J$61:$J$72,""),IF(_xlpm.x<>"",_xlpm.x,M24))} -> 0 | S24: {=_xlfn.LET(_xlpm.x,_xlfn.XLOOKUP(A24,Dashboard!$M$61:$M$72,Dashboard!$K$61:$K$72,""),_xlpm.orig,N24,IF(_xlpm.x<>"",_xlpm.x,IF(OR(_xlpm.orig="",_xlpm.orig=0),"",_xlpm.orig)))}
A25: PR1039 | B25: Almoosa Schools | C25: Eslam Abo Elezz | D25: =_xlfn.XLOOKUP(Projects_Follow_UP[[#This Row],[Client Name]],'Hot Leads'!A:A,'Hot Leads'!B:B,0,0) -> 966595291415 | E25: =_xlfn.XLOOKUP(Projects_Follow_UP[[#This Row],[Client Phone Number]],'Hot Leads'!B:B,'Hot Leads'!C:C,0,0) -> Albadayeel البدائل | F25: =_xlfn.XLOOKUP(Projects_Follow_UP[[#This Row],[Client Name]],'Hot Leads'!A:A,'Hot Leads'!F:F, ,0) -> 0 | K25: حصل فيه كتير جدا جدا | O25: =IFERROR(VALUE(SUBSTITUTE(TRIM(SUBSTITUTE(Projects_Follow_UP[[#This Row],[Est. value]],"SAR","")),",","")),0) -> 0 | R25: {=_xlfn.LET(_xlpm.x,_xlfn.XLOOKUP(A25,Dashboard!$M$61:$M$72,Dashboard!$J$61:$J$72,""),IF(_xlpm.x<>"",_xlpm.x,M25))} -> 0 | S25: {=_xlfn.LET(_xlpm.x,_xlfn.XLOOKUP(A25,Dashboard!$M$61:$M$72,Dashboard!$K$61:$K$72,""),_xlpm.orig,N25,IF(_xlpm.x<>"",_xlpm.x,IF(OR(_xlpm.orig="",_xlpm.orig=0),"",_xlpm.orig)))}
A26: PR1040 | B26: رابطة العالم الاسلامي | C26: Omar Albatal | D26: =_xlfn.XLOOKUP(Projects_Follow_UP[[#This Row],[Client Name]],'Hot Leads'!A:A,'Hot Leads'!B:B,0,0) -> 966503355231 | E26: =_xlfn.XLOOKUP(Projects_Follow_UP[[#This Row],[Client Phone Number]],'Hot Leads'!B:B,'Hot Leads'!C:C,0,0) -> Al-Waref Contracting Comapny | F26: =_xlfn.XLOOKUP(Projects_Follow_UP[[#This Row],[Client Name]],'Hot Leads'!A:A,'Hot Leads'!F:F, ,0) -> 0 | G26: In Hand | H26: Makkah | I26: RFQ Processing | K26: شغالين على ال BMS و ال PA , CCTV , Passive , | O26: =IFERROR(VALUE(SUBSTITUTE(TRIM(SUBSTITUTE(Projects_Follow_UP[[#This Row],[Est. value]],"SAR","")),",","")),0) -> 0 | R26: {=_xlfn.LET(_xlpm.x,_xlfn.XLOOKUP(A26,Dashboard!$M$61:$M$72,Dashboard!$J$61:$J$72,""),IF(_xlpm.x<>"",_xlpm.x,M26))} -> 0 | S26: {=_xlfn.LET(_xlpm.x,_xlfn.XLOOKUP(A26,Dashboard!$M$61:$M$72,Dashboard!$K$61:$K$72,""),_xlpm.orig,N26,IF(_xlpm.x<>"",_xlpm.x,IF(OR(_xlpm.orig="",_xlpm.orig=0),"",_xlpm.orig)))}
A27: PR1041 | B27: WATCO Madina | D27: =_xlfn.XLOOKUP(Projects_Follow_UP[[#This Row],[Client Name]],'Hot Leads'!A:A,'Hot Leads'!B:B,0,0) -> 0 | E27: =_xlfn.XLOOKUP(Projects_Follow_UP[[#This Row],[Client Phone Number]],'Hot Leads'!B:B,'Hot Leads'!C:C,0,0) -> 0 | F27: =_xlfn.XLOOKUP(Projects_Follow_UP[[#This Row],[Client Name]],'Hot Leads'!A:A,'Hot Leads'!F:F, ,0) -> 0 | O27: =IFERROR(VALUE(SUBSTITUTE(TRIM(SUBSTITUTE(Projects_Follow_UP[[#This Row],[Est. value]],"SAR","")),",","")),0) -> 0 | R27: {=_xlfn.LET(_xlpm.x,_xlfn.XLOOKUP(A27,Dashboard!$M$61:$M$72,Dashboard!$J$61:$J$72,""),IF(_xlpm.x<>"",_xlpm.x,M27))} -> 0 | S27: {=_xlfn.LET(_xlpm.x,_xlfn.XLOOKUP(A27,Dashboard!$M$61:$M$72,Dashboard!$K$61:$K$72,""),_xlpm.orig,N27,IF(_xlpm.x<>"",_xlpm.x,IF(OR(_xlpm.orig="",_xlpm.orig=0),"",_xlpm.orig)))}
A28: PR1042 | B28: Caterion CLA | D28: =_xlfn.XLOOKUP(Projects_Follow_UP[[#This Row],[Client Name]],'Hot Leads'!A:A,'Hot Leads'!B:B,0,0) -> 0 | E28: =_xlfn.XLOOKUP(Projects_Follow_UP[[#This Row],[Client Phone Number]],'Hot Leads'!B:B,'Hot Leads'!C:C,0,0) -> 0 | F28: =_xlfn.XLOOKUP(Projects_Follow_UP[[#This Row],[Client Name]],'Hot Leads'!A:A,'Hot Leads'!F:F, ,0) -> 0 | O28: =IFERROR(VALUE(SUBSTITUTE(TRIM(SUBSTITUTE(Projects_Follow_UP[[#This Row],[Est. value]],"SAR","")),",","")),0) -> 0 | R28: {=_xlfn.LET(_xlpm.x,_xlfn.XLOOKUP(A28,Dashboard!$M$61:$M$72,Dashboard!$J$61:$J$72,""),IF(_xlpm.x<>"",_xlpm.x,M28))} -> 0 | S28: {=_xlfn.LET(_xlpm.x,_xlfn.XLOOKUP(A28,Dashboard!$M$61:$M$72,Dashboard!$K$61:$K$72,""),_xlpm.orig,N28,IF(_xlpm.x<>"",_xlpm.x,IF(OR(_xlpm.orig="",_xlpm.orig=0),"",_xlpm.orig)))}
A29: PR1043 | B29: Al- TAhliyah Business Park | C29: Salman MEP Manager | D29: =_xlfn.XLOOKUP(Projects_Follow_UP[[#This Row],[Client Name]],'Hot Leads'!A:A,'Hot Leads'!B:B,0,0) -> 966572572847 | E29: =_xlfn.XLOOKUP(Projects_Follow_UP[[#This Row],[Client Phone Number]],'Hot Leads'!B:B,'Hot Leads'!C:C,0,0) -> BAK United Arabia | F29: =_xlfn.XLOOKUP(Projects_Follow_UP[[#This Row],[Client Name]],'Hot Leads'!A:A,'Hot Leads'!F:F, ,0) -> salmanshah@bakunited.sa | G29: In Hand | H29: Jeddah | I29: Negotiation | J29: 220000 | K29: مستني ابعتله سعر كوتيشن بوش عشان هو لازم يكون معاه 2 اوبشن يوريهم للاستشاري اما فارديون بتاع هانويل | O29: =IFERROR(VALUE(SUBSTITUTE(TRIM(SUBSTITUTE(Projects_Follow_UP[[#This Row],[Est. value]],"SAR","")),",","")),0) -> 220000 | R29: {=_xlfn.LET(_xlpm.x,_xlfn.XLOOKUP(A29,Dashboard!$M$61:$M$72,Dashboard!$J$61:$J$72,""),IF(_xlpm.x<>"",_xlpm.x,M29))} -> 0 | S29: {=_xlfn.LET(_xlpm.x,_xlfn.XLOOKUP(A29,Dashboard!$M$61:$M$72,Dashboard!$K$61:$K$72,""),_xlpm.orig,N29,IF(_xlpm.x<>"",_xlpm.x,IF(OR(_xlpm.orig="",_xlpm.orig=0),"",_xlpm.orig)))}
A30: PR1044 | B30: Saudi German Hospital | D30: =_xlfn.XLOOKUP(Projects_Follow_UP[[#This Row],[Client Name]],'Hot Leads'!A:A,'Hot Leads'!B:B,0,0) -> 0 | E30: =_xlfn.XLOOKUP(Projects_Follow_UP[[#This Row],[Client Phone Number]],'Hot Leads'!B:B,'Hot Leads'!C:C,0,0) -> 0 | F30: =_xlfn.XLOOKUP(Projects_Follow_UP[[#This Row],[Client Name]],'Hot Leads'!A:A,'Hot Leads'!F:F, ,0) -> 0 | G30: In Hand | H30: Jeddah | O30: =IFERROR(VALUE(SUBSTITUTE(TRIM(SUBSTITUTE(Projects_Follow_UP[[#This Row],[Est. value]],"SAR","")),",","")),0) -> 0 | R30: {=_xlfn.LET(_xlpm.x,_xlfn.XLOOKUP(A30,Dashboard!$M$61:$M$72,Dashboard!$J$61:$J$72,""),IF(_xlpm.x<>"",_xlpm.x,M30))} -> 0 | S30: {=_xlfn.LET(_xlpm.x,_xlfn.XLOOKUP(A30,Dashboard!$M$61:$M$72,Dashboard!$K$61:$K$72,""),_xlpm.orig,N30,IF(_xlpm.x<>"",_xlpm.x,IF(OR(_xlpm.orig="",_xlpm.orig=0),"",_xlpm.orig)))}
A31: PR1045 | D31: =_xlfn.XLOOKUP(Projects_Follow_UP[[#This Row],[Client Name]],'Hot Leads'!A:A,'Hot Leads'!B:B,0,0) -> 0 | E31: =_xlfn.XLOOKUP(Projects_Follow_UP[[#This Row],[Client Phone Number]],'Hot Leads'!B:B,'Hot Leads'!C:C,0,0) -> 0 | F31: =_xlfn.XLOOKUP(Projects_Follow_UP[[#This Row],[Client Name]],'Hot Leads'!A:A,'Hot Leads'!F:F, ,0) -> 0 | O31: =IFERROR(VALUE(SUBSTITUTE(TRIM(SUBSTITUTE(Projects_Follow_UP[[#This Row],[Est. value]],"SAR","")),",","")),0) -> 0 | R31: {=_xlfn.LET(_xlpm.x,_xlfn.XLOOKUP(A31,Dashboard!$M$61:$M$72,Dashboard!$J$61:$J$72,""),IF(_xlpm.x<>"",_xlpm.x,M31))} -> 0 | S31: {=_xlfn.LET(_xlpm.x,_xlfn.XLOOKUP(A31,Dashboard!$M$61:$M$72,Dashboard!$K$61:$K$72,""),_xlpm.orig,N31,IF(_xlpm.x<>"",_xlpm.x,IF(OR(_xlpm.orig="",_xlpm.orig=0),"",_xlpm.orig)))}
A32: PR1046 | D32: =_xlfn.XLOOKUP(Projects_Follow_UP[[#This Row],[Client Name]],'Hot Leads'!A:A,'Hot Leads'!B:B,0,0) -> 0 | E32: =_xlfn.XLOOKUP(Projects_Follow_UP[[#This Row],[Client Phone Number]],'Hot Leads'!B:B,'Hot Leads'!C:C,0,0) -> 0 | F32: =_xlfn.XLOOKUP(Projects_Follow_UP[[#This Row],[Client Name]],'Hot Leads'!A:A,'Hot Leads'!F:F, ,0) -> 0 | O32: =IFERROR(VALUE(SUBSTITUTE(TRIM(SUBSTITUTE(Projects_Follow_UP[[#This Row],[Est. value]],"SAR","")),",","")),0) -> 0 | R32: {=_xlfn.LET(_xlpm.x,_xlfn.XLOOKUP(A32,Dashboard!$M$61:$M$72,Dashboard!$J$61:$J$72,""),IF(_xlpm.x<>"",_xlpm.x,M32))} -> 0 | S32: {=_xlfn.LET(_xlpm.x,_xlfn.XLOOKUP(A32,Dashboard!$M$61:$M$72,Dashboard!$K$61:$K$72,""),_xlpm.orig,N32,IF(_xlpm.x<>"",_xlpm.x,IF(OR(_xlpm.orig="",_xlpm.orig=0),"",_xlpm.orig)))}
A33: PR1047 | D33: =_xlfn.XLOOKUP(Projects_Follow_UP[[#This Row],[Client Name]],'Hot Leads'!A:A,'Hot Leads'!B:B,0,0) -> 0 | E33: =_xlfn.XLOOKUP(Projects_Follow_UP[[#This Row],[Client Phone Number]],'Hot Leads'!B:B,'Hot Leads'!C:C,0,0) -> 0 | F33: =_xlfn.XLOOKUP(Projects_Follow_UP[[#This Row],[Client Name]],'Hot Leads'!A:A,'Hot Leads'!F:F, ,0) -> 0 | O33: =IFERROR(VALUE(SUBSTITUTE(TRIM(SUBSTITUTE(Projects_Follow_UP[[#This Row],[Est. value]],"SAR","")),",","")),0) -> 0 | R33: {=_xlfn.LET(_xlpm.x,_xlfn.XLOOKUP(A33,Dashboard!$M$61:$M$72,Dashboard!$J$61:$J$72,""),IF(_xlpm.x<>"",_xlpm.x,M33))} -> 0 | S33: {=_xlfn.LET(_xlpm.x,_xlfn.XLOOKUP(A33,Dashboard!$M$61:$M$72,Dashboard!$K$61:$K$72,""),_xlpm.orig,N33,IF(_xlpm.x<>"",_xlpm.x,IF(OR(_xlpm.orig="",_xlpm.orig=0),"",_xlpm.orig)))}
A34: PR1048 | D34: =_xlfn.XLOOKUP(Projects_Follow_UP[[#This Row],[Client Name]],'Hot Leads'!A:A,'Hot Leads'!B:B,0,0) -> 0 | E34: =_xlfn.XLOOKUP(Projects_Follow_UP[[#This Row],[Client Phone Number]],'Hot Leads'!B:B,'Hot Leads'!C:C,0,0) -> 0 | F34: =_xlfn.XLOOKUP(Projects_Follow_UP[[#This Row],[Client Name]],'Hot Leads'!A:A,'Hot Leads'!F:F, ,0) -> 0 | O34: =IFERROR(VALUE(SUBSTITUTE(TRIM(SUBSTITUTE(Projects_Follow_UP[[#This Row],[Est. value]],"SAR","")),",","")),0) -> 0 | R34: {=_xlfn.LET(_xlpm.x,_xlfn.XLOOKUP(A34,Dashboard!$M$61:$M$72,Dashboard!$J$61:$J$72,""),IF(_xlpm.x<>"",_xlpm.x,M34))} -> 0 | S34: {=_xlfn.LET(_xlpm.x,_xlfn.XLOOKUP(A34,Dashboard!$M$61:$M$72,Dashboard!$K$61:$K$72,""),_xlpm.orig,N34,IF(_xlpm.x<>"",_xlpm.x,IF(OR(_xlpm.orig="",_xlpm.orig=0),"",_xlpm.orig)))}
A35: PR1049 | D35: =_xlfn.XLOOKUP(Projects_Follow_UP[[#This Row],[Client Name]],'Hot Leads'!A:A,'Hot Leads'!B:B,0,0) -> 0 | E35: =_xlfn.XLOOKUP(Projects_Follow_UP[[#This Row],[Client Phone Number]],'Hot Leads'!B:B,'Hot Leads'!C:C,0,0) -> 0 | F35: =_xlfn.XLOOKUP(Projects_Follow_UP[[#This Row],[Client Name]],'Hot Leads'!A:A,'Hot Leads'!F:F, ,0) -> 0 | O35: =IFERROR(VALUE(SUBSTITUTE(TRIM(SUBSTITUTE(Projects_Follow_UP[[#This Row],[Est. value]],"SAR","")),",","")),0) -> 0 | R35: {=_xlfn.LET(_xlpm.x,_xlfn.XLOOKUP(A35,Dashboard!$M$61:$M$72,Dashboard!$J$61:$J$72,""),IF(_xlpm.x<>"",_xlpm.x,M35))} -> 0 | S35: {=_xlfn.LET(_xlpm.x,_xlfn.XLOOKUP(A35,Dashboard!$M$61:$M$72,Dashboard!$K$61:$K$72,""),_xlpm.orig,N35,IF(_xlpm.x<>"",_xlpm.x,IF(OR(_xlpm.orig="",_xlpm.orig=0),"",_xlpm.orig)))}
A36: PR1050 | D36: =_xlfn.XLOOKUP(Projects_Follow_UP[[#This Row],[Client Name]],'Hot Leads'!A:A,'Hot Leads'!B:B,0,0) -> 0 | E36: =_xlfn.XLOOKUP(Projects_Follow_UP[[#This Row],[Client Phone Number]],'Hot Leads'!B:B,'Hot Leads'!C:C,0,0) -> 0 | F36: =_xlfn.XLOOKUP(Projects_Follow_UP[[#This Row],[Client Name]],'Hot Leads'!A:A,'Hot Leads'!F:F, ,0) -> 0 | O36: =IFERROR(VALUE(SUBSTITUTE(TRIM(SUBSTITUTE(Projects_Follow_UP[[#This Row],[Est. value]],"SAR","")),",","")),0) -> 0 | R36: {=_xlfn.LET(_xlpm.x,_xlfn.XLOOKUP(A36,Dashboard!$M$61:$M$72,Dashboard!$J$61:$J$72,""),IF(_xlpm.x<>"",_xlpm.x,M36))} -> 0 | S36: {=_xlfn.LET(_xlpm.x,_xlfn.XLOOKUP(A36,Dashboard!$M$61:$M$72,Dashboard!$K$61:$K$72,""),_xlpm.orig,N36,IF(_xlpm.x<>"",_xlpm.x,IF(OR(_xlpm.orig="",_xlpm.orig=0),"",_xlpm.orig)))}
A37: PR1051 | D37: =_xlfn.XLOOKUP(Projects_Follow_UP[[#This Row],[Client Name]],'Hot Leads'!A:A,'Hot Leads'!B:B,0,0) -> 0 | E37: =_xlfn.XLOOKUP(Projects_Follow_UP[[#This Row],[Client Phone Number]],'Hot Leads'!B:B,'Hot Leads'!C:C,0,0) -> 0 | F37: =_xlfn.XLOOKUP(Projects_Follow_UP[[#This Row],[Client Name]],'Hot Leads'!A:A,'Hot Leads'!F:F, ,0) -> 0 | O37: =IFERROR(VALUE(SUBSTITUTE(TRIM(SUBSTITUTE(Projects_Follow_UP[[#This Row],[Est. value]],"SAR","")),",","")),0) -> 0 | R37: {=_xlfn.LET(_xlpm.x,_xlfn.XLOOKUP(A37,Dashboard!$M$61:$M$72,Dashboard!$J$61:$J$72,""),IF(_xlpm.x<>"",_xlpm.x,M37))} -> 0 | S37: {=_xlfn.LET(_xlpm.x,_xlfn.XLOOKUP(A37,Dashboard!$M$61:$M$72,Dashboard!$K$61:$K$72,""),_xlpm.orig,N37,IF(_xlpm.x<>"",_xlpm.x,IF(OR(_xlpm.orig="",_xlpm.orig=0),"",_xlpm.orig)))}
A38: PR1052 | D38: =_xlfn.XLOOKUP(Projects_Follow_UP[[#This Row],[Client Name]],'Hot Leads'!A:A,'Hot Leads'!B:B,0,0) -> 0 | E38: =_xlfn.XLOOKUP(Projects_Follow_UP[[#This Row],[Client Phone Number]],'Hot Leads'!B:B,'Hot Leads'!C:C,0,0) -> 0 | F38: =_xlfn.XLOOKUP(Projects_Follow_UP[[#This Row],[Client Name]],'Hot Leads'!A:A,'Hot Leads'!F:F, ,0) -> 0 | O38: =IFERROR(VALUE(SUBSTITUTE(TRIM(SUBSTITUTE(Projects_Follow_UP[[#This Row],[Est. value]],"SAR","")),",","")),0) -> 0 | R38: {=_xlfn.LET(_xlpm.x,_xlfn.XLOOKUP(A38,Dashboard!$M$61:$M$72,Dashboard!$J$61:$J$72,""),IF(_xlpm.x<>"",_xlpm.x,M38))} -> 0 | S38: {=_xlfn.LET(_xlpm.x,_xlfn.XLOOKUP(A38,Dashboard!$M$61:$M$72,Dashboard!$K$61:$K$72,""),_xlpm.orig,N38,IF(_xlpm.x<>"",_xlpm.x,IF(OR(_xlpm.orig="",_xlpm.orig=0),"",_xlpm.orig)))}
A39: PR1053 | D39: =_xlfn.XLOOKUP(Projects_Follow_UP[[#This Row],[Client Name]],'Hot Leads'!A:A,'Hot Leads'!B:B,0,0) -> 0 | E39: =_xlfn.XLOOKUP(Projects_Follow_UP[[#This Row],[Client Phone Number]],'Hot Leads'!B:B,'Hot Leads'!C:C,0,0) -> 0 | F39: =_xlfn.XLOOKUP(Projects_Follow_UP[[#This Row],[Client Name]],'Hot Leads'!A:A,'Hot Leads'!F:F, ,0) -> 0 | O39: =IFERROR(VALUE(SUBSTITUTE(TRIM(SUBSTITUTE(Projects_Follow_UP[[#This Row],[Est. value]],"SAR","")),",","")),0) -> 0 | R39: {=_xlfn.LET(_xlpm.x,_xlfn.XLOOKUP(A39,Dashboard!$M$61:$M$72,Dashboard!$J$61:$J$72,""),IF(_xlpm.x<>"",_xlpm.x,M39))} -> 0 | S39: {=_xlfn.LET(_xlpm.x,_xlfn.XLOOKUP(A39,Dashboard!$M$61:$M$72,Dashboard!$K$61:$K$72,""),_xlpm.orig,N39,IF(_xlpm.x<>"",_xlpm.x,IF(OR(_xlpm.orig="",_xlpm.orig=0),"",_xlpm.orig)))}
A40: PR1054 | D40: =_xlfn.XLOOKUP(Projects_Follow_UP[[#This Row],[Client Name]],'Hot Leads'!A:A,'Hot Leads'!B:B,0,0) -> 0 | E40: =_xlfn.XLOOKUP(Projects_Follow_UP[[#This Row],[Client Phone Number]],'Hot Leads'!B:B,'Hot Leads'!C:C,0,0) -> 0 | F40: =_xlfn.XLOOKUP(Projects_Follow_UP[[#This Row],[Client Name]],'Hot Leads'!A:A,'Hot Leads'!F:F, ,0) -> 0 | O40: =IFERROR(VALUE(SUBSTITUTE(TRIM(SUBSTITUTE(Projects_Follow_UP[[#This Row],[Est. value]],"SAR","")),",","")),0) -> 0 | R40: {=_xlfn.LET(_xlpm.x,_xlfn.XLOOKUP(A40,Dashboard!$M$61:$M$72,Dashboard!$J$61:$J$72,""),IF(_xlpm.x<>"",_xlpm.x,M40))} -> 0 | S40: {=_xlfn.LET(_xlpm.x,_xlfn.XLOOKUP(A40,Dashboard!$M$61:$M$72,Dashboard!$K$61:$K$72,""),_xlpm.orig,N40,IF(_xlpm.x<>"",_xlpm.x,IF(OR(_xlpm.orig="",_xlpm.orig=0),"",_xlpm.orig)))}
A41: PR1055 | D41: =_xlfn.XLOOKUP(Projects_Follow_UP[[#This Row],[Client Name]],'Hot Leads'!A:A,'Hot Leads'!B:B,0,0) -> 0 | E41: =_xlfn.XLOOKUP(Projects_Follow_UP[[#This Row],[Client Phone Number]],'Hot Leads'!B:B,'Hot Leads'!C:C,0,0) -> 0 | F41: =_xlfn.XLOOKUP(Projects_Follow_UP[[#This Row],[Client Name]],'Hot Leads'!A:A,'Hot Leads'!F:F, ,0) -> 0 | O41: =IFERROR(VALUE(SUBSTITUTE(TRIM(SUBSTITUTE(Projects_Follow_UP[[#This Row],[Est. value]],"SAR","")),",","")),0) -> 0 | R41: {=_xlfn.LET(_xlpm.x,_xlfn.XLOOKUP(A41,Dashboard!$M$61:$M$72,Dashboard!$J$61:$J$72,""),IF(_xlpm.x<>"",_xlpm.x,M41))} -> 0 | S41: {=_xlfn.LET(_xlpm.x,_xlfn.XLOOKUP(A41,Dashboard!$M$61:$M$72,Dashboard!$K$61:$K$72,""),_xlpm.orig,N41,IF(_xlpm.x<>"",_xlpm.x,IF(OR(_xlpm.orig="",_xlpm.orig=0),"",_xlpm.orig)))}
A42: PR1056 | D42: =_xlfn.XLOOKUP(Projects_Follow_UP[[#This Row],[Client Name]],'Hot Leads'!A:A,'Hot Leads'!B:B,0,0) -> 0 | E42: =_xlfn.XLOOKUP(Projects_Follow_UP[[#This Row],[Client Phone Number]],'Hot Leads'!B:B,'Hot Leads'!C:C,0,0) -> 0 | F42: =_xlfn.XLOOKUP(Projects_Follow_UP[[#This Row],[Client Name]],'Hot Leads'!A:A,'Hot Leads'!F:F, ,0) -> 0 | O42: =IFERROR(VALUE(SUBSTITUTE(TRIM(SUBSTITUTE(Projects_Follow_UP[[#This Row],[Est. value]],"SAR","")),",","")),0) -> 0 | R42: {=_xlfn.LET(_xlpm.x,_xlfn.XLOOKUP(A42,Dashboard!$M$61:$M$72,Dashboard!$J$61:$J$72,""),IF(_xlpm.x<>"",_xlpm.x,M42))} -> 0 | S42: {=_xlfn.LET(_xlpm.x,_xlfn.XLOOKUP(A42,Dashboard!$M$61:$M$72,Dashboard!$K$61:$K$72,""),_xlpm.orig,N42,IF(_xlpm.x<>"",_xlpm.x,IF(OR(_xlpm.orig="",_xlpm.orig=0),"",_xlpm.orig)))}
... A139: PR1153 | D139: =_xlfn.XLOOKUP(Projects_Follow_UP[[#This Row],[Client Name]],'Hot Leads'!A:A,'Hot Leads'!B:B,0,0) -> 0 | E139: =_xlfn.XLOOKUP(Projects_Follow_UP[[#This Row],[Client Phone Number]],'Hot Leads'!B:B,'Hot Leads'!C:C,0,0) -> 0 | F139: =_xlfn.XLOOKUP(Projects_Follow_UP[[#This Row],[Client Name]],'Hot Leads'!A:A,'Hot Leads'!F:F, ,0) -> 0 | O139: =IFERROR(VALUE(SUBSTITUTE(TRIM(SUBSTITUTE(Projects_Follow_UP[[#This Row],[Est. value]],"SAR","")),",","")),0) -> 0 | R139: {=_xlfn.LET(_xlpm.x,_xlfn.XLOOKUP(A139,Dashboard!$M$61:$M$72,Dashboard!$J$61:$J$72,""),IF(_xlpm.x<>"",_xlpm.x,M139))} -> 0 | S139: {=_xlfn.LET(_xlpm.x,_xlfn.XLOOKUP(A139,Dashboard!$M$61:$M$72,Dashboard!$K$61:$K$72,""),_xlpm.orig,N139,IF(_xlpm.x<>"",_xlpm.x,IF(OR(_xlpm.orig="",_xlpm.orig=0),"",_xlpm.orig)))}

Sheet Hot Leads
A1: Name | B1: Phone | C1: Company | D1: Google Map Location | E1: Company Based on | F1: Email | G1: Position | H1: Last Call Date | I1: Notes | J1: Next Follow Up Notes | K1: Next Follow Up Date | L1: Gone To Referral ? | M1: Current Action Required | N1: Current Action Date
A2: Mohamed Hussain | B2: 966562846152 | C2: Creet | D2: https://maps.app.goo.gl/dDuLptLbo71wA8du9 | E2: Jeddah | F2: m.hussain@creet.net | G2: Procurement Engineer | H2: 46131 | I2: بعتلنا مشروع New Industrial Factory عشان نعدل الكميات و نبعتله السعر الجديد و لسة | J2: اول ما الكوتيشن تخلص هكلمه | M2: {=_xlfn.LET(_xlpm.x,_xlfn.XLOOKUP(Hot_Leads[[#This Row],[Phone]],Dashboard!$M$44:$M$58,Dashboard!$J$44:$J$58,""),IF(_xlpm.x<>"",_xlpm.x,Hot_Leads[[#This Row],[Next Follow Up Notes]]))} -> اول ما الكوتيشن تخلص هكلمه | N2: {=_xlfn.LET(_xlpm.x,_xlfn.XLOOKUP(Hot_Leads[[#This Row],[Phone]],Dashboard!$M$44:$M$58,Dashboard!$K$44:$K$58,""),_xlpm.orig,Hot_Leads[[#This Row],[Next Follow Up Date]],IF(_xlpm.x<>"",_xlpm.x,IF(OR(_xlpm.orig="",_xlpm.orig=0),"",_xlpm.orig)))}
A3: Nasser Bn Mounir | B3: 966540374734 | C3: Inshaa Aljezra | D3: https://maps.app.goo.gl/JzJ3RJ7bUkrwNRUZA | E3: Makkah | F3: -- | G3: Procurement Manager | H3: 46176 | I3: خلصوا المشاريع الي معاهم حاليا و فيه مشروع تاني معاهم بعد الحج قالي ابعتلي البروفايل و ابعتلي البزنس كارد | J3: لسة على نفس المشروع القديم و مفيش جديد خالص | M3: {=_xlfn.LET(_xlpm.x,_xlfn.XLOOKUP(Hot_Leads[[#This Row],[Phone]],Dashboard!$M$44:$M$58,Dashboard!$J$44:$J$58,""),IF(_xlpm.x<>"",_xlpm.x,Hot_Leads[[#This Row],[Next Follow Up Notes]]))} -> لسة على نفس المشروع القديم و مفيش جديد خالص | N3: {=_xlfn.LET(_xlpm.x,_xlfn.XLOOKUP(Hot_Leads[[#This Row],[Phone]],Dashboard!$M$44:$M$58,Dashboard!$K$44:$K$58,""),_xlpm.orig,Hot_Leads[[#This Row],[Next Follow Up Date]],IF(_xlpm.x<>"",_xlpm.x,IF(OR(_xlpm.orig="",_xlpm.orig=0),"",_xlpm.orig)))}
A4: Asghar Ali | B4: 966552196041 | C4: ALghanem | F4: asgar.ali@orc-constructions.com | G4: Engineering rep | H4: 46131 | I4: معنهمش مشاريع جديدة | J4: Send Business Card & Company Profile | M4: {=_xlfn.LET(_xlpm.x,_xlfn.XLOOKUP(Hot_Leads[[#This Row],[Phone]],Dashboard!$M$44:$M$58,Dashboard!$J$44:$J$58,""),IF(_xlpm.x<>"",_xlpm.x,Hot_Leads[[#This Row],[Next Follow Up Notes]]))} -> Send Business Card & Company Profile | N4: {=_xlfn.LET(_xlpm.x,_xlfn.XLOOKUP(Hot_Leads[[#This Row],[Phone]],Dashboard!$M$44:$M$58,Dashboard!$K$44:$K$58,""),_xlpm.orig,Hot_Leads[[#This Row],[Next Follow Up Date]],IF(_xlpm.x<>"",_xlpm.x,IF(OR(_xlpm.orig="",_xlpm.orig=0),"",_xlpm.orig)))}
A5: Mark Brian | B5: 966550796895 | C5: Hexagon | D5: https://maps.app.goo.gl/iSnFecR4DVJ6biXV9 | E5: Dammam | F5: Brian.Nemi@hexagon.sa | G5: Technical Manager | H5: 46131 | I5: Na | J5: Na | M5: {=_xlfn.LET(_xlpm.x,_xlfn.XLOOKUP(Hot_Leads[[#This Row],[Phone]],Dashboard!$M$44:$M$58,Dashboard!$J$44:$J$58,""),IF(_xlpm.x<>"",_xlpm.x,Hot_Leads[[#This Row],[Next Follow Up Notes]]))} -> Na | N5: {=_xlfn.LET(_xlpm.x,_xlfn.XLOOKUP(Hot_Leads[[#This Row],[Phone]],Dashboard!$M$44:$M$58,Dashboard!$K$44:$K$58,""),_xlpm.orig,Hot_Leads[[#This Row],[Next Follow Up Date]],IF(_xlpm.x<>"",_xlpm.x,IF(OR(_xlpm.orig="",_xlpm.orig=0),"",_xlpm.orig)))}
A6: Mohamed Abdelhady | B6: 966547017064 | C6: GAC | D6: https://maps.app.goo.gl/a1oNGzQ8BDT2fyjHA | E6: Dammam | F6: mohammed.abdulhadi@gac-cont.com | G6: Engineering Manager | H6: 46131 | I6: معاه مشروع Digital Signage Screen في مستشفى الملك فهد التخصصي في الدمام و تفاصيل المشروع معاك في النوت و مستني منك كوتيشن | J6: Send Quotation and Ask for the sister company for BMS | L6: Abdelrahman | M6: {=_xlfn.LET(_xlpm.x,_xlfn.XLOOKUP(Hot_Leads[[#This Row],[Phone]],Dashboard!$M$44:$M$58,Dashboard!$J$44:$J$58,""),IF(_xlpm.x<>"",_xlpm.x,Hot_Leads[[#This Row],[Next Follow Up Notes]]))} -> Send Quotation and Ask for the sister company for BMS | N6: {=_xlfn.LET(_xlpm.x,_xlfn.XLOOKUP(Hot_Leads[[#This Row],[Phone]],Dashboard!$M$44:$M$58,Dashboard!$K$44:$K$58,""),_xlpm.orig,Hot_Leads[[#This Row],[Next Follow Up Date]],IF(_xlpm.x<>"",_xlpm.x,IF(OR(_xlpm.orig="",_xlpm.orig=0),"",_xlpm.orig)))}
A7: Ibrahim Ahmed | B7: 966546468592 | C7: Al-Fanar | D7: https://maps.app.goo.gl/c5pWiicmKMLBYKo58 | E7: Riyadh | G7: Engineering Manager | H7: 46176 | I7: ساب شركة السعد و راح شركة الفنار و معاه مشروع King Salman Park ده تندر لسة و مفيش جديد خالص حمدي جلال هو الي بيتابع معاه | J7: هكلمه يوم الاتنين عشان اعرف التفاصيل الجديدة | M7: {=_xlfn.LET(_xlpm.x,_xlfn.XLOOKUP(Hot_Leads[[#This Row],[Phone]],Dashboard!$M$44:$M$58,Dashboard!$J$44:$J$58,""),IF(_xlpm.x<>"",_xlpm.x,Hot_Leads[[#This Row],[Next Follow Up Notes]]))} -> هكلمه يوم الاتنين عشان اعرف التفاصيل الجديدة | N7: {=_xlfn.LET(_xlpm.x,_xlfn.XLOOKUP(Hot_Leads[[#This Row],[Phone]],Dashboard!$M$44:$M$58,Dashboard!$K$44:$K$58,""),_xlpm.orig,Hot_Leads[[#This Row],[Next Follow Up Date]],IF(_xlpm.x<>"",_xlpm.x,IF(OR(_xlpm.orig="",_xlpm.orig=0),"",_xlpm.orig)))} -> 46146
A8: Yasser Bahussin | B8: 966506694282 | C8: Alsalama Hospital | D8: https://maps.app.goo.gl/hduVAmcVWzY67pd2A | E8: Jeddah | F8: yasser.bahussain@alsalamahospital.com | G8: Engineering manager | H8: 46131 | I8: ابعتله البروفايل و اتابع معاه كل اسبوع لحد ما يفتكرني دايما | J8: عندي ميتنج معاه يوم الاحد | M8: {=_xlfn.LET(_xlpm.x,_xlfn.XLOOKUP(Hot_Leads[[#This Row],[Phone]],Dashboard!$M$44:$M$58,Dashboard!$J$44:$J$58,""),IF(_xlpm.x<>"",_xlpm.x,Hot_Leads[[#This Row],[Next Follow Up Notes]]))} -> قالي ان البرنامج هيرسى علينا و مستني بس موفقه الادارة | N8: {=_xlfn.LET(_xlpm.x,_xlfn.XLOOKUP(Hot_Leads[[#This Row],[Phone]],Dashboard!$M$44:$M$58,Dashboard!$K$44:$K$58,""),_xlpm.orig,Hot_Leads[[#This Row],[Next Follow Up Date]],IF(_xlpm.x<>"",_xlpm.x,IF(OR(_xlpm.orig="",_xlpm.orig=0),"",_xlpm.orig)))} -> 46250
A9: Ibrahim Abdelhamid | B9: 966500029803 | C9: Redcon International | D9: -- | E9: Riyadh | F9: ibrahim.abdelhamid@redconinternational.com | G9: Engineering manager | H9: 46132 | I9: عاوز يسعر Spine Mall و ال Sports Club بتاع مشروع Benan TMG طلعت مصطفى و حولت الكونتاكت لمهندس حمدي عشان المكتب بتاعهم في الرياض | J9: ده خلاص بقا مع مهندس حمدي | L9: Hamdy | M9: {=_xlfn.LET(_xlpm.x,_xlfn.XLOOKUP(Hot_Leads[[#This Row],[Phone]],Dashboard!$M$44:$M$58,Dashboard!$J$44:$J$58,""),IF(_xlpm.x<>"",_xlpm.x,Hot_Leads[[#This Row],[Next Follow Up Notes]]))} -> ده خلاص بقا مع مهندس حمدي | N9: {=_xlfn.LET(_xlpm.x,_xlfn.XLOOKUP(Hot_Leads[[#This Row],[Phone]],Dashboard!$M$44:$M$58,Dashboard!$K$44:$K$58,""),_xlpm.orig,Hot_Leads[[#This Row],[Next Follow Up Date]],IF(_xlpm.x<>"",_xlpm.x,IF(OR(_xlpm.orig="",_xlpm.orig=0),"",_xlpm.orig)))}
A10: Hussni | B10: 966532001107 | C10: Jash | F10: hussni@jash.com.sa | G10: - | H10: 46132 | I10: عنده مشروع تجديد صالة الامير فيصل للفنون فيها Barriers , CCTV , BMS و قالي ان انا سالت عليكم و انتم سعركم غالي جدا | J10: اداني رقم مهندس تاني هكلمه دلوقتي عشان نروح نعمل معاينه | M10: {=_xlfn.LET(_xlpm.x,_xlfn.XLOOKUP(Hot_Leads[[#This Row],[Phone]],Dashboard!$M$44:$M$58,Dashboard!$J$44:$J$58,""),IF(_xlpm.x<>"",_xlpm.x,Hot_Leads[[#This Row],[Next Follow Up Notes]]))} -> اداني رقم مهندس تاني هكلمه دلوقتي عشان نروح نعمل معاينه | N10: {=_xlfn.LET(_xlpm.x,_xlfn.XLOOKUP(Hot_Leads[[#This Row],[Phone]],Dashboard!$M$44:$M$58,Dashboard!$K$44:$K$58,""),_xlpm.orig,Hot_Leads[[#This Row],[Next Follow Up Date]],IF(_xlpm.x<>"",_xlpm.x,IF(OR(_xlpm.orig="",_xlpm.orig=0),"",_xlpm.orig)))}
A11: Mohamed Elkholy | B11: 966541016847 | C11: Fairmont Makkah | E11: Makkah | G11: Engineering manager | H11: 46132 | I11: ده مهم عنده سيستم عاوز ينفذه في الفندق و قالي ابعتلي الميل بتاعك عشان ابعتلك تسعرلي | J11: كلمته و قالي الحاجة وصلتني و انه كان مشغول و هيبعت المشروع على الميل على طول | M11: {=_xlfn.LET(_xlpm.x,_xlfn.XLOOKUP(Hot_Leads[[#This Row],[Phone]],Dashboard!$M$44:$M$58,Dashboard!$J$44:$J$58,""),IF(_xlpm.x<>"",_xlpm.x,Hot_Leads[[#This Row],[Next Follow Up Notes]]))} -> مفيش اخبار جديدة عنه | N11: {=_xlfn.LET(_xlpm.x,_xlfn.XLOOKUP(Hot_Leads[[#This Row],[Phone]],Dashboard!$M$44:$M$58,Dashboard!$K$44:$K$58,""),_xlpm.orig,Hot_Leads[[#This Row],[Next Follow Up Date]],IF(_xlpm.x<>"",_xlpm.x,IF(OR(_xlpm.orig="",_xlpm.orig=0),"",_xlpm.orig)))} -> 46243
A12: Refaat | B12: 201118383863 | C12: SIAC KSA Branch | G12: Project Manager | H12: 46132 | I12: كان معاهم مشروعين و هم خلاص في مرحلة التسليم الاخيرة و مفيش معاهم حاجة تاني حاليا | J12: Follow up Next Week | M12: {=_xlfn.LET(_xlpm.x,_xlfn.XLOOKUP(Hot_Leads[[#This Row],[Phone]],Dashboard!$M$44:$M$58,Dashboard!$J$44:$J$58,""),IF(_xlpm.x<>"",_xlpm.x,Hot_Leads[[#This Row],[Next Follow Up Notes]]))} -> Follow up Next Week | N12: {=_xlfn.LET(_xlpm.x,_xlfn.XLOOKUP(Hot_Leads[[#This Row],[Phone]],Dashboard!$M$44:$M$58,Dashboard!$K$44:$K$58,""),_xlpm.orig,Hot_Leads[[#This Row],[Next Follow Up Date]],IF(_xlpm.x<>"",_xlpm.x,IF(OR(_xlpm.orig="",_xlpm.orig=0),"",_xlpm.orig)))}
A13: Helmy Abdelrazeq | B13: 966560374964 | C13: AlShamela | E13: Jeddah | F13: hemlyac@alshamela.com.sa | G13: Project Manager | H13: 46133 | I13: عاوز فايل ال Pre Qualification بتاعنا على الميل عشان يعرف احنا ممكن نشتغل معاهم في ايه | J13: تابع معاه يوم الاحد | M13: {=_xlfn.LET(_xlpm.x,_xlfn.XLOOKUP(Hot_Leads[[#This Row],[Phone]],Dashboard!$M$44:$M$58,Dashboard!$J$44:$J$58,""),IF(_xlpm.x<>"",_xlpm.x,Hot_Leads[[#This Row],[Next Follow Up Notes]]))} -> تابع معاه يوم الاحد | N13: {=_xlfn.LET(_xlpm.x,_xlfn.XLOOKUP(Hot_Leads[[#This Row],[Phone]],Dashboard!$M$44:$M$58,Dashboard!$K$44:$K$58,""),_xlpm.orig,Hot_Leads[[#This Row],[Next Follow Up Date]],IF(_xlpm.x<>"",_xlpm.x,IF(OR(_xlpm.orig="",_xlpm.orig=0),"",_xlpm.orig)))}
A14: شركة رؤى الحرم المكي | H14: 46133 | I14: عاوز حد من هناك ضروري اعرف المشاريع الي عندهم | M14: {=_xlfn.LET(_xlpm.x,_xlfn.XLOOKUP(Hot_Leads[[#This Row],[Phone]],Dashboard!$M$44:$M$58,Dashboard!$J$44:$J$58,""),IF(_xlpm.x<>"",_xlpm.x,Hot_Leads[[#This Row],[Next Follow Up Notes]]))} -> 0 | N14: {=_xlfn.LET(_xlpm.x,_xlfn.XLOOKUP(Hot_Leads[[#This Row],[Phone]],Dashboard!$M$44:$M$58,Dashboard!$K$44:$K$58,""),_xlpm.orig,Hot_Leads[[#This Row],[Next Follow Up Date]],IF(_xlpm.x<>"",_xlpm.x,IF(OR(_xlpm.orig="",_xlpm.orig=0),"",_xlpm.orig)))}
A15: Mohamed Taqash | B15: 966569972444 | C15: Al-Saif | E15: Jeddah | G15: Project Manager | H15: 46176 | I15: ده مهندس عماد كان مقدمله مشروع IMC كنت بتابع معاه بس مفيش معلومات جديدة و قالي انه هيدي رقمي للمشتريات عشان يبعتولي لو فيه مشاريع جديدة | J15: Follow Up Next Week | M15: {=_xlfn.LET(_xlpm.x,_xlfn.XLOOKUP(Hot_Leads[[#This Row],[Phone]],Dashboard!$M$44:$M$58,Dashboard!$J$44:$J$58,""),IF(_xlpm.x<>"",_xlpm.x,Hot_Leads[[#This Row],[Next Follow Up Notes]]))} -> Follow Up Next Week | N15: {=_xlfn.LET(_xlpm.x,_xlfn.XLOOKUP(Hot_Leads[[#This Row],[Phone]],Dashboard!$M$44:$M$58,Dashboard!$K$44:$K$58,""),_xlpm.orig,Hot_Leads[[#This Row],[Next Follow Up Date]],IF(_xlpm.x<>"",_xlpm.x,IF(OR(_xlpm.orig="",_xlpm.orig=0),"",_xlpm.orig)))} -> 46140
C16: Freyssinet Saudi Arabia | D16: https://maps.app.goo.gl/h5ByLCjX7i9xPuA27 | E16: Jeddah | H16: 46134 | I16: الشركة دي من ال shortlisted الي المفروض نبعتلها في مشروع IMC كمان و اخر تقديم ليهم هو يوم الاحد 26-4-2026 | J16: Book a Visit | M16: {=_xlfn.LET(_xlpm.x,_xlfn.XLOOKUP(Hot_Leads[[#This Row],[Phone]],Dashboard!$M$44:$M$58,Dashboard!$J$44:$J$58,""),IF(_xlpm.x<>"",_xlpm.x,Hot_Leads[[#This Row],[Next Follow Up Notes]]))} -> Book a Visit | N16: {=_xlfn.LET(_xlpm.x,_xlfn.XLOOKUP(Hot_Leads[[#This Row],[Phone]],Dashboard!$M$44:$M$58,Dashboard!$K$44:$K$58,""),_xlpm.orig,Hot_Leads[[#This Row],[Next Follow Up Date]],IF(_xlpm.x<>"",_xlpm.x,IF(OR(_xlpm.orig="",_xlpm.orig=0),"",_xlpm.orig)))}
A17: Emad Hamwi | B17: 966503840536 | C17: BlueApps | F17: imad@blueapps.net | G17: Marketing Manager | H17: 46135 | I17: هتابع معاه عادي مش معاهم شغل حاليا | J17: الاكونت ده مع عبدالرحمن خلاص | L17: Abdelrahman | M17: {=_xlfn.LET(_xlpm.x,_xlfn.XLOOKUP(Hot_Leads[[#This Row],[Phone]],Dashboard!$M$44:$M$58,Dashboard!$J$44:$J$58,""),IF(_xlpm.x<>"",_xlpm.x,Hot_Leads[[#This Row],[Next Follow Up Notes]]))} -> الاكونت ده مع عبدالرحمن خلاص | N17: {=_xlfn.LET(_xlpm.x,_xlfn.XLOOKUP(Hot_Leads[[#This Row],[Phone]],Dashboard!$M$44:$M$58,Dashboard!$K$44:$K$58,""),_xlpm.orig,Hot_Leads[[#This Row],[Next Follow Up Date]],IF(_xlpm.x<>"",_xlpm.x,IF(OR(_xlpm.orig="",_xlpm.orig=0),"",_xlpm.orig)))}
A18: Majdi I. Al-Zoubi | B18: 966569548850 | C18: Rafa Gulf Contracting | F18: majdi@rafagulf.com | G18: Procurement Manager | H18: 46135 | I18: المهندس حمدي حاموي بتاع شركة BlueApps مسعر من عندنا مشروع اسمه CGC لشركة Rafa Gulf الي هو المهندس مجدي و بيقولي ان فيه اخبار قريبا عن المشروع عشان الادارة اتغيرت و احتمال يخلصوا فيه | J18: Follow Up Next Week | M18: {=_xlfn.LET(_xlpm.x,_xlfn.XLOOKUP(Hot_Leads[[#This Row],[Phone]],Dashboard!$M$44:$M$58,Dashboard!$J$44:$J$58,""),IF(_xlpm.x<>"",_xlpm.x,Hot_Leads[[#This Row],[Next Follow Up Notes]]))} -> ده خلاص مبقاش معايا مهندس عبدالرحمن قالي ان فيه حد مكمل معاه | N18: {=_xlfn.LET(_xlpm.x,_xlfn.XLOOKUP(Hot_Leads[[#This Row],[Phone]],Dashboard!$M$44:$M$58,Dashboard!$K$44:$K$58,""),_xlpm.orig,Hot_Leads[[#This Row],[Next Follow Up Date]],IF(_xlpm.x<>"",_xlpm.x,IF(OR(_xlpm.orig="",_xlpm.orig=0),"",_xlpm.orig)))} -> 46456
A19: Mohamed Khalifah | B19: 966500055718 | C19: Al-Awalat Company | E19: Madinah | G19: Project manager | H19: 46137 | I19: بعتلي المشروع | M19: {=_xlfn.LET(_xlpm.x,_xlfn.XLOOKUP(Hot_Leads[[#This Row],[Phone]],Dashboard!$M$44:$M$58,Dashboard!$J$44:$J$58,""),IF(_xlpm.x<>"",_xlpm.x,Hot_Leads[[#This Row],[Next Follow Up Notes]]))} -> 0 | N19: {=_xlfn.LET(_xlpm.x,_xlfn.XLOOKUP(Hot_Leads[[#This Row],[Phone]],Dashboard!$M$44:$M$58,Dashboard!$K$44:$K$58,""),_xlpm.orig,Hot_Leads[[#This Row],[Next Follow Up Date]],IF(_xlpm.x<>"",_xlpm.x,IF(OR(_xlpm.orig="",_xlpm.orig=0),"",_xlpm.orig)))}
A20: Mohamed Abodagga | B20: 966591245470 | C20: Hexagon | D20: https://maps.app.goo.gl/iSnFecR4DVJ6biXV9 | G20: Project manager | M20: {=_xlfn.LET(_xlpm.x,_xlfn.XLOOKUP(Hot_Leads[[#This Row],[Phone]],Dashboard!$M$44:$M$58,Dashboard!$J$44:$J$58,""),IF(_xlpm.x<>"",_xlpm.x,Hot_Leads[[#This Row],[Next Follow Up Notes]]))} -> 0 | N20: {=_xlfn.LET(_xlpm.x,_xlfn.XLOOKUP(Hot_Leads[[#This Row],[Phone]],Dashboard!$M$44:$M$58,Dashboard!$K$44:$K$58,""),_xlpm.orig,Hot_Leads[[#This Row],[Next Follow Up Date]],IF(_xlpm.x<>"",_xlpm.x,IF(OR(_xlpm.orig="",_xlpm.orig=0),"",_xlpm.orig)))}
A21: Ashraf Gadallah | B21: 966562292293 | C21: Afrina ACUD | D21: https://maps.app.goo.gl/iWmTQ4WzUsgV1X7i9 | E21: Jeddah | F21: ashraf.elsayed@acud.sa | G21: Technical Office Manager | H21: 46140 | I21: الشركة دي مهمة جدا معاهم 4 مشاريع in hand و معاهم بالاخص مشروع ابراج موطن المسار الي على طريق جده كلمته و هحدد معاه ميعاد بعد ما يبص على البروفايل بتاعنا | J21: هتابع معاه كمان يومين | M21: {=_xlfn.LET(_xlpm.x,_xlfn.XLOOKUP(Hot_Leads[[#This Row],[Phone]],Dashboard!$M$44:$M$58,Dashboard!$J$44:$J$58,""),IF(_xlpm.x<>"",_xlpm.x,Hot_Leads[[#This Row],[Next Follow Up Notes]]))} -> في اجازة في مصر و هرجع يبعتلنا مشروع ديار الحرم عشان نخشه سوا | N21: {=_xlfn.LET(_xlpm.x,_xlfn.XLOOKUP(Hot_Leads[[#This Row],[Phone]],Dashboard!$M$44:$M$58,Dashboard!$K$44:$K$58,""),_xlpm.orig,Hot_Leads[[#This Row],[Next Follow Up Date]],IF(_xlpm.x<>"",_xlpm.x,IF(OR(_xlpm.orig="",_xlpm.orig=0),"",_xlpm.orig)))} -> 46265
A22: Khaled ElShiekh | B22: 966509199592 | C22: Afrina ACUD | D22: https://maps.app.goo.gl/iWmTQ4WzUsgV1X7i9 | E22: Jeddah | G22: MEP Manager | H22: 46140 | I22: الشركة دي مهمة جدا معاهم 4 مشاريع in hand و معاهم بالاخص مشروع ابراج موطن المسار الي على طريق جده | J22: مردش و هكلمه تاني بس خلاص م/ اششرف رد عليا | M22: {=_xlfn.LET(_xlpm.x,_xlfn.XLOOKUP(Hot_Leads[[#This Row],[Phone]],Dashboard!$M$44:$M$58,Dashboard!$J$44:$J$58,""),IF(_xlpm.x<>"",_xlpm.x,Hot_Leads[[#This Row],[Next Follow Up Notes]]))} -> مردش و هكلمه تاني بس خلاص م/ اششرف رد عليا | N22: {=_xlfn.LET(_xlpm.x,_xlfn.XLOOKUP(Hot_Leads[[#This Row],[Phone]],Dashboard!$M$44:$M$58,Dashboard!$K$44:$K$58,""),_xlpm.orig,Hot_Leads[[#This Row],[Next Follow Up Date]],IF(_xlpm.x<>"",_xlpm.x,IF(OR(_xlpm.orig="",_xlpm.orig=0),"",_xlpm.orig)))}
A23: عبد العزيز حبيب | B23: 966569356683 | C23: شركة الضيافة الشامخة | E23: Makkah | G23: MEP Engineer | H23: 46139 | I23: لسة هكلمه نزلت شوفت اليافطة و انا معدي في الزايدي | M23: {=_xlfn.LET(_xlpm.x,_xlfn.XLOOKUP(Hot_Leads[[#This Row],[Phone]],Dashboard!$M$44:$M$58,Dashboard!$J$44:$J$58,""),IF(_xlpm.x<>"",_xlpm.x,Hot_Leads[[#This Row],[Next Follow Up Notes]]))} -> 0 | N23: {=_xlfn.LET(_xlpm.x,_xlfn.XLOOKUP(Hot_Leads[[#This Row],[Phone]],Dashboard!$M$44:$M$58,Dashboard!$K$44:$K$58,""),_xlpm.orig,Hot_Leads[[#This Row],[Next Follow Up Date]],IF(_xlpm.x<>"",_xlpm.x,IF(OR(_xlpm.orig="",_xlpm.orig=0),"",_xlpm.orig)))}
A24: مسار العقارية | B24: 966546686990 | C24: مسار العقارية | E24: Makkah | G24: MEP Engineer | H24: 46139 | I24: لسة هكلمه نزلت شوفت اليافطة و انا معدي في الزايدي | M24: {=_xlfn.LET(_xlpm.x,_xlfn.XLOOKUP(Hot_Leads[[#This Row],[Phone]],Dashboard!$M$44:$M$58,Dashboard!$J$44:$J$58,""),IF(_xlpm.x<>"",_xlpm.x,Hot_Leads[[#This Row],[Next Follow Up Notes]]))} -> 0 | N24: {=_xlfn.LET(_xlpm.x,_xlfn.XLOOKUP(Hot_Leads[[#This Row],[Phone]],Dashboard!$M$44:$M$58,Dashboard!$K$44:$K$58,""),_xlpm.orig,Hot_Leads[[#This Row],[Next Follow Up Date]],IF(_xlpm.x<>"",_xlpm.x,IF(OR(_xlpm.orig="",_xlpm.orig=0),"",_xlpm.orig)))}
A25: Sohail | B25: 966571664609 | C25: FOM العقارية | E25: Makkah | G25: Supervisor | H25: 46139 | I25: ده ال Supervisor بتاع مشروع V-Yard لمجموعة الزايدي في مكة هكلمه و اشوف ازاي اخش مع المهندسين | M25: {=_xlfn.LET(_xlpm.x,_xlfn.XLOOKUP(Hot_Leads[[#This Row],[Phone]],Dashboard!$M$44:$M$58,Dashboard!$J$44:$J$58,""),IF(_xlpm.x<>"",_xlpm.x,Hot_Leads[[#This Row],[Next Follow Up Notes]]))} -> 0 | N25: {=_xlfn.LET(_xlpm.x,_xlfn.XLOOKUP(Hot_Leads[[#This Row],[Phone]],Dashboard!$M$44:$M$58,Dashboard!$K$44:$K$58,""),_xlpm.orig,Hot_Leads[[#This Row],[Next Follow Up Date]],IF(_xlpm.x<>"",_xlpm.x,IF(OR(_xlpm.orig="",_xlpm.orig=0),"",_xlpm.orig)))}
C26: Roshan | E26: Makkah | H26: 46139 | I26: ده مشروع مجمع المنار عبارة عن سكني و تجاري و المفروض اتابع مع عبدالرحمن محمد و اعرف التفاصيل | M26: {=_xlfn.LET(_xlpm.x,_xlfn.XLOOKUP(Hot_Leads[[#This Row],[Phone]],Dashboard!$M$44:$M$58,Dashboard!$J$44:$J$58,""),IF(_xlpm.x<>"",_xlpm.x,Hot_Leads[[#This Row],[Next Follow Up Notes]]))} -> 0 | N26: {=_xlfn.LET(_xlpm.x,_xlfn.XLOOKUP(Hot_Leads[[#This Row],[Phone]],Dashboard!$M$44:$M$58,Dashboard!$K$44:$K$58,""),_xlpm.orig,Hot_Leads[[#This Row],[Next Follow Up Date]],IF(_xlpm.x<>"",_xlpm.x,IF(OR(_xlpm.orig="",_xlpm.orig=0),"",_xlpm.orig)))}
A27: Ahmed Abo Saif | B27: 966564236176 | C27: انجاز | E27: Makkah | G27: MEP Manager | H27: 46139 | I27: خدت رقم احمد ابو سيف ده MEP Manager في شركة انجاز و دي شركة MEP Sub Contactor في المشروع و كلمته و لسة مردش عليا بخصوص مشروع بوابة الملك سلمان | M27: {=_xlfn.LET(_xlpm.x,_xlfn.XLOOKUP(Hot_Leads[[#This Row],[Phone]],Dashboard!$M$44:$M$58,Dashboard!$J$44:$J$58,""),IF(_xlpm.x<>"",_xlpm.x,Hot_Leads[[#This Row],[Next Follow Up Notes]]))} -> 0 | N27: {=_xlfn.LET(_xlpm.x,_xlfn.XLOOKUP(Hot_Leads[[#This Row],[Phone]],Dashboard!$M$44:$M$58,Dashboard!$K$44:$K$58,""),_xlpm.orig,Hot_Leads[[#This Row],[Next Follow Up Date]],IF(_xlpm.x<>"",_xlpm.x,IF(OR(_xlpm.orig="",_xlpm.orig=0),"",_xlpm.orig)))}
A28: Ahmed Yasser | B28: 966540986497 | C28: واحة الرفاع | E28: Makkah | G28: MEP Manager | H28: 46139 | I28: ده فندق واحة الرفاع بيعملوا تجديدات من وقت للتاني و تحتيهم اكثر من فندق شغالين عليه و كلمته و مردش و هكلمه تاني انهاردة | M28: {=_xlfn.LET(_xlpm.x,_xlfn.XLOOKUP(Hot_Leads[[#This Row],[Phone]],Dashboard!$M$44:$M$58,Dashboard!$J$44:$J$58,""),IF(_xlpm.x<>"",_xlpm.x,Hot_Leads[[#This Row],[Next Follow Up Notes]]))} -> 0 | N28: {=_xlfn.LET(_xlpm.x,_xlfn.XLOOKUP(Hot_Leads[[#This Row],[Phone]],Dashboard!$M$44:$M$58,Dashboard!$K$44:$K$58,""),_xlpm.orig,Hot_Leads[[#This Row],[Next Follow Up Date]],IF(_xlpm.x<>"",_xlpm.x,IF(OR(_xlpm.orig="",_xlpm.orig=0),"",_xlpm.orig)))}
A29: Mohamed Radwan | M29: {=_xlfn.LET(_xlpm.x,_xlfn.XLOOKUP(Hot_Leads[[#This Row],[Phone]],Dashboard!$M$44:$M$58,Dashboard!$J$44:$J$58,""),IF(_xlpm.x<>"",_xlpm.x,Hot_Leads[[#This Row],[Next Follow Up Notes]]))} -> 0 | N29: {=_xlfn.LET(_xlpm.x,_xlfn.XLOOKUP(Hot_Leads[[#This Row],[Phone]],Dashboard!$M$44:$M$58,Dashboard!$K$44:$K$58,""),_xlpm.orig,Hot_Leads[[#This Row],[Next Follow Up Date]],IF(_xlpm.x<>"",_xlpm.x,IF(OR(_xlpm.orig="",_xlpm.orig=0),"",_xlpm.orig)))}
A30: Abdelrahman El-Kaffas | M30: {=_xlfn.LET(_xlpm.x,_xlfn.XLOOKUP(Hot_Leads[[#This Row],[Phone]],Dashboard!$M$44:$M$58,Dashboard!$J$44:$J$58,""),IF(_xlpm.x<>"",_xlpm.x,Hot_Leads[[#This Row],[Next Follow Up Notes]]))} -> 0 | N30: {=_xlfn.LET(_xlpm.x,_xlfn.XLOOKUP(Hot_Leads[[#This Row],[Phone]],Dashboard!$M$44:$M$58,Dashboard!$K$44:$K$58,""),_xlpm.orig,Hot_Leads[[#This Row],[Next Follow Up Date]],IF(_xlpm.x<>"",_xlpm.x,IF(OR(_xlpm.orig="",_xlpm.orig=0),"",_xlpm.orig)))}
A31: Sir Kumar Morgan | B31: 966548377568 | C31: Alsalama Hospital | E31: Jeddah | G31: Electrical Engineer | H31: 46140 | I31: كلمته عشان مستشفى السلامة عشان احدد معاه الميعاد بكرة الساعة 9 | M31: {=_xlfn.LET(_xlpm.x,_xlfn.XLOOKUP(Hot_Leads[[#This Row],[Phone]],Dashboard!$M$44:$M$58,Dashboard!$J$44:$J$58,""),IF(_xlpm.x<>"",_xlpm.x,Hot_Leads[[#This Row],[Next Follow Up Notes]]))} -> 0 | N31: {=_xlfn.LET(_xlpm.x,_xlfn.XLOOKUP(Hot_Leads[[#This Row],[Phone]],Dashboard!$M$44:$M$58,Dashboard!$K$44:$K$58,""),_xlpm.orig,Hot_Leads[[#This Row],[Next Follow Up Date]],IF(_xlpm.x<>"",_xlpm.x,IF(OR(_xlpm.orig="",_xlpm.orig=0),"",_xlpm.orig)))}
A32: Mohamed 3essa | B32: 966598803998 | C32: Honeywell | E32: Jeddah | G32: Onity Account Manager | H32: 46140 | I32: م/ عمير اداني رقمه اكلمه عشان انزل اقابله و اتعرف عليه و م اخد منه مشاريع الميتنج يوم الاحد القادم و هأكد عليه السبت | J32: كلمته الاحد بس مردش عليا | M32: {=_xlfn.LET(_xlpm.x,_xlfn.XLOOKUP(Hot_Leads[[#This Row],[Phone]],Dashboard!$M$44:$M$58,Dashboard!$J$44:$J$58,""),IF(_xlpm.x<>"",_xlpm.x,Hot_Leads[[#This Row],[Next Follow Up Notes]]))} -> كلمته الاحد بس مردش عليا | N32: {=_xlfn.LET(_xlpm.x,_xlfn.XLOOKUP(Hot_Leads[[#This Row],[Phone]],Dashboard!$M$44:$M$58,Dashboard!$K$44:$K$58,""),_xlpm.orig,Hot_Leads[[#This Row],[Next Follow Up Date]],IF(_xlpm.x<>"",_xlpm.x,IF(OR(_xlpm.orig="",_xlpm.orig=0),"",_xlpm.orig)))} -> 46146
A33: Abdallah Lutf | B33: 966573395135 | C33: Al-Jammaz | E33: Jeddah | F33: Abdullah.lutf@al-jammaz.com | G33: Account Manager | H33: 46141 | I33: روحت الايفنت بتاع اروبا الي هو ايفنت الجماز للتكنولوجيا ده موزع لبراندات كتير جدا | M33: {=_xlfn.LET(_xlpm.x,_xlfn.XLOOKUP(Hot_Leads[[#This Row],[Phone]],Dashboard!$M$44:$M$58,Dashboard!$J$44:$J$58,""),IF(_xlpm.x<>"",_xlpm.x,Hot_Leads[[#This Row],[Next Follow Up Notes]]))} -> 0 | N33: {=_xlfn.LET(_xlpm.x,_xlfn.XLOOKUP(Hot_Leads[[#This Row],[Phone]],Dashboard!$M$44:$M$58,Dashboard!$K$44:$K$58,""),_xlpm.orig,Hot_Leads[[#This Row],[Next Follow Up Date]],IF(_xlpm.x<>"",_xlpm.x,IF(OR(_xlpm.orig="",_xlpm.orig=0),"",_xlpm.orig)))}
A34: Hassan Samir Zino | B34: 966538599958 | C34: Honeywell | E34: Jeddah | F34: Hasan.zino@honeywell.com | G34: Senior Accounts Manager Hospitality | H34: 46141 | I34: حسن ده الي هيكون معايا في اي ميتنج يخص الفنادق الجديدة و القديمة في مكة و جدة و المدينة و تخصصه GRMS & KNX | M34: {=_xlfn.LET(_xlpm.x,_xlfn.XLOOKUP(Hot_Leads[[#This Row],[Phone]],Dashboard!$M$44:$M$58,Dashboard!$J$44:$J$58,""),IF(_xlpm.x<>"",_xlpm.x,Hot_Leads[[#This Row],[Next Follow Up Notes]]))} -> 0 | N34: {=_xlfn.LET(_xlpm.x,_xlfn.XLOOKUP(Hot_Leads[[#This Row],[Phone]],Dashboard!$M$44:$M$58,Dashboard!$K$44:$K$58,""),_xlpm.orig,Hot_Leads[[#This Row],[Next Follow Up Date]],IF(_xlpm.x<>"",_xlpm.x,IF(OR(_xlpm.orig="",_xlpm.orig=0),"",_xlpm.orig)))}
A35: Alaa | C35: Honeywell | E35: Jeddah | G35: BMS Manager | H35: 46141 | I35: مهندس علاء ده مدير ال BMS & PLC | J35: عاوز رقمه | M35: {=_xlfn.LET(_xlpm.x,_xlfn.XLOOKUP(Hot_Leads[[#This Row],[Phone]],Dashboard!$M$44:$M$58,Dashboard!$J$44:$J$58,""),IF(_xlpm.x<>"",_xlpm.x,Hot_Leads[[#This Row],[Next Follow Up Notes]]))} -> عاوز رقمه | N35: {=_xlfn.LET(_xlpm.x,_xlfn.XLOOKUP(Hot_Leads[[#This Row],[Phone]],Dashboard!$M$44:$M$58,Dashboard!$K$44:$K$58,""),_xlpm.orig,Hot_Leads[[#This Row],[Next Follow Up Date]],IF(_xlpm.x<>"",_xlpm.x,IF(OR(_xlpm.orig="",_xlpm.orig=0),"",_xlpm.orig)))}
A36: Mohamed Kahla | B36: 966536136430 | C36: Bits Arabia | E36: Jeddah | F36: mohamedkahla@bitsarabia.com | G36: Pre-Sales ICT Manager | H36: 46141 | I36: اتعرفت عليه في الايفنت و ممكن يكون فيه تواصل بينا مستمر عشان المشاريع لو ينفع نبدل مع بعض المشاريع دي | M36: {=_xlfn.LET(_xlpm.x,_xlfn.XLOOKUP(Hot_Leads[[#This Row],[Phone]],Dashboard!$M$44:$M$58,Dashboard!$J$44:$J$58,""),IF(_xlpm.x<>"",_xlpm.x,Hot_Leads[[#This Row],[Next Follow Up Notes]]))} -> 0 | N36: {=_xlfn.LET(_xlpm.x,_xlfn.XLOOKUP(Hot_Leads[[#This Row],[Phone]],Dashboard!$M$44:$M$58,Dashboard!$K$44:$K$58,""),_xlpm.orig,Hot_Leads[[#This Row],[Next Follow Up Date]],IF(_xlpm.x<>"",_xlpm.x,IF(OR(_xlpm.orig="",_xlpm.orig=0),"",_xlpm.orig)))}
A37: Mohamed Atef | B37: 966544411842 | C37: AlShamela - Riyadh | E37: Jeddah | H37: 46142 | I37: بعتله على الواتساب الميل بتاعي و البزنس كارد و قالي انه هيتابع معايا لو فيه اي مشاريع جديدة جاتله و ساب شركة الشاملة و راح شركة الرياض | M37: {=_xlfn.LET(_xlpm.x,_xlfn.XLOOKUP(Hot_Leads[[#This Row],[Phone]],Dashboard!$M$44:$M$58,Dashboard!$J$44:$J$58,""),IF(_xlpm.x<>"",_xlpm.x,Hot_Leads[[#This Row],[Next Follow Up Notes]]))} -> 0 | N37: {=_xlfn.LET(_xlpm.x,_xlfn.XLOOKUP(Hot_Leads[[#This Row],[Phone]],Dashboard!$M$44:$M$58,Dashboard!$K$44:$K$58,""),_xlpm.orig,Hot_Leads[[#This Row],[Next Follow Up Date]],IF(_xlpm.x<>"",_xlpm.x,IF(OR(_xlpm.orig="",_xlpm.orig=0),"",_xlpm.orig)))} -> 46149
A38: Ahmed Naserallah | B38: 966561333021 | C38: ALmawel Contracting | H38: 46142 | I38: كلمته و مكانش يعرفنا سألته على المشاريع بس دلوقتي مفيش حاجة و الاسبوع الجي هيكون فيه مشروع | J38: هتابع معاه الاسبوع الجي | M38: {=_xlfn.LET(_xlpm.x,_xlfn.XLOOKUP(Hot_Leads[[#This Row],[Phone]],Dashboard!$M$44:$M$58,Dashboard!$J$44:$J$58,""),IF(_xlpm.x<>"",_xlpm.x,Hot_Leads[[#This Row],[Next Follow Up Notes]]))} -> هتابع معاه الاسبوع الجي | N38: {=_xlfn.LET(_xlpm.x,_xlfn.XLOOKUP(Hot_Leads[[#This Row],[Phone]],Dashboard!$M$44:$M$58,Dashboard!$K$44:$K$58,""),_xlpm.orig,Hot_Leads[[#This Row],[Next Follow Up Date]],IF(_xlpm.x<>"",_xlpm.x,IF(OR(_xlpm.orig="",_xlpm.orig=0),"",_xlpm.orig)))} -> 46149
A39: Abdelrahman Rubei | B39: 966535326266 | C39: KAMC | H39: 46142 | I39: كلمته و مردش و بعتله على الواتساب عشان اتابع معاه لو فيه مشاريع | M39: {=_xlfn.LET(_xlpm.x,_xlfn.XLOOKUP(Hot_Leads[[#This Row],[Phone]],Dashboard!$M$44:$M$58,Dashboard!$J$44:$J$58,""),IF(_xlpm.x<>"",_xlpm.x,Hot_Leads[[#This Row],[Next Follow Up Notes]]))} -> 0 | N39: {=_xlfn.LET(_xlpm.x,_xlfn.XLOOKUP(Hot_Leads[[#This Row],[Phone]],Dashboard!$M$44:$M$58,Dashboard!$K$44:$K$58,""),_xlpm.orig,Hot_Leads[[#This Row],[Next Follow Up Date]],IF(_xlpm.x<>"",_xlpm.x,IF(OR(_xlpm.orig="",_xlpm.orig=0),"",_xlpm.orig)))}
A40: Sameh Saber | B40: 966568061671 | C40: Freyssinet | E40: Jeddah | F40: sameh.saber@fsa.com.sa | G40: Electrical Procurement Manager | H40: 46142 | I40: لسة متصل بيا دلوقتي و قالي ابعتلي Pre و هنتكلم تاني نتعرف على بعض اكتر | J40: Send Pre and follow up | M40: {=_xlfn.LET(_xlpm.x,_xlfn.XLOOKUP(Hot_Leads[[#This Row],[Phone]],Dashboard!$M$44:$M$58,Dashboard!$J$44:$J$58,""),IF(_xlpm.x<>"",_xlpm.x,Hot_Leads[[#This Row],[Next Follow Up Notes]]))} -> Send Pre and follow up | N40: {=_xlfn.LET(_xlpm.x,_xlfn.XLOOKUP(Hot_Leads[[#This Row],[Phone]],Dashboard!$M$44:$M$58,Dashboard!$K$44:$K$58,""),_xlpm.orig,Hot_Leads[[#This Row],[Next Follow Up Date]],IF(_xlpm.x<>"",_xlpm.x,IF(OR(_xlpm.orig="",_xlpm.orig=0),"",_xlpm.orig)))} -> 46145
A41: Mohamed Hanifa | B41: 966540654038 | C41: Alagamsi MHM | E41: Jeddah | F41: hanifa@almagamsi.com | G41: Project Manager | H41: 46144 | I41: طلب مني ديسكاونت كويس عشان هو بيجهز ال submittal بتاعه الاخير خلاص و ان شاء الله يكون المشروع معانا | J41: طلب مني ديسكاونت كويس عشان هو بيجهز ال submittal بتاعه الاخير خلاص و ان شاء الله يكون المشروع معانا | M41: {=_xlfn.LET(_xlpm.x,_xlfn.XLOOKUP(Hot_Leads[[#This Row],[Phone]],Dashboard!$M$44:$M$58,Dashboard!$J$44:$J$58,""),IF(_xlpm.x<>"",_xlpm.x,Hot_Leads[[#This Row],[Next Follow Up Notes]]))} -> طلب مني ديسكاونت كويس عشان هو بيجهز ال submittal بتاعه الاخير خلاص و ان شاء الله يكون المشروع معانا | N41: {=_xlfn.LET(_xlpm.x,_xlfn.XLOOKUP(Hot_Leads[[#This Row],[Phone]],Dashboard!$M$44:$M$58,Dashboard!$K$44:$K$58,""),_xlpm.orig,Hot_Leads[[#This Row],[Next Follow Up Date]],IF(_xlpm.x<>"",_xlpm.x,IF(OR(_xlpm.orig="",_xlpm.orig=0),"",_xlpm.orig)))}
A42: Abdelrahman Al-Shibi | B42: 966507220728 | C42: Rafa Gulf | E42: Khobar | F42: abdelrahman.alshibi@rafagulf.com | G42: Project Manager | H42: 46144 | I42: فيه مشروع اسمه Code 3 اتبعتلهم Technical Submittal و خلاص الاستشاري وافق عليه و مستني الابديت الاخير | J42: المشروع ده عبدالرحمن عبدالعيلم بيتابعه في الرياش | L42: Abdelrahman | M42: {=_xlfn.LET(_xlpm.x,_xlfn.XLOOKUP(Hot_Leads[[#This Row],[Phone]],Dashboard!$M$44:$M$58,Dashboard!$J$44:$J$58,""),IF(_xlpm.x<>"",_xlpm.x,Hot_Leads[[#This Row],[Next Follow Up Notes]]))} -> المشروع ده عبدالرحمن عبدالعيلم بيتابعه في الرياش | N42: {=_xlfn.LET(_xlpm.x,_xlfn.XLOOKUP(Hot_Leads[[#This Row],[Phone]],Dashboard!$M$44:$M$58,Dashboard!$K$44:$K$58,""),_xlpm.orig,Hot_Leads[[#This Row],[Next Follow Up Date]],IF(_xlpm.x<>"",_xlpm.x,IF(OR(_xlpm.orig="",_xlpm.orig=0),"",_xlpm.orig)))}
A43: Mohamed IKK | B43: 966564498774 | C43: Kabbani Construction Group | D43: https://share.google/BeqySgEuSwCLv1en5 | E43: Jeddah | F43: mohammadh.saleh@ikkgroup.com | G43: Procurement Manager | H43: 46144 | I43: كلمته يوم الاحد و قالي ابعتلي على الميل البروفايل بتاع الشركة و انا هخلي الشباب يحطوك في ال cc في اي مشروع | J43: تابع معاه تاني لو مردش عليك | M43: {=_xlfn.LET(_xlpm.x,_xlfn.XLOOKUP(Hot_Leads[[#This Row],[Phone]],Dashboard!$M$44:$M$58,Dashboard!$J$44:$J$58,""),IF(_xlpm.x<>"",_xlpm.x,Hot_Leads[[#This Row],[Next Follow Up Notes]]))} -> تابع معاه تاني لو مردش عليك | N43: {=_xlfn.LET(_xlpm.x,_xlfn.XLOOKUP(Hot_Leads[[#This Row],[Phone]],Dashboard!$M$44:$M$58,Dashboard!$K$44:$K$58,""),_xlpm.orig,Hot_Leads[[#This Row],[Next Follow Up Date]],IF(_xlpm.x<>"",_xlpm.x,IF(OR(_xlpm.orig="",_xlpm.orig=0),"",_xlpm.orig)))}
A44: Afroz Misk | B44: 966534939921 | C44: Jash | E44: Riyadh | H44: 46144 | I44: ده مهندس صالة الامير فيصل للفنون | M44: {=_xlfn.LET(_xlpm.x,_xlfn.XLOOKUP(Hot_Leads[[#This Row],[Phone]],Dashboard!$M$44:$M$58,Dashboard!$J$44:$J$58,""),IF(_xlpm.x<>"",_xlpm.x,Hot_Leads[[#This Row],[Next Follow Up Notes]]))} -> 0 | N44: {=_xlfn.LET(_xlpm.x,_xlfn.XLOOKUP(Hot_Leads[[#This Row],[Phone]],Dashboard!$M$44:$M$58,Dashboard!$K$44:$K$58,""),_xlpm.orig,Hot_Leads[[#This Row],[Next Follow Up Date]],IF(_xlpm.x<>"",_xlpm.x,IF(OR(_xlpm.orig="",_xlpm.orig=0),"",_xlpm.orig)))}
A45: Mo2nes Amr | B45: 966581074664 | C45: Creet | E45: Jeddah | F45: m.amr@creet.net | G45: Procurement Manager | H45: 46144 | I45: كلمته عشان اعرف الفلوس المتأخره هتتحول امتى و كمان عشان هم ليهم عندنا بضاعة | J45: مصطفى هزاع بيشوف اخر ابديت للبضاعه و كمان أمل بتشوف المستحقات بتاعتنا قد ايه | M45: {=_xlfn.LET(_xlpm.x,_xlfn.XLOOKUP(Hot_Leads[[#This Row],[Phone]],Dashboard!$M$44:$M$58,Dashboard!$J$44:$J$58,""),IF(_xlpm.x<>"",_xlpm.x,Hot_Leads[[#This Row],[Next Follow Up Notes]]))} -> مصطفى هزاع بيشوف اخر ابديت للبضاعه و كمان أمل بتشوف المستحقات بتاعتنا قد ايه | N45: {=_xlfn.LET(_xlpm.x,_xlfn.XLOOKUP(Hot_Leads[[#This Row],[Phone]],Dashboard!$M$44:$M$58,Dashboard!$K$44:$K$58,""),_xlpm.orig,Hot_Leads[[#This Row],[Next Follow Up Date]],IF(_xlpm.x<>"",_xlpm.x,IF(OR(_xlpm.orig="",_xlpm.orig=0),"",_xlpm.orig)))}
A46: Youssef Adwi | B46: 966554711520 | C46: IHCC | E46: Jeddah | F46: y.adwi@ihcc.sa | G46: Senior Tender Engineer | H46: 46144 | I46: قالي ان مشروع Western Tower ده مع المشتريات خلاص و هيبعتلي رقم حد منهم بكرة | J46: عاوز رقم حد من المشتريات | M46: {=_xlfn.LET(_xlpm.x,_xlfn.XLOOKUP(Hot_Leads[[#This Row],[Phone]],Dashboard!$M$44:$M$58,Dashboard!$J$44:$J$58,""),IF(_xlpm.x<>"",_xlpm.x,Hot_Leads[[#This Row],[Next Follow Up Notes]]))} -> عاوز رقم حد من المشتريات | N46: {=_xlfn.LET(_xlpm.x,_xlfn.XLOOKUP(Hot_Leads[[#This Row],[Phone]],Dashboard!$M$44:$M$58,Dashboard!$K$44:$K$58,""),_xlpm.orig,Hot_Leads[[#This Row],[Next Follow Up Date]],IF(_xlpm.x<>"",_xlpm.x,IF(OR(_xlpm.orig="",_xlpm.orig=0),"",_xlpm.orig)))} -> 46145
A47: Omar Alsaad | B47: 966549733284 | C47: Alsaad Contracting | D47: https://maps.app.goo.gl/c5pWiicmKMLBYKo58 | E47: Jeddah | F47: omar.abdullah@alsaad.com.sa | G47: Tender Engineer | H47: 46144 | I47: قالي انه هيجيبلي تفاصيل IMC بكرة و كمان فيه مشروع من سنتين و نص على حدود الاردن اسمه Zedca ده عبارة عن منافذ حدودية | J47: هكلمه بكره تاني عشان اعرف التفاصيل الي قالي عليها | M47: {=_xlfn.LET(_xlpm.x,_xlfn.XLOOKUP(Hot_Leads[[#This Row],[Phone]],Dashboard!$M$44:$M$58,Dashboard!$J$44:$J$58,""),IF(_xlpm.x<>"",_xlpm.x,Hot_Leads[[#This Row],[Next Follow Up Notes]]))} -> هكلمه بكره تاني عشان اعرف التفاصيل الي قالي عليها | N47: {=_xlfn.LET(_xlpm.x,_xlfn.XLOOKUP(Hot_Leads[[#This Row],[Phone]],Dashboard!$M$44:$M$58,Dashboard!$K$44:$K$58,""),_xlpm.orig,Hot_Leads[[#This Row],[Next Follow Up Date]],IF(_xlpm.x<>"",_xlpm.x,IF(OR(_xlpm.orig="",_xlpm.orig=0),"",_xlpm.orig)))} -> 46145
A48: Ibrahim Sabry | B48: 201111448448 | C48: Sedra Electric | G48: Sales Manager | H48: 46144 | I48: سألته على المشروع بتاع onity بس مفيش رد جديد لسة الراجل مش بيرد علينا | J48: هكلمه كمان 3 ايام كده اشوف ايه الجديد معاه | M48: {=_xlfn.LET(_xlpm.x,_xlfn.XLOOKUP(Hot_Leads[[#This Row],[Phone]],Dashboard!$M$44:$M$58,Dashboard!$J$44:$J$58,""),IF(_xlpm.x<>"",_xlpm.x,Hot_Leads[[#This Row],[Next Follow Up Notes]]))} -> مفيش جديد مش معاه مشاريع تانيه حاليا | N48: {=_xlfn.LET(_xlpm.x,_xlfn.XLOOKUP(Hot_Leads[[#This Row],[Phone]],Dashboard!$M$44:$M$58,Dashboard!$K$44:$K$58,""),_xlpm.orig,Hot_Leads[[#This Row],[Next Follow Up Date]],IF(_xlpm.x<>"",_xlpm.x,IF(OR(_xlpm.orig="",_xlpm.orig=0),"",_xlpm.orig)))} -> 46364
A49: Mohamed Arif | B49: 966509702995 | C49: IHCC | E49: Jeddah | H49: 46145 | I49: فيه كوتيشن مسعرينها معانا رقمها : q969.16.lcu و بيقولي انهم بعتوا ال submittal خلاص و مستنيين الفيدباك خلال اسبوعين | J49: كلمه كمان اسبوعين اعرف ايه الدنيا في المشروع ده | M49: {=_xlfn.LET(_xlpm.x,_xlfn.XLOOKUP(Hot_Leads[[#This Row],[Phone]],Dashboard!$M$44:$M$58,Dashboard!$J$44:$J$58,""),IF(_xlpm.x<>"",_xlpm.x,Hot_Leads[[#This Row],[Next Follow Up Notes]]))} -> كلمه كمان اسبوعين اعرف ايه الدنيا في المشروع ده | N49: {=_xlfn.LET(_xlpm.x,_xlfn.XLOOKUP(Hot_Leads[[#This Row],[Phone]],Dashboard!$M$44:$M$58,Dashboard!$K$44:$K$58,""),_xlpm.orig,Hot_Leads[[#This Row],[Next Follow Up Date]],IF(_xlpm.x<>"",_xlpm.x,IF(OR(_xlpm.orig="",_xlpm.orig=0),"",_xlpm.orig)))}
A50: Zubair | B50: 966597556284 | C50: IHCC | E50: Jeddah | G50: Procurement Engineer | H50: 46145 | I50: قالي انه مفيش مشاريع في الوقت الحالي و بخصوص ال BMS واحد من صحابة في الشغل هو الي ماشي في الحتة دي | J50: عاوز منه رقم صاحبه بتاع ال BMS و عاوز اتابع معاه كل اسبوع | M50: {=_xlfn.LET(_xlpm.x,_xlfn.XLOOKUP(Hot_Leads[[#This Row],[Phone]],Dashboard!$M$44:$M$58,Dashboard!$J$44:$J$58,""),IF(_xlpm.x<>"",_xlpm.x,Hot_Leads[[#This Row],[Next Follow Up Notes]]))} -> عاوز منه رقم صاحبه بتاع ال BMS و عاوز اتابع معاه كل اسبوع | N50: {=_xlfn.LET(_xlpm.x,_xlfn.XLOOKUP(Hot_Leads[[#This Row],[Phone]],Dashboard!$M$44:$M$58,Dashboard!$K$44:$K$58,""),_xlpm.orig,Hot_Leads[[#This Row],[Next Follow Up Date]],IF(_xlpm.x<>"",_xlpm.x,IF(OR(_xlpm.orig="",_xlpm.orig=0),"",_xlpm.orig)))}
A51: Omar El Hanoun | B51: 966531895117 | C51: MACC | F51: omer.elhanoun@macc-fm.com | G51: Procurement Engineer | H51: 46147 | I51: بيبعتلي في الاول مقطوعيات بس و دلوقتي معاه مشاريع و بتابع معاه كل اسبوع لو فيه حاجة جديدة | J51: كلمه يوم السبت و حاول تحدد معاه ميعاد تزوره فيه | M51: {=_xlfn.LET(_xlpm.x,_xlfn.XLOOKUP(Hot_Leads[[#This Row],[Phone]],Dashboard!$M$44:$M$58,Dashboard!$J$44:$J$58,""),IF(_xlpm.x<>"",_xlpm.x,Hot_Leads[[#This Row],[Next Follow Up Notes]]))} -> كلمه يوم السبت و حاول تحدد معاه ميعاد تزوره فيه | N51: {=_xlfn.LET(_xlpm.x,_xlfn.XLOOKUP(Hot_Leads[[#This Row],[Phone]],Dashboard!$M$44:$M$58,Dashboard!$K$44:$K$58,""),_xlpm.orig,Hot_Leads[[#This Row],[Next Follow Up Date]],IF(_xlpm.x<>"",_xlpm.x,IF(OR(_xlpm.orig="",_xlpm.orig=0),"",_xlpm.orig)))}
A52: Azazuddin Mohamed | B52: 966505520073 | C52: IHCC | E52: Jeddah | G52: BMS Manager | H52: 46146 | I52: بحدد معاه ميتنج عشان اروح ازوره في المكتب و اعرف المشاريع ال in hand معاهم بخصوص ال BMS في شركة IHCC | J52: حدد معاه ميتنج يوم الثلاثاء 6/5/2026 | M52: {=_xlfn.LET(_xlpm.x,_xlfn.XLOOKUP(Hot_Leads[[#This Row],[Phone]],Dashboard!$M$44:$M$58,Dashboard!$J$44:$J$58,""),IF(_xlpm.x<>"",_xlpm.x,Hot_Leads[[#This Row],[Next Follow Up Notes]]))} -> حدد معاه ميتنج يوم الثلاثاء 6/5/2026 | N52: {=_xlfn.LET(_xlpm.x,_xlfn.XLOOKUP(Hot_Leads[[#This Row],[Phone]],Dashboard!$M$44:$M$58,Dashboard!$K$44:$K$58,""),_xlpm.orig,Hot_Leads[[#This Row],[Next Follow Up Date]],IF(_xlpm.x<>"",_xlpm.x,IF(OR(_xlpm.orig="",_xlpm.orig=0),"",_xlpm.orig)))} -> 46148
A53: Abo Sultan | B53: 966557077244 | C53: Diamond House Developments | E53: Jeddah | G53: Site Supervisor | H53: 46146 | I53: ده مشرف موقع Diamond House و دول اكثر من فيلا ممكن ناخد التيار الخفيف منهم هكلمه و ارجع احط الفيدباك | J53: خد منه رقم حد من المهندسين او لوكيشن الشركة | M53: {=_xlfn.LET(_xlpm.x,_xlfn.XLOOKUP(Hot_Leads[[#This Row],[Phone]],Dashboard!$M$44:$M$58,Dashboard!$J$44:$J$58,""),IF(_xlpm.x<>"",_xlpm.x,Hot_Leads[[#This Row],[Next Follow Up Notes]]))} -> خد منه رقم حد من المهندسين او لوكيشن الشركة | N53: {=_xlfn.LET(_xlpm.x,_xlfn.XLOOKUP(Hot_Leads[[#This Row],[Phone]],Dashboard!$M$44:$M$58,Dashboard!$K$44:$K$58,""),_xlpm.orig,Hot_Leads[[#This Row],[Next Follow Up Date]],IF(_xlpm.x<>"",_xlpm.x,IF(OR(_xlpm.orig="",_xlpm.orig=0),"",_xlpm.orig)))} -> 46149
A54: شركة ابو الجدايل للمقاولات و الصيانة المحدودة | B54: - | C54: شركة ابو الجدايل للمقاولات و الصيانة المحدودة | E54: Jeddah | H54: 46146 | I54: محتاج اروح للشركة دي جدا لانها عندها كمية مشاريع مش طبيعية في جدة | J54: اوصل لحد من الشركة | M54: {=_xlfn.LET(_xlpm.x,_xlfn.XLOOKUP(Hot_Leads[[#This Row],[Phone]],Dashboard!$M$44:$M$58,Dashboard!$J$44:$J$58,""),IF(_xlpm.x<>"",_xlpm.x,Hot_Leads[[#This Row],[Next Follow Up Notes]]))} -> اوصل لحد من الشركة | N54: {=_xlfn.LET(_xlpm.x,_xlfn.XLOOKUP(Hot_Leads[[#This Row],[Phone]],Dashboard!$M$44:$M$58,Dashboard!$K$44:$K$58,""),_xlpm.orig,Hot_Leads[[#This Row],[Next Follow Up Date]],IF(_xlpm.x<>"",_xlpm.x,IF(OR(_xlpm.orig="",_xlpm.orig=0),"",_xlpm.orig)))}
A55: امانة جدة | B55: - | C55: امانة جدة | E55: Jeddah | H55: 46146 | I55: جهاز مدينة جدة و ده معاه كمية مشاريع كبيرة جدا جدا في ابحر الشمالية بس تخيل باقي مناطق جدة لازم اوصل لحد من هناك | J55: اوصل لحد من الشركة | M55: {=_xlfn.LET(_xlpm.x,_xlfn.XLOOKUP(Hot_Leads[[#This Row],[Phone]],Dashboard!$M$44:$M$58,Dashboard!$J$44:$J$58,""),IF(_xlpm.x<>"",_xlpm.x,Hot_Leads[[#This Row],[Next Follow Up Notes]]))} -> اوصل لحد من الشركة | N55: {=_xlfn.LET(_xlpm.x,_xlfn.XLOOKUP(Hot_Leads[[#This Row],[Phone]],Dashboard!$M$44:$M$58,Dashboard!$K$44:$K$58,""),_xlpm.orig,Hot_Leads[[#This Row],[Next Follow Up Date]],IF(_xlpm.x<>"",_xlpm.x,IF(OR(_xlpm.orig="",_xlpm.orig=0),"",_xlpm.orig)))}
A56: مباني جدة للتطوير العقاري | B56: - | C56: مباني جدة للتطوير العقاري | E56: Jeddah | H56: 46146 | I56: المشروع لسة ارض فاضية بس محتاج اعرف حد من الشركة عشان اقدر اوصل لحاجة | J56: اوصل لحد من الشركة | M56: {=_xlfn.LET(_xlpm.x,_xlfn.XLOOKUP(Hot_Leads[[#This Row],[Phone]],Dashboard!$M$44:$M$58,Dashboard!$J$44:$J$58,""),IF(_xlpm.x<>"",_xlpm.x,Hot_Leads[[#This Row],[Next Follow Up Notes]]))} -> اوصل لحد من الشركة | N56: {=_xlfn.LET(_xlpm.x,_xlfn.XLOOKUP(Hot_Leads[[#This Row],[Phone]],Dashboard!$M$44:$M$58,Dashboard!$K$44:$K$58,""),_xlpm.orig,Hot_Leads[[#This Row],[Next Follow Up Date]],IF(_xlpm.x<>"",_xlpm.x,IF(OR(_xlpm.orig="",_xlpm.orig=0),"",_xlpm.orig)))}
A57: برج جدة | B57: - | C57: برج جدة | E57: Jeddah | H57: 46146 | I57: حاولت اخش معرفتش و قالولي هتروح منطقة الحمدانية هتلاقي هناك ادارة برج جده شوف انت تعرف تخش هناك ازاي و تجيب شغلك كله من هناك | J57: اوصل لحد من الشركة | M57: {=_xlfn.LET(_xlpm.x,_xlfn.XLOOKUP(Hot_Leads[[#This Row],[Phone]],Dashboard!$M$44:$M$58,Dashboard!$J$44:$J$58,""),IF(_xlpm.x<>"",_xlpm.x,Hot_Leads[[#This Row],[Next Follow Up Notes]]))} -> اوصل لحد من الشركة | N57: {=_xlfn.LET(_xlpm.x,_xlfn.XLOOKUP(Hot_Leads[[#This Row],[Phone]],Dashboard!$M$44:$M$58,Dashboard!$K$44:$K$58,""),_xlpm.orig,Hot_Leads[[#This Row],[Next Follow Up Date]],IF(_xlpm.x<>"",_xlpm.x,IF(OR(_xlpm.orig="",_xlpm.orig=0),"",_xlpm.orig)))}
A58: Ayan Real Estate | B58: - | C58: Ayan Real Estate | E58: Jeddah | H58: 46146 | I58: ده كان من ال Hunting عندهم مشروع فلل فقط و محتاج اوصل لحد من هناك صاحب الشركة اسمه سعد الغامدي | J58: اوصل لحد من الشركة | M58: {=_xlfn.LET(_xlpm.x,_xlfn.XLOOKUP(Hot_Leads[[#This Row],[Phone]],Dashboard!$M$44:$M$58,Dashboard!$J$44:$J$58,""),IF(_xlpm.x<>"",_xlpm.x,Hot_Leads[[#This Row],[Next Follow Up Notes]]))} -> اوصل لحد من الشركة | N58: {=_xlfn.LET(_xlpm.x,_xlfn.XLOOKUP(Hot_Leads[[#This Row],[Phone]],Dashboard!$M$44:$M$58,Dashboard!$K$44:$K$58,""),_xlpm.orig,Hot_Leads[[#This Row],[Next Follow Up Date]],IF(_xlpm.x<>"",_xlpm.x,IF(OR(_xlpm.orig="",_xlpm.orig=0),"",_xlpm.orig)))}
A59: Ehab GRC | B59: 966582792050 | C59: GRC | E59: Jeddah | H59: 46148 | I59: ده معاه المشاريع الي جابها مهندس فراس و المشاريع دي مهمة اوي و الراجل مستعجل عليها جدا جدا | J59: محتاج اتابع المشاريع الي اترفعت هتخلص امتى ضروري جدا بحد اقصى يوم السسبت | M59: {=_xlfn.LET(_xlpm.x,_xlfn.XLOOKUP(Hot_Leads[[#This Row],[Phone]],Dashboard!$M$44:$M$58,Dashboard!$J$44:$J$58,""),IF(_xlpm.x<>"",_xlpm.x,Hot_Leads[[#This Row],[Next Follow Up Notes]]))} -> محتاج اتابع المشاريع الي اترفعت هتخلص امتى ضروري جدا بحد اقصى يوم السسبت | N59: {=_xlfn.LET(_xlpm.x,_xlfn.XLOOKUP(Hot_Leads[[#This Row],[Phone]],Dashboard!$M$44:$M$58,Dashboard!$K$44:$K$58,""),_xlpm.orig,Hot_Leads[[#This Row],[Next Follow Up Date]],IF(_xlpm.x<>"",_xlpm.x,IF(OR(_xlpm.orig="",_xlpm.orig=0),"",_xlpm.orig)))}
A60: Khaled Hussain | B60: 966537929837 | C60: Creet | E60: Jeddah | G60: Project Manager | H60: 46147 | I60: معاه مشروع فندق Renovation و محتاج Low Current Systems و كمان GRMS وصلت معاه لاني بجيب سعر من Legrand , Schneider , EAE , Incomm و مستعجل على المشروع جدا اخر يوم هو يوم الاحد و ده هو عاوز كوميشن لنفسه عشان المشروع ده بره شركة Creet | J60: تابع الكوتيشن | M60: {=_xlfn.LET(_xlpm.x,_xlfn.XLOOKUP(Hot_Leads[[#This Row],[Phone]],Dashboard!$M$44:$M$58,Dashboard!$J$44:$J$58,""),IF(_xlpm.x<>"",_xlpm.x,Hot_Leads[[#This Row],[Next Follow Up Notes]]))} -> تابع الكوتيشن | N60: {=_xlfn.LET(_xlpm.x,_xlfn.XLOOKUP(Hot_Leads[[#This Row],[Phone]],Dashboard!$M$44:$M$58,Dashboard!$K$44:$K$58,""),_xlpm.orig,Hot_Leads[[#This Row],[Next Follow Up Date]],IF(_xlpm.x<>"",_xlpm.x,IF(OR(_xlpm.orig="",_xlpm.orig=0),"",_xlpm.orig)))}
A61: Mohamed Ramadan | B61: 966533315768 | C61: ACUD | E61: Jeddah | G61: Procurement Manager | H61: 46147 | I61: ده معاه الباكدج بتاعت مشروع موطن مسار و بعتله ال Pre Qualification بتاعتنا و قالي اول ما هبص عليها هبعتلك الباكدج عشان تسعرها على طول | J61: Follow Up | M61: {=_xlfn.LET(_xlpm.x,_xlfn.XLOOKUP(Hot_Leads[[#This Row],[Phone]],Dashboard!$M$44:$M$58,Dashboard!$J$44:$J$58,""),IF(_xlpm.x<>"",_xlpm.x,Hot_Leads[[#This Row],[Next Follow Up Notes]]))} -> Follow Up | N61: {=_xlfn.LET(_xlpm.x,_xlfn.XLOOKUP(Hot_Leads[[#This Row],[Phone]],Dashboard!$M$44:$M$58,Dashboard!$K$44:$K$58,""),_xlpm.orig,Hot_Leads[[#This Row],[Next Follow Up Date]],IF(_xlpm.x<>"",_xlpm.x,IF(OR(_xlpm.orig="",_xlpm.orig=0),"",_xlpm.orig)))}
A62: Raneem Schneider | B62: 966549065163 | C62: Schneider GRMS | E62: Riyadh | G62: Tender Engineer | H62: 46152 | I62: بتابع معاها مشروع Rosemond عشان تسعرلي الداتات بتاعتي | J62: Waiting for my reply on the quotation | M62: {=_xlfn.LET(_xlpm.x,_xlfn.XLOOKUP(Hot_Leads[[#This Row],[Phone]],Dashboard!$M$44:$M$58,Dashboard!$J$44:$J$58,""),IF(_xlpm.x<>"",_xlpm.x,Hot_Leads[[#This Row],[Next Follow Up Notes]]))} -> Waiting for my reply on the quotation | N62: {=_xlfn.LET(_xlpm.x,_xlfn.XLOOKUP(Hot_Leads[[#This Row],[Phone]],Dashboard!$M$44:$M$58,Dashboard!$K$44:$K$58,""),_xlpm.orig,Hot_Leads[[#This Row],[Next Follow Up Date]],IF(_xlpm.x<>"",_xlpm.x,IF(OR(_xlpm.orig="",_xlpm.orig=0),"",_xlpm.orig)))}
A63: Lo2ai | B63: 966541053223 | C63: SATCO | E63: Riyadh | G63: MEP Manager | H63: 46152 | I63: محتاج سعر الكويتشن عشان الاصلاحات الي هتحصل عندهم في الموقع | J63: Send him the quotation Urgently | M63: {=_xlfn.LET(_xlpm.x,_xlfn.XLOOKUP(Hot_Leads[[#This Row],[Phone]],Dashboard!$M$44:$M$58,Dashboard!$J$44:$J$58,""),IF(_xlpm.x<>"",_xlpm.x,Hot_Leads[[#This Row],[Next Follow Up Notes]]))} -> Send him the quotation Urgently | N63: {=_xlfn.LET(_xlpm.x,_xlfn.XLOOKUP(Hot_Leads[[#This Row],[Phone]],Dashboard!$M$44:$M$58,Dashboard!$K$44:$K$58,""),_xlpm.orig,Hot_Leads[[#This Row],[Next Follow Up Date]],IF(_xlpm.x<>"",_xlpm.x,IF(OR(_xlpm.orig="",_xlpm.orig=0),"",_xlpm.orig)))}
A64: Emad Khater | B64: 966573044009 | C64: شركة هاني رضوان | E64: Jeddah | G64: MEP Manager | H64: 46152 | I64: ده كان Site hunting بس للاسف خلصوا المشروع بالكامل و خدت رقمه اكلمه عشان لو فيه مشاريع جديدة جاية | J64: Follow Up | M64: {=_xlfn.LET(_xlpm.x,_xlfn.XLOOKUP(Hot_Leads[[#This Row],[Phone]],Dashboard!$M$44:$M$58,Dashboard!$J$44:$J$58,""),IF(_xlpm.x<>"",_xlpm.x,Hot_Leads[[#This Row],[Next Follow Up Notes]]))} -> Follow Up | N64: {=_xlfn.LET(_xlpm.x,_xlfn.XLOOKUP(Hot_Leads[[#This Row],[Phone]],Dashboard!$M$44:$M$58,Dashboard!$K$44:$K$58,""),_xlpm.orig,Hot_Leads[[#This Row],[Next Follow Up Date]],IF(_xlpm.x<>"",_xlpm.x,IF(OR(_xlpm.orig="",_xlpm.orig=0),"",_xlpm.orig)))}
A65: Hani Roberto | B65: 966535501124 | C65: First Fix | E65: Jeddah | G65: Procurement Manager | H65: 46152 | I65: ده مشروع مستشفى العرب و للاسف ملحقناش نخشه خلصوا المشروع من بره على طول مع شركات sebca - Top 10 - MTTS | J65: Follow up Next Week | M65: {=_xlfn.LET(_xlpm.x,_xlfn.XLOOKUP(Hot_Leads[[#This Row],[Phone]],Dashboard!$M$44:$M$58,Dashboard!$J$44:$J$58,""),IF(_xlpm.x<>"",_xlpm.x,Hot_Leads[[#This Row],[Next Follow Up Notes]]))} -> Follow up Next Week | N65: {=_xlfn.LET(_xlpm.x,_xlfn.XLOOKUP(Hot_Leads[[#This Row],[Phone]],Dashboard!$M$44:$M$58,Dashboard!$K$44:$K$58,""),_xlpm.orig,Hot_Leads[[#This Row],[Next Follow Up Date]],IF(_xlpm.x<>"",_xlpm.x,IF(OR(_xlpm.orig="",_xlpm.orig=0),"",_xlpm.orig)))}
A66: Mohamed Hazem | B66: 966541554364 | C66: Schneider GRMS | E66: Riyadh | G66: Technical Office Manager GRMS | H66: 46153 | I66: بعتلي المشروع اخيرا و مستني منه الديسكاونت كمان لما ناخد المشروع منهم | J66: مستني الديسكاونت لما اقعد مع العميل نفسه هناك | M66: {=_xlfn.LET(_xlpm.x,_xlfn.XLOOKUP(Hot_Leads[[#This Row],[Phone]],Dashboard!$M$44:$M$58,Dashboard!$J$44:$J$58,""),IF(_xlpm.x<>"",_xlpm.x,Hot_Leads[[#This Row],[Next Follow Up Notes]]))} -> مستني الديسكاونت لما اقعد مع العميل نفسه هناك | N66: {=_xlfn.LET(_xlpm.x,_xlfn.XLOOKUP(Hot_Leads[[#This Row],[Phone]],Dashboard!$M$44:$M$58,Dashboard!$K$44:$K$58,""),_xlpm.orig,Hot_Leads[[#This Row],[Next Follow Up Date]],IF(_xlpm.x<>"",_xlpm.x,IF(OR(_xlpm.orig="",_xlpm.orig=0),"",_xlpm.orig)))}
A67: Ayman Aburub | B67: 966581469699 | C67: KFOCO | F67: ak@kfoco.com | M67: {=_xlfn.LET(_xlpm.x,_xlfn.XLOOKUP(Hot_Leads[[#This Row],[Phone]],Dashboard!$M$44:$M$58,Dashboard!$J$44:$J$58,""),IF(_xlpm.x<>"",_xlpm.x,Hot_Leads[[#This Row],[Next Follow Up Notes]]))} -> 0 | N67: {=_xlfn.LET(_xlpm.x,_xlfn.XLOOKUP(Hot_Leads[[#This Row],[Phone]],Dashboard!$M$44:$M$58,Dashboard!$K$44:$K$58,""),_xlpm.orig,Hot_Leads[[#This Row],[Next Follow Up Date]],IF(_xlpm.x<>"",_xlpm.x,IF(OR(_xlpm.orig="",_xlpm.orig=0),"",_xlpm.orig)))}
A68: Hamdy Abdelrasoul | B68: 201014492936 | C68: Dar Al-Kahrabaa | F68: hamdyabdelrasoul@daralkahrbaa.com | G68: CEO | H68: 46163 | I68: طلبت منه يجي يعمل معاينه للمشروع بتاع Rosemond و جه بالفعل و عمل المعاينه و لسة مبعتلناش السعر بتاعه عاوز مني BOQ بكامل الشغل المطلوب عشان يعرف يسعر المشروع - و بعتله مشروع تاني اسمه KEC Cluster 2 المشروع ده السكوب بتاعه اضاءة و ارضي بس بعتهوله و مستني منه ابديت | M68: {=_xlfn.LET(_xlpm.x,_xlfn.XLOOKUP(Hot_Leads[[#This Row],[Phone]],Dashboard!$M$44:$M$58,Dashboard!$J$44:$J$58,""),IF(_xlpm.x<>"",_xlpm.x,Hot_Leads[[#This Row],[Next Follow Up Notes]]))} -> 0 | N68: {=_xlfn.LET(_xlpm.x,_xlfn.XLOOKUP(Hot_Leads[[#This Row],[Phone]],Dashboard!$M$44:$M$58,Dashboard!$K$44:$K$58,""),_xlpm.orig,Hot_Leads[[#This Row],[Next Follow Up Date]],IF(_xlpm.x<>"",_xlpm.x,IF(OR(_xlpm.orig="",_xlpm.orig=0),"",_xlpm.orig)))}
A69: Abdelrahman United | B69: 966500605363 | C69: United Hospital | G69: Maintenance Engineer | H69: 46159 | I69: قالي كلمني بعد العيد هيحتاج سيستم المستشفى الي انا عامله ده | M69: {=_xlfn.LET(_xlpm.x,_xlfn.XLOOKUP(Hot_Leads[[#This Row],[Phone]],Dashboard!$M$44:$M$58,Dashboard!$J$44:$J$58,""),IF(_xlpm.x<>"",_xlpm.x,Hot_Leads[[#This Row],[Next Follow Up Notes]]))} -> 0 | N69: {=_xlfn.LET(_xlpm.x,_xlfn.XLOOKUP(Hot_Leads[[#This Row],[Phone]],Dashboard!$M$44:$M$58,Dashboard!$K$44:$K$58,""),_xlpm.orig,Hot_Leads[[#This Row],[Next Follow Up Date]],IF(_xlpm.x<>"",_xlpm.x,IF(OR(_xlpm.orig="",_xlpm.orig=0),"",_xlpm.orig)))}
A70: Mohamed Babik | B70: 966596223487 | C70: مركز مكة الطبي | E70: Makkah | G70: Maintenance Engineer | H70: 46161 | I70: قالي انه محتاج حد يشتغل Honeywell في المستشفى و قالي ان فيه غرف جديدة و غرف بتتجدد و وريته السيستم بتاعنا و قالي انه فعلا محتاج حاجة زي كده بس قالي بعد العيد نتكلم | M70: {=_xlfn.LET(_xlpm.x,_xlfn.XLOOKUP(Hot_Leads[[#This Row],[Phone]],Dashboard!$M$44:$M$58,Dashboard!$J$44:$J$58,""),IF(_xlpm.x<>"",_xlpm.x,Hot_Leads[[#This Row],[Next Follow Up Notes]]))} -> 0 | N70: {=_xlfn.LET(_xlpm.x,_xlfn.XLOOKUP(Hot_Leads[[#This Row],[Phone]],Dashboard!$M$44:$M$58,Dashboard!$K$44:$K$58,""),_xlpm.orig,Hot_Leads[[#This Row],[Next Follow Up Date]],IF(_xlpm.x<>"",_xlpm.x,IF(OR(_xlpm.orig="",_xlpm.orig=0),"",_xlpm.orig)))}
A71: Mohamed Assef | B71: 966509409233 | C71: مستشفى السعودي الالماني | E71: Makkah | G71: Maintenance Engineer | H71: 46162 | I71: ده مدير الصيانة في السعودي الالماني قالي انه محتاج السيستم ده برضه جدا و عاوزين نشتغل معاهم في الاكسيس كده و نظبطها سوا و قالي ان فيه واحد اسمه حاتم في فرع السعودي الالماني الجديد في جده و الراجل ده مهم جدا اني اكلمه عشان نخش معاهم في الباكدج مستخدمين BMS johnson , Access Honeywell , PAVA EATON | M71: {=_xlfn.LET(_xlpm.x,_xlfn.XLOOKUP(Hot_Leads[[#This Row],[Phone]],Dashboard!$M$44:$M$58,Dashboard!$J$44:$J$58,""),IF(_xlpm.x<>"",_xlpm.x,Hot_Leads[[#This Row],[Next Follow Up Notes]]))} -> 0 | N71: {=_xlfn.LET(_xlpm.x,_xlfn.XLOOKUP(Hot_Leads[[#This Row],[Phone]],Dashboard!$M$44:$M$58,Dashboard!$K$44:$K$58,""),_xlpm.orig,Hot_Leads[[#This Row],[Next Follow Up Date]],IF(_xlpm.x<>"",_xlpm.x,IF(OR(_xlpm.orig="",_xlpm.orig=0),"",_xlpm.orig)))}
A72: Amr MK | B72: 966553205344 | C72: MK Honeywell | H72: 46162 | I72: ده سيلز ل MK by Honeywell | M72: {=_xlfn.LET(_xlpm.x,_xlfn.XLOOKUP(Hot_Leads[[#This Row],[Phone]],Dashboard!$M$44:$M$58,Dashboard!$J$44:$J$58,""),IF(_xlpm.x<>"",_xlpm.x,Hot_Leads[[#This Row],[Next Follow Up Notes]]))} -> 0 | N72: {=_xlfn.LET(_xlpm.x,_xlfn.XLOOKUP(Hot_Leads[[#This Row],[Phone]],Dashboard!$M$44:$M$58,Dashboard!$K$44:$K$58,""),_xlpm.orig,Hot_Leads[[#This Row],[Next Follow Up Date]],IF(_xlpm.x<>"",_xlpm.x,IF(OR(_xlpm.orig="",_xlpm.orig=0),"",_xlpm.orig)))}
A73: Ibrahim Aboradi | B73: 966546881473 | C73: GTS | H73: 46162 | I73: محتاج خصم على مشروع مع عبدالرحمن و بيكلمني تاني كتير عشان الخصم ده ضروري بالنسبة ليه | M73: {=_xlfn.LET(_xlpm.x,_xlfn.XLOOKUP(Hot_Leads[[#This Row],[Phone]],Dashboard!$M$44:$M$58,Dashboard!$J$44:$J$58,""),IF(_xlpm.x<>"",_xlpm.x,Hot_Leads[[#This Row],[Next Follow Up Notes]]))} -> 0 | N73: {=_xlfn.LET(_xlpm.x,_xlfn.XLOOKUP(Hot_Leads[[#This Row],[Phone]],Dashboard!$M$44:$M$58,Dashboard!$K$44:$K$58,""),_xlpm.orig,Hot_Leads[[#This Row],[Next Follow Up Date]],IF(_xlpm.x<>"",_xlpm.x,IF(OR(_xlpm.orig="",_xlpm.orig=0),"",_xlpm.orig)))}
A74: Mazen Vision | B74: 966547160894 | C74: Vision Contracting | E74: Jeddah | F74: m.hassan@vision-cc.com | G74: Tender Engineer | H74: 46176 | M74: {=_xlfn.LET(_xlpm.x,_xlfn.XLOOKUP(Hot_Leads[[#This Row],[Phone]],Dashboard!$M$44:$M$58,Dashboard!$J$44:$J$58,""),IF(_xlpm.x<>"",_xlpm.x,Hot_Leads[[#This Row],[Next Follow Up Notes]]))} -> 0 | N74: {=_xlfn.LET(_xlpm.x,_xlfn.XLOOKUP(Hot_Leads[[#This Row],[Phone]],Dashboard!$M$44:$M$58,Dashboard!$K$44:$K$58,""),_xlpm.orig,Hot_Leads[[#This Row],[Next Follow Up Date]],IF(_xlpm.x<>"",_xlpm.x,IF(OR(_xlpm.orig="",_xlpm.orig=0),"",_xlpm.orig)))}
A75: Hashem Creet | B75: 966540419448 | C75: Creet | M75: {=_xlfn.LET(_xlpm.x,_xlfn.XLOOKUP(Hot_Leads[[#This Row],[Phone]],Dashboard!$M$44:$M$58,Dashboard!$J$44:$J$58,""),IF(_xlpm.x<>"",_xlpm.x,Hot_Leads[[#This Row],[Next Follow Up Notes]]))} -> 0 | N75: {=_xlfn.LET(_xlpm.x,_xlfn.XLOOKUP(Hot_Leads[[#This Row],[Phone]],Dashboard!$M$44:$M$58,Dashboard!$K$44:$K$58,""),_xlpm.orig,Hot_Leads[[#This Row],[Next Follow Up Date]],IF(_xlpm.x<>"",_xlpm.x,IF(OR(_xlpm.orig="",_xlpm.orig=0),"",_xlpm.orig)))}
A76: Mohamed Desouky | B76: 966551514407 | C76: Al Mardoof Contracting | E76: Madinah | F76: mohammed.desouky@almardoof.com | H76: 46180 | M76: {=_xlfn.LET(_xlpm.x,_xlfn.XLOOKUP(Hot_Leads[[#This Row],[Phone]],Dashboard!$M$44:$M$58,Dashboard!$J$44:$J$58,""),IF(_xlpm.x<>"",_xlpm.x,Hot_Leads[[#This Row],[Next Follow Up Notes]]))} -> 0 | N76: {=_xlfn.LET(_xlpm.x,_xlfn.XLOOKUP(Hot_Leads[[#This Row],[Phone]],Dashboard!$M$44:$M$58,Dashboard!$K$44:$K$58,""),_xlpm.orig,Hot_Leads[[#This Row],[Next Follow Up Date]],IF(_xlpm.x<>"",_xlpm.x,IF(OR(_xlpm.orig="",_xlpm.orig=0),"",_xlpm.orig)))}
A77: Samy Elsaid | B77: 966504612747 | C77: AHC - شركة انشاءات الافاق المتقدمة | E77: Jeddah | F77: seradwan@ahc-contracting.com | G77: Project Manager | H77: 46183 | I77: ده مدير مشروع مستشفى سليمان فقيه بمكة و لسة المشروع بدري عليه مفيش رسومات ولا اي حاجة لسة في مرحلة الحفر و مش معاهم مشاريع تانيه كل الباقي خلاص بيتسلم | M77: {=_xlfn.LET(_xlpm.x,_xlfn.XLOOKUP(Hot_Leads[[#This Row],[Phone]],Dashboard!$M$44:$M$58,Dashboard!$J$44:$J$58,""),IF(_xlpm.x<>"",_xlpm.x,Hot_Leads[[#This Row],[Next Follow Up Notes]]))} -> 0 | N77: {=_xlfn.LET(_xlpm.x,_xlfn.XLOOKUP(Hot_Leads[[#This Row],[Phone]],Dashboard!$M$44:$M$58,Dashboard!$K$44:$K$58,""),_xlpm.orig,Hot_Leads[[#This Row],[Next Follow Up Date]],IF(_xlpm.x<>"",_xlpm.x,IF(OR(_xlpm.orig="",_xlpm.orig=0),"",_xlpm.orig)))}
A78: Mahmoud ADEX | B78: 966547794011 | C78: ADEX | G78: MEP Engineer | H78: 46221 | I78: روحتله السايت و بعتله البروفايل و مستني منه ال RFQ | M78: {=_xlfn.LET(_xlpm.x,_xlfn.XLOOKUP(Hot_Leads[[#This Row],[Phone]],Dashboard!$M$44:$M$58,Dashboard!$J$44:$J$58,""),IF(_xlpm.x<>"",_xlpm.x,Hot_Leads[[#This Row],[Next Follow Up Notes]]))} -> 0 | N78: {=_xlfn.LET(_xlpm.x,_xlfn.XLOOKUP(Hot_Leads[[#This Row],[Phone]],Dashboard!$M$44:$M$58,Dashboard!$K$44:$K$58,""),_xlpm.orig,Hot_Leads[[#This Row],[Next Follow Up Date]],IF(_xlpm.x<>"",_xlpm.x,IF(OR(_xlpm.orig="",_xlpm.orig=0),"",_xlpm.orig)))}
A79: HAZEM KHALIL | B79: +966 54 5660067 | C79: ARABIAN CONSTRUCTION COMPANY - ACC | H79: 46221 | M79: {=_xlfn.LET(_xlpm.x,_xlfn.XLOOKUP(Hot_Leads[[#This Row],[Phone]],Dashboard!$M$44:$M$58,Dashboard!$J$44:$J$58,""),IF(_xlpm.x<>"",_xlpm.x,Hot_Leads[[#This Row],[Next Follow Up Notes]]))} -> 0 | N79: {=_xlfn.LET(_xlpm.x,_xlfn.XLOOKUP(Hot_Leads[[#This Row],[Phone]],Dashboard!$M$44:$M$58,Dashboard!$K$44:$K$58,""),_xlpm.orig,Hot_Leads[[#This Row],[Next Follow Up Date]],IF(_xlpm.x<>"",_xlpm.x,IF(OR(_xlpm.orig="",_xlpm.orig=0),"",_xlpm.orig)))}
A80: AYMAN ISMAIL | B80: +966 55 5010745 | C80: SAUDI DEVELOPMENT COMPANY | H80: 46221 | M80: {=_xlfn.LET(_xlpm.x,_xlfn.XLOOKUP(Hot_Leads[[#This Row],[Phone]],Dashboard!$M$44:$M$58,Dashboard!$J$44:$J$58,""),IF(_xlpm.x<>"",_xlpm.x,Hot_Leads[[#This Row],[Next Follow Up Notes]]))} -> 0 | N80: {=_xlfn.LET(_xlpm.x,_xlfn.XLOOKUP(Hot_Leads[[#This Row],[Phone]],Dashboard!$M$44:$M$58,Dashboard!$K$44:$K$58,""),_xlpm.orig,Hot_Leads[[#This Row],[Next Follow Up Date]],IF(_xlpm.x<>"",_xlpm.x,IF(OR(_xlpm.orig="",_xlpm.orig=0),"",_xlpm.orig)))}
A81: ASHRAF AMEIRAH | B81: +966 50 6660287 | C81: EL SEIF ENGINEERING | H81: 46221 | M81: {=_xlfn.LET(_xlpm.x,_xlfn.XLOOKUP(Hot_Leads[[#This Row],[Phone]],Dashboard!$M$44:$M$58,Dashboard!$J$44:$J$58,""),IF(_xlpm.x<>"",_xlpm.x,Hot_Leads[[#This Row],[Next Follow Up Notes]]))} -> 0 | N81: {=_xlfn.LET(_xlpm.x,_xlfn.XLOOKUP(Hot_Leads[[#This Row],[Phone]],Dashboard!$M$44:$M$58,Dashboard!$K$44:$K$58,""),_xlpm.orig,Hot_Leads[[#This Row],[Next Follow Up Date]],IF(_xlpm.x<>"",_xlpm.x,IF(OR(_xlpm.orig="",_xlpm.orig=0),"",_xlpm.orig)))}
A82: OBAID AL BAYED | B82: +966 53 1327771 | C82: NESMA & PARTNERS | H82: 46221 | M82: {=_xlfn.LET(_xlpm.x,_xlfn.XLOOKUP(Hot_Leads[[#This Row],[Phone]],Dashboard!$M$44:$M$58,Dashboard!$J$44:$J$58,""),IF(_xlpm.x<>"",_xlpm.x,Hot_Leads[[#This Row],[Next Follow Up Notes]]))} -> 0 | N82: {=_xlfn.LET(_xlpm.x,_xlfn.XLOOKUP(Hot_Leads[[#This Row],[Phone]],Dashboard!$M$44:$M$58,Dashboard!$K$44:$K$58,""),_xlpm.orig,Hot_Leads[[#This Row],[Next Follow Up Date]],IF(_xlpm.x<>"",_xlpm.x,IF(OR(_xlpm.orig="",_xlpm.orig=0),"",_xlpm.orig)))}
A83: Yahia Jamal | B83: +966 50 4656703 | C83: AL BAWANI | H83: 46221 | M83: {=_xlfn.LET(_xlpm.x,_xlfn.XLOOKUP(Hot_Leads[[#This Row],[Phone]],Dashboard!$M$44:$M$58,Dashboard!$J$44:$J$58,""),IF(_xlpm.x<>"",_xlpm.x,Hot_Leads[[#This Row],[Next Follow Up Notes]]))} -> 0 | N83: {=_xlfn.LET(_xlpm.x,_xlfn.XLOOKUP(Hot_Leads[[#This Row],[Phone]],Dashboard!$M$44:$M$58,Dashboard!$K$44:$K$58,""),_xlpm.orig,Hot_Leads[[#This Row],[Next Follow Up Date]],IF(_xlpm.x<>"",_xlpm.x,IF(OR(_xlpm.orig="",_xlpm.orig=0),"",_xlpm.orig)))}
A84: فرسان نماء العقارية | B84: 920018200 | C84: فرسان نماء العقارية | E84: Makkah | H84: 46221 | M84: {=_xlfn.LET(_xlpm.x,_xlfn.XLOOKUP(Hot_Leads[[#This Row],[Phone]],Dashboard!$M$44:$M$58,Dashboard!$J$44:$J$58,""),IF(_xlpm.x<>"",_xlpm.x,Hot_Leads[[#This Row],[Next Follow Up Notes]]))} -> 0 | N84: {=_xlfn.LET(_xlpm.x,_xlfn.XLOOKUP(Hot_Leads[[#This Row],[Phone]],Dashboard!$M$44:$M$58,Dashboard!$K$44:$K$58,""),_xlpm.orig,Hot_Leads[[#This Row],[Next Follow Up Date]],IF(_xlpm.x<>"",_xlpm.x,IF(OR(_xlpm.orig="",_xlpm.orig=0),"",_xlpm.orig)))}
A85: Magdy Radwan | B85: 966549806047 | C85: Al Ayuni Investment | G85: Procurement Manager | H85: 46222 | I85: Sent Company Profile | M85: {=_xlfn.LET(_xlpm.x,_xlfn.XLOOKUP(Hot_Leads[[#This Row],[Phone]],Dashboard!$M$44:$M$58,Dashboard!$J$44:$J$58,""),IF(_xlpm.x<>"",_xlpm.x,Hot_Leads[[#This Row],[Next Follow Up Notes]]))} -> 0 | N85: {=_xlfn.LET(_xlpm.x,_xlfn.XLOOKUP(Hot_Leads[[#This Row],[Phone]],Dashboard!$M$44:$M$58,Dashboard!$K$44:$K$58,""),_xlpm.orig,Hot_Leads[[#This Row],[Next Follow Up Date]],IF(_xlpm.x<>"",_xlpm.x,IF(OR(_xlpm.orig="",_xlpm.orig=0),"",_xlpm.orig)))}
A86: Faizan | B86: 966597399509 | C86: IHCC | G86: Procurement Manager | H86: 46222 | I86: Sent Company Profile | M86: {=_xlfn.LET(_xlpm.x,_xlfn.XLOOKUP(Hot_Leads[[#This Row],[Phone]],Dashboard!$M$44:$M$58,Dashboard!$J$44:$J$58,""),IF(_xlpm.x<>"",_xlpm.x,Hot_Leads[[#This Row],[Next Follow Up Notes]]))} -> 0 | N86: {=_xlfn.LET(_xlpm.x,_xlfn.XLOOKUP(Hot_Leads[[#This Row],[Phone]],Dashboard!$M$44:$M$58,Dashboard!$K$44:$K$58,""),_xlpm.orig,Hot_Leads[[#This Row],[Next Follow Up Date]],IF(_xlpm.x<>"",_xlpm.x,IF(OR(_xlpm.orig="",_xlpm.orig=0),"",_xlpm.orig)))}
A87: Shareef | B87: 966534523054 | C87: LEVELS | G87: Procurement Manager | H87: 46223 | I87: مفيش مشاريع حاليا و هتابع معاه كل فترة | M87: {=_xlfn.LET(_xlpm.x,_xlfn.XLOOKUP(Hot_Leads[[#This Row],[Phone]],Dashboard!$M$44:$M$58,Dashboard!$J$44:$J$58,""),IF(_xlpm.x<>"",_xlpm.x,Hot_Leads[[#This Row],[Next Follow Up Notes]]))} -> 0 | N87: {=_xlfn.LET(_xlpm.x,_xlfn.XLOOKUP(Hot_Leads[[#This Row],[Phone]],Dashboard!$M$44:$M$58,Dashboard!$K$44:$K$58,""),_xlpm.orig,Hot_Leads[[#This Row],[Next Follow Up Date]],IF(_xlpm.x<>"",_xlpm.x,IF(OR(_xlpm.orig="",_xlpm.orig=0),"",_xlpm.orig)))}
A88: Abdelaziz Hassan | B88: 966592851015 | C88: MAG المجال العربي | E88: Riyadh | F88: a.alessa@mag-sa.com | G88: Electrical Engineer | H88: 46224 | I88: خدت منه مشروع الهيئة العامة و شغالين عليه حاليا | J88: اول ما الكوتيشن تخلص هبعتهاله | M88: {=_xlfn.LET(_xlpm.x,_xlfn.XLOOKUP(Hot_Leads[[#This Row],[Phone]],Dashboard!$M$44:$M$58,Dashboard!$J$44:$J$58,""),IF(_xlpm.x<>"",_xlpm.x,Hot_Leads[[#This Row],[Next Follow Up Notes]]))} -> اول ما الكوتيشن تخلص هبعتهاله | N88: {=_xlfn.LET(_xlpm.x,_xlfn.XLOOKUP(Hot_Leads[[#This Row],[Phone]],Dashboard!$M$44:$M$58,Dashboard!$K$44:$K$58,""),_xlpm.orig,Hot_Leads[[#This Row],[Next Follow Up Date]],IF(_xlpm.x<>"",_xlpm.x,IF(OR(_xlpm.orig="",_xlpm.orig=0),"",_xlpm.orig)))}
A89: Mohamed Tharwat | B89: 966532495219 | C89: ACC | E89: Jeddah | G89: Project Manager | H89: 46224 | I89: دخلت عليه على مشروع هيلتون ذاخر بس طلعنا خسرنا المشروع ده وقالي نتعاون في مشروع تاني بعدها | J89: هبتعله البروفايل | M89: {=_xlfn.LET(_xlpm.x,_xlfn.XLOOKUP(Hot_Leads[[#This Row],[Phone]],Dashboard!$M$44:$M$58,Dashboard!$J$44:$J$58,""),IF(_xlpm.x<>"",_xlpm.x,Hot_Leads[[#This Row],[Next Follow Up Notes]]))} -> هبتعله البروفايل | N89: {=_xlfn.LET(_xlpm.x,_xlfn.XLOOKUP(Hot_Leads[[#This Row],[Phone]],Dashboard!$M$44:$M$58,Dashboard!$K$44:$K$58,""),_xlpm.orig,Hot_Leads[[#This Row],[Next Follow Up Date]],IF(_xlpm.x<>"",_xlpm.x,IF(OR(_xlpm.orig="",_xlpm.orig=0),"",_xlpm.orig)))}
A90: Ahmed Hegazy | B90: 966580314748 | C90: شركة جوار المشاعر | E90: Makkah | H90: 46222 | M90: {=_xlfn.LET(_xlpm.x,_xlfn.XLOOKUP(Hot_Leads[[#This Row],[Phone]],Dashboard!$M$44:$M$58,Dashboard!$J$44:$J$58,""),IF(_xlpm.x<>"",_xlpm.x,Hot_Leads[[#This Row],[Next Follow Up Notes]]))} -> 0 | N90: {=_xlfn.LET(_xlpm.x,_xlfn.XLOOKUP(Hot_Leads[[#This Row],[Phone]],Dashboard!$M$44:$M$58,Dashboard!$K$44:$K$58,""),_xlpm.orig,Hot_Leads[[#This Row],[Next Follow Up Date]],IF(_xlpm.x<>"",_xlpm.x,IF(OR(_xlpm.orig="",_xlpm.orig=0),"",_xlpm.orig)))}
A91: Salim | B91: 966561359563 | C91: Arif Group | E91: Makkah | G91: MEP Engineer | H91: 46222 | I91: ده الي ماسك مشروع Voco جده الي معانا و بتواصل معاه عشان يبعتلنا باقي الرسومات | J91: بنخلص رسومات ال GRMS Layout و هنبعتهاله | M91: {=_xlfn.LET(_xlpm.x,_xlfn.XLOOKUP(Hot_Leads[[#This Row],[Phone]],Dashboard!$M$44:$M$58,Dashboard!$J$44:$J$58,""),IF(_xlpm.x<>"",_xlpm.x,Hot_Leads[[#This Row],[Next Follow Up Notes]]))} -> بنخلص رسومات ال GRMS Layout و هنبعتهاله | N91: {=_xlfn.LET(_xlpm.x,_xlfn.XLOOKUP(Hot_Leads[[#This Row],[Phone]],Dashboard!$M$44:$M$58,Dashboard!$K$44:$K$58,""),_xlpm.orig,Hot_Leads[[#This Row],[Next Follow Up Date]],IF(_xlpm.x<>"",_xlpm.x,IF(OR(_xlpm.orig="",_xlpm.orig=0),"",_xlpm.orig)))}
A92: Moaz | B92: 966535266629 | C92: IHCC | E92: Jeddah | G92: MEP Engineer | H92: 46222 | I92: كلمته يبعتلي رقم مدير المشتريات في الشركة | M92: {=_xlfn.LET(_xlpm.x,_xlfn.XLOOKUP(Hot_Leads[[#This Row],[Phone]],Dashboard!$M$44:$M$58,Dashboard!$J$44:$J$58,""),IF(_xlpm.x<>"",_xlpm.x,Hot_Leads[[#This Row],[Next Follow Up Notes]]))} -> 0 | N92: {=_xlfn.LET(_xlpm.x,_xlfn.XLOOKUP(Hot_Leads[[#This Row],[Phone]],Dashboard!$M$44:$M$58,Dashboard!$K$44:$K$58,""),_xlpm.orig,Hot_Leads[[#This Row],[Next Follow Up Date]],IF(_xlpm.x<>"",_xlpm.x,IF(OR(_xlpm.orig="",_xlpm.orig=0),"",_xlpm.orig)))}
A93: Mohamed Daghreri | B93: 96655570083 | C93: Vision Construction | E93: Jeddah | H93: 46223 | I93: كلمته عشان مازن مش بيرد من هناك و قولت اخد منه رقم حد تاني احتياطي | M93: {=_xlfn.LET(_xlpm.x,_xlfn.XLOOKUP(Hot_Leads[[#This Row],[Phone]],Dashboard!$M$44:$M$58,Dashboard!$J$44:$J$58,""),IF(_xlpm.x<>"",_xlpm.x,Hot_Leads[[#This Row],[Next Follow Up Notes]]))} -> 0 | N93: {=_xlfn.LET(_xlpm.x,_xlfn.XLOOKUP(Hot_Leads[[#This Row],[Phone]],Dashboard!$M$44:$M$58,Dashboard!$K$44:$K$58,""),_xlpm.orig,Hot_Leads[[#This Row],[Next Follow Up Date]],IF(_xlpm.x<>"",_xlpm.x,IF(OR(_xlpm.orig="",_xlpm.orig=0),"",_xlpm.orig)))}
A94: Ahmed Hamdy | B94: 966553961953 | C94: الفؤاد للمقاولات | E94: Makkah | G94: MEP Engineer | H94: 46224 | I94: قالي ابعتلي البروفايل و هيبعتها للمكتب بتاعهم عشان يشوف لو لسة في باكدج مراحتش لحد نقدر نسعرها | M94: {=_xlfn.LET(_xlpm.x,_xlfn.XLOOKUP(Hot_Leads[[#This Row],[Phone]],Dashboard!$M$44:$M$58,Dashboard!$J$44:$J$58,""),IF(_xlpm.x<>"",_xlpm.x,Hot_Leads[[#This Row],[Next Follow Up Notes]]))} -> 0 | N94: {=_xlfn.LET(_xlpm.x,_xlfn.XLOOKUP(Hot_Leads[[#This Row],[Phone]],Dashboard!$M$44:$M$58,Dashboard!$K$44:$K$58,""),_xlpm.orig,Hot_Leads[[#This Row],[Next Follow Up Date]],IF(_xlpm.x<>"",_xlpm.x,IF(OR(_xlpm.orig="",_xlpm.orig=0),"",_xlpm.orig)))}
A95: Hamdy | B95: 966562506362 | C95: الرواد جدة | E95: Jeddah | G95: MEP Engineer | H95: 46228 | I95: دخلنا المشروع متأخر بس هبعتلك البرفايل عشان لو فيه اي شغل جديد ان شاء الله | M95: {=_xlfn.LET(_xlpm.x,_xlfn.XLOOKUP(Hot_Leads[[#This Row],[Phone]],Dashboard!$M$44:$M$58,Dashboard!$J$44:$J$58,""),IF(_xlpm.x<>"",_xlpm.x,Hot_Leads[[#This Row],[Next Follow Up Notes]]))} -> 0 | N95: {=_xlfn.LET(_xlpm.x,_xlfn.XLOOKUP(Hot_Leads[[#This Row],[Phone]],Dashboard!$M$44:$M$58,Dashboard!$K$44:$K$58,""),_xlpm.orig,Hot_Leads[[#This Row],[Next Follow Up Date]],IF(_xlpm.x<>"",_xlpm.x,IF(OR(_xlpm.orig="",_xlpm.orig=0),"",_xlpm.orig)))}
A96: Mahmoud Tayser | B96: 966593891343 | C96: Temco | E96: Jeddah | G96: Procurement Engineer | H96: 46228 | I96: لقيت مهندس المشتريات في السايت و قالي انهم تقريبا مخلصين 90% من انظمة التيار الخفيف و بعتله البروفايل مستني رده هل نقدر نخش في الوقت ده ولا خلاص | M96: {=_xlfn.LET(_xlpm.x,_xlfn.XLOOKUP(Hot_Leads[[#This Row],[Phone]],Dashboard!$M$44:$M$58,Dashboard!$J$44:$J$58,""),IF(_xlpm.x<>"",_xlpm.x,Hot_Leads[[#This Row],[Next Follow Up Notes]]))} -> 0 | N96: {=_xlfn.LET(_xlpm.x,_xlfn.XLOOKUP(Hot_Leads[[#This Row],[Phone]],Dashboard!$M$44:$M$58,Dashboard!$K$44:$K$58,""),_xlpm.orig,Hot_Leads[[#This Row],[Next Follow Up Date]],IF(_xlpm.x<>"",_xlpm.x,IF(OR(_xlpm.orig="",_xlpm.orig=0),"",_xlpm.orig)))}
A97: Abdelrahman | B97: 966509498891 | C97: Nuzum for Trading | E97: Makkah | G97: Electrical Engineer | H97: 46226 | I97: عاوز items من Televes | M97: {=_xlfn.LET(_xlpm.x,_xlfn.XLOOKUP(Hot_Leads[[#This Row],[Phone]],Dashboard!$M$44:$M$58,Dashboard!$J$44:$J$58,""),IF(_xlpm.x<>"",_xlpm.x,Hot_Leads[[#This Row],[Next Follow Up Notes]]))} -> 0 | N97: {=_xlfn.LET(_xlpm.x,_xlfn.XLOOKUP(Hot_Leads[[#This Row],[Phone]],Dashboard!$M$44:$M$58,Dashboard!$K$44:$K$58,""),_xlpm.orig,Hot_Leads[[#This Row],[Next Follow Up Date]],IF(_xlpm.x<>"",_xlpm.x,IF(OR(_xlpm.orig="",_xlpm.orig=0),"",_xlpm.orig)))}
A98: Mohamed Abdelatif | B98: 966545150782 | C98: تيسر للتجارة | E98: Makkah | G98: Electrical Engineer | H98: 46230 | I98: ده تبع مشورع العزيزية بتاع مشروع تيسر و بعتلي ككوتيشن و عاوزني اعمل A2P كوتيشن | M98: {=_xlfn.LET(_xlpm.x,_xlfn.XLOOKUP(Hot_Leads[[#This Row],[Phone]],Dashboard!$M$44:$M$58,Dashboard!$J$44:$J$58,""),IF(_xlpm.x<>"",_xlpm.x,Hot_Leads[[#This Row],[Next Follow Up Notes]]))} -> 0 | N98: {=_xlfn.LET(_xlpm.x,_xlfn.XLOOKUP(Hot_Leads[[#This Row],[Phone]],Dashboard!$M$44:$M$58,Dashboard!$K$44:$K$58,""),_xlpm.orig,Hot_Leads[[#This Row],[Next Follow Up Date]],IF(_xlpm.x<>"",_xlpm.x,IF(OR(_xlpm.orig="",_xlpm.orig=0),"",_xlpm.orig)))}
A99: Hamed | B99: 966596290999 | C99: نخبة سعد ( ابراج مكة العزيزة ) | E99: Makkah | G99: Procurement Engineer | H99: 46230 | M99: {=_xlfn.LET(_xlpm.x,_xlfn.XLOOKUP(Hot_Leads[[#This Row],[Phone]],Dashboard!$M$44:$M$58,Dashboard!$J$44:$J$58,""),IF(_xlpm.x<>"",_xlpm.x,Hot_Leads[[#This Row],[Next Follow Up Notes]]))} -> 0 | N99: {=_xlfn.LET(_xlpm.x,_xlfn.XLOOKUP(Hot_Leads[[#This Row],[Phone]],Dashboard!$M$44:$M$58,Dashboard!$K$44:$K$58,""),_xlpm.orig,Hot_Leads[[#This Row],[Next Follow Up Date]],IF(_xlpm.x<>"",_xlpm.x,IF(OR(_xlpm.orig="",_xlpm.orig=0),"",_xlpm.orig)))}
A100: Mr. Mohamed Arif | B100: 966536687616 | C100: شركة الضيافة للتشغيل الفندقي | E100: Makkah | G100: Supervisor | H100: 46230 | I100: سيبتله الكارت عشان لما يجي المهندس ياخده | M100: {=_xlfn.LET(_xlpm.x,_xlfn.XLOOKUP(Hot_Leads[[#This Row],[Phone]],Dashboard!$M$44:$M$58,Dashboard!$J$44:$J$58,""),IF(_xlpm.x<>"",_xlpm.x,Hot_Leads[[#This Row],[Next Follow Up Notes]]))} -> 0 | N100: {=_xlfn.LET(_xlpm.x,_xlfn.XLOOKUP(Hot_Leads[[#This Row],[Phone]],Dashboard!$M$44:$M$58,Dashboard!$K$44:$K$58,""),_xlpm.orig,Hot_Leads[[#This Row],[Next Follow Up Date]],IF(_xlpm.x<>"",_xlpm.x,IF(OR(_xlpm.orig="",_xlpm.orig=0),"",_xlpm.orig)))}
...

Sheet Master Plan (2)
A1: Date | B1: Week | C1: Opportunity | D1: Contact | E1: Period | F1: Type | G1: Visit Type | H1: Project Stage | I1: Project Status | J1: Project Location | K1: Action | L1: Follow Up Date | M1: Follow Up Action
A2: 46145 | B2: =WEEKNUM(A2) -> 19 | C2: Alsalama Hospital | D2: Yasser Bahussin | E2: 9:00-10:00AM | F2: Call | G2: Follow up | H2: In Hand | I2: Gather Info. | J2: Jeddah | K2: Confirm Online Meeting at 1PM | L2: 46145 | M2: Team Meeting
A3: 46145 | B3: =WEEKNUM(A3) -> 19 | C3: KIX Futsal Complex | D3: Mohamed Hanifa | E3: 9:00-10:00AM | F3: Call | G3: Follow up | H3: Tender | I3: Send to Client | J3: Jeddah | K3: Get feedback on quotation | L3: 46145 | M3: Update project status
A4: 46145 | B4: =WEEKNUM(A4) -> 19 | C4: IMC Hospital | D4: Sameh Saber | E4: 9:00-10:00AM | F4: Call | G4: Follow up | H4: - | I4: - | J4: Jeddah | K4: Send Pre-Qualification as requested | L4: 46147 | M4: Schedule meeting
A5: 46145 | B5: =WEEKNUM(A5) -> 19 | C5: Honeywell | D5: Mohamed 3essa | E5: 10:00-11:00AM | F5: Call | G5: Follow up | H5: - | I5: - | J5: Jeddah | K5: Confirm F2F meeting today | L5: 46145 | M5: F2F Meeting
A6: 46145 | B6: =WEEKNUM(A6) -> 19 | C6: Code 3 Project | D6: Abdelrahman Al-Shibi | E6: 10:00-11:00AM | F6: Call | G6: Follow up | H6: In Hand | I6: RFQ Processing | J6: Khobar | K6: Get follow sheet via email | L6: 46147 | M6: Update status
A7: 46145 | B7: =WEEKNUM(A7) -> 19 | C7: IKK Group | D7: Mohamed IKK | E7: 10:00-11:00AM | F7: Call | G7: Follow up | H7: - | I7: - | J7: Jeddah | K7: Ask about new projects | L7: 46149 | M7: Follow up
A8: 46145 | B8: =WEEKNUM(A8) -> 19 | C8: IHCC - Western Tower | D8: Mohamed Youssef | E8: 11:00-12:00PM | F8: Call | G8: Follow up | H8: Tender | I8: RFQ Processing | J8: Jeddah | K8: Get procurement contact | L8: 46147 | M8: Contact procurement
A9: 46145 | B9: =WEEKNUM(A9) -> 19 | C9: IMC Project | D9: Omar Alsaad | E9: 11:00-12:00PM | F9: Call | G9: Follow up | H9: Tender | I9: RFQ Processing | J9: Jeddah | K9: Get IMC Phase 2 details + Zedca info | L9: 46149 | M9: Update pipeline
A10: 46145 | B10: =WEEKNUM(A10) -> 19 | C10: Sedra Electric | D10: Ibrahim Sabry | E10: 11:00-12:00PM | F10: Call | G10: Follow up | H10: In Hand | I10: Negotiation | J10: Makkah | K10: Check if client responded | L10: 46148 | M10: Push for response
A11: 46145 | B11: =WEEKNUM(A11) -> 19 | C11: Honeywell | D11: Mohamed 3essa | E11: 12:00-1:00PM | F11: F2F Meeting | G11: Visit | H11: - | I11: - | J11: Jeddah | K11: Meet & introduce company | L11: 46152 | M11: Send projects
A12: 46145 | B12: =WEEKNUM(A12) -> 19 | C12: Alsalama Hospital | D12: Yasser Bahussin | E12: 1:00-2:00PM | F12: Online Meeting | G12: Follow up | H12: In Hand | I12: Gather Info. | J12: Jeddah | K12: Online meeting with engineering team | L12: 46146 | M12: Send solution proposal
A13: 46145 | B13: =WEEKNUM(A13) -> 19 | C13: Freyssinet | D13: Sameh Saber | E13: 2:00-3:00PM | F13: Call | G13: Follow up | H13: - | I13: - | J13: Jeddah | K13: First meeting - introduce company | L13: 46149 | M13: Send quotation if needed
... A15: 46145 | B15: =WEEKNUM(A15) -> 19 | C15: Hexagon | D15: Mohamed Abudagga | E15: 3:00-4:00PM | F15: Call | G15: Follow up | H15: In Hand | I15: RFQ Processing | J15: Khobar | K15: Follow up on payment + Seven SBG project | L15: 46149 | M15: Get payment update
A16: 46145 | B16: =WEEKNUM(A16) -> 19 | C16: Daily Summary | E16: 4:00-5:00PM | F16: Office Stuff | G16: - | H16: - | I16: - | J16: Office | K16: Update Master Report + prepare tomorrow
A17: 46146 | B17: =WEEKNUM(A17) -> 19 | C17: Afrina ACUD | D17: Ashraf Gadallah | E17: 9:00-10:00AM | F17: Call | G17: Follow up | H17: In Hand | I17: Gather Info. | J17: Jeddah | K17: Schedule F2F meeting this week | L17: 46148 | M17: Book visit
A18: 46146 | B18: =WEEKNUM(A18) -> 19 | C18: ALsaad Contracting | D18: Ibrahim Ahmed | E18: 9:00-10:00AM | F18: Call | G18: Follow up | H18: - | I18: - | J18: Jeddah | K18: Ask about new projects as planned Monday | L18: 46149 | M18: Get project details
A19: 46146 | B19: =WEEKNUM(A19) -> 19 | C19: AlShamela | D19: Helmy Abdelrazeq | E19: 9:00-10:00AM | F19: Call | G19: Follow up | H19: - | I19: - | J19: Jeddah | K19: Follow up on Pre-Qualification sent | L19: 46149 | M19: Schedule meeting
A20: 46146 | B20: =WEEKNUM(A20) -> 19 | C20: Creet | D20: Mohamed Hussain | E20: 10:00-11:00AM | F20: Call | G20: Follow up | H20: In Hand | I20: Negotiation | J20: Riyadh | K20: Check new pricing status | L20: 46148 | M20: Get final price
A21: 46146 | B21: =WEEKNUM(A21) -> 19 | C21: Alsalama Hospital | D21: Yasser Bahussin | E21: 10:00-11:00AM | F21: Call | G21: Follow up | H21: In Hand | I21: Gather Info. | J21: Jeddah | K21: Follow up on yesterday meeting | L21: 46148 | M21: Send technical proposal
A22: 46146 | B22: =WEEKNUM(A22) -> 19 | C22: MHM - KIX | D22: Mohamed Hanifa | E22: 10:00-11:00AM | F22: Call | G22: Follow up | H22: Tender | I22: Send to Client | J22: Jeddah | K22: Get final decision on project | L22: 46149 | M22: Close or update status
A23: 46146 | B23: =WEEKNUM(A23) -> 19 | C23: IMC Project | D23: Mazen Abdelghany | E23: 11:00-12:00PM | F23: Call | G23: Follow up | H23: Tender | I23: RFQ Processing | J23: Jeddah | K23: Check pricing status with Eng. Mayar | L23: 46149 | M23: Get quotation
A24: 46146 | B24: =WEEKNUM(A24) -> 19 | C24: Rafa Gulf - CGC | D24: Majdi I. Al-Zoubi | E24: 11:00-12:00PM | F24: Call | G24: Follow up | H24: In Hand | I24: Negotiation | J24: Khobar | K24: Check CGC project update | L24: 46149 | M24: Get news
A25: 46146 | B25: =WEEKNUM(A25) -> 19 | C25: BlueApps | D25: Emad Hamwi | E25: 11:00-12:00PM | F25: Call | G25: Follow up | H25: - | I25: - | J25: Jeddah | K25: Normal follow up - check for projects | L25: 46153 | M25: Regular check
A26: 46146 | B26: =WEEKNUM(A26) -> 19 | C26: Fairmont Makkah | D26: Mohamed Elkholy | E26: 12:00-1:00PM | F26: F2F Meeting | G26: Follow up | H26: In Hand | I26: RFQ Processing | J26: Makkah | K26: Visit hotel - discuss system requirements | L26: 46149 | M26: Send quotation
A27: 46146 | B27: =WEEKNUM(A27) -> 19 | C27: SIAC KSA | D27: Refaat | E27: 1:00-2:00PM | F27: Call | G27: Follow up | H27: - | I27: - | J27: Jeddah | K27: Follow up on new projects | L27: 46153 | M27: Monthly check
A28: 46146 | B28: =WEEKNUM(A28) -> 19 | C28: Hotel Hunting - Makkah | E28: 2:00-3:00PM | F28: Hunting | G28: New Lead | H28: - | I28: - | J28: Makkah | K28: Visit hotels in Makkah area - Route 1 | L28: 46149 | M28: Add new contacts
A29: 46146 | B29: =WEEKNUM(A29) -> 19 | C29: فندق واحة الرفاع | D29: Ahmed Yasser | E29: 3:00-4:00PM | F29: Call | G29: Follow up | H29: In Hand | I29: Gather Info. | J29: Makkah | K29: Follow up - he didn't answer before | L29: 46149 | M29: Get project details
A30: 46146 | B30: =WEEKNUM(A30) -> 19 | C30: انجاز - King Salman Gate | D30: Ahmed Abo Saif | E30: 3:00-4:00PM | F30: Call | G30: Follow up | H30: In Hand | I30: Gather Info. | J30: Makkah | K30: Follow up on King Salman Gate project | L30: 46149 | M30: Get requirements
A31: 46146 | B31: =WEEKNUM(A31) -> 19 | C31: Daily Summary | E31: 4:00-5:00PM | F31: Office Stuff | G31: - | H31: - | I31: - | J31: Office | K31: Update Master Report + prepare tomorrow
A32: 46147 | B32: =WEEKNUM(A32) -> 19 | C32: IMC Hospital | D32: Sameh Saber | E32: 9:00-10:00AM | F32: Call | G32: Follow up | H32: - | I32: - | J32: Jeddah | K32: Follow up on Pre-Qualification sent Sunday | L32: 46149 | M32: Schedule meeting
A33: 46147 | B33: =WEEKNUM(A33) -> 19 | C33: Code 3 - Rafa Gulf | D33: Abdelrahman Al-Shibi | E33: 9:00-10:00AM | F33: Call | G33: Follow up | H33: In Hand | I33: RFQ Processing | J33: Khobar | K33: Get follow sheet update | L33: 46152 | M33: Track progress
A34: 46147 | B34: =WEEKNUM(A34) -> 19 | C34: IHCC | D34: Mohamed Youssef | E34: 9:00-10:00AM | F34: Call | G34: Follow up | H34: Tender | I34: RFQ Processing | J34: Jeddah | K34: Contact procurement team | L34: 46152 | M34: Get RFQ
A35: 46147 | B35: =WEEKNUM(A35) -> 19 | C35: ORC - Madinah | D35: Amira Ibrahim | E35: 10:00-11:00AM | F35: Call | G35: Follow up | H35: Tender | I35: RFQ Processing | J35: Madinah | K35: Check project pricing status | L35: 46149 | M35: Get quotation status
A36: 46147 | B36: =WEEKNUM(A36) -> 19 | C36: Al-Awalat - فندق الادلاء | D36: Mohamed Khalifah | E36: 10:00-11:00AM | F36: Call | G36: Follow up | H36: In Hand | I36: RFQ Processing | J36: Madinah | K36: Check quotation status | L36: 46152 | M36: Get pricing
A37: 46147 | B37: =WEEKNUM(A37) -> 19 | C37: ALsaad Contracting | D37: Ibrahim Ahmed | E37: 10:00-11:00AM | F37: Call | G37: Follow up | H37: - | I37: - | J37: Jeddah | K37: Get project details from Monday call | L37: 46152 | M37: Add to pipeline
A38: 46147 | B38: =WEEKNUM(A38) -> 19 | C38: Creet - New Factory | D38: Mo2nes Amr | E38: 11:00-12:00PM | F38: Call | G38: Follow up | H38: In Hand | I38: Negotiation | J38: Jeddah | K38: Check payment + goods status | L38: 46152 | M38: Get update
A39: 46147 | B39: =WEEKNUM(A39) -> 19 | C39: Al-Saif | D39: Mohamed Taqash | E39: 11:00-12:00PM | F39: Call | G39: Follow up | H39: - | I39: - | J39: Jeddah | K39: Follow up - he'll share procurement contact | L39: 46152 | M39: Get procurement number
A40: 46147 | B40: =WEEKNUM(A40) -> 19 | C40: AlShamela Riyadh | D40: Mohamed Atef | E40: 11:00-12:00PM | F40: Call | G40: Follow up | H40: - | I40: - | J40: Riyadh | K40: Follow up on new projects | L40: 46154 | M40: Monthly check
A41: 46147 | B41: =WEEKNUM(A41) -> 19 | C41: Afrina - ابراج موطن المسار | D41: Ashraf Gadallah | E41: 12:00-1:00PM | F41: F2F Meeting | G41: Follow up | H41: In Hand | I41: Gather Info. | J41: Jeddah | K41: Office visit - discuss 4 in-hand projects | L41: 46152 | M41: Get RFQs
A42: 46147 | B42: =WEEKNUM(A42) -> 19 | C42: ALsaad - IMC | D42: Omar Alsaad | E42: 1:00-2:00PM | F42: F2F Meeting | G42: Follow up | H42: Tender | I42: RFQ Processing | J42: Jeddah | K42: Discuss IMC Phase 2 + Zedca project | L42: 46154 | M42: Get specifications
A43: 46147 | B43: =WEEKNUM(A43) -> 19 | C43: Hotel Hunting - Jeddah | E43: 2:00-3:00PM | F43: Hunting | G43: New Lead | H43: - | I43: - | J43: Jeddah | K43: Visit hotels - Route 2 Jabal Omar area | L43: 46152 | M43: Add new contacts
A44: 46147 | B44: =WEEKNUM(A44) -> 19 | C44: ALmawel Contracting | D44: Ahmed Naserallah | E44: 3:00-4:00PM | F44: Call | G44: Follow up | H44: - | I44: - | J44: Jeddah | K44: Check for new project this week | L44: 46154 | M44: Get project details
A45: 46147 | B45: =WEEKNUM(A45) -> 19 | C45: Bits Arabia | D45: Mohamed Kahla | E45: 3:00-4:00PM | F45: Call | G45: Follow up | H45: - | I45: - | J45: Jeddah | K45: Exchange project leads | L45: 46154 | M45: Collaborate
A46: 46147 | B46: =WEEKNUM(A46) -> 19 | C46: Daily Summary | E46: 4:00-5:00PM | F46: Office Stuff | G46: - | H46: - | I46: - | J46: Office | K46: Update Master Report + prepare tomorrow
A47: 46148 | B47: =WEEKNUM(A47) -> 19 | C47: Sedra Electric | D47: Ibrahim Sabry | E47: 9:00-10:00AM | F47: Call | G47: Follow up | H47: In Hand | I47: Negotiation | J47: Makkah | K47: Push for client response - 1.6M project! | L47: 46152 | M47: Get final decision
A48: 46148 | B48: =WEEKNUM(A48) -> 19 | C48: Creet - Factory | D48: Mohamed Hussain | E48: 9:00-10:00AM | F48: Call | G48: Follow up | H48: In Hand | I48: Negotiation | J48: Riyadh | K48: Get final pricing - 442K project | L48: 46152 | M48: Close negotiation
A49: 46148 | B49: =WEEKNUM(A49) -> 19 | C49: Alsalama Hospital | D49: Yasser Bahussin | E49: 9:00-10:00AM | F49: Call | G49: Follow up | H49: In Hand | I49: Gather Info. | J49: Jeddah | K49: Send technical proposal as discussed | L49: 46152 | M49: Get approval
A50: 46148 | B50: =WEEKNUM(A50) -> 19 | C50: Afrina | D50: Ashraf Gadallah | E50: 10:00-11:00AM | F50: Call | G50: Follow up | H50: In Hand | I50: Gather Info. | J50: Jeddah | K50: Follow up after Tuesday meeting | L50: 46154 | M50: Get BOQs
A51: 46148 | B51: =WEEKNUM(A51) -> 19 | C51: IMC - Vision | D51: Mazen Abdelghany | E51: 10:00-11:00AM | F51: Call | G51: Follow up | H51: Tender | I51: RFQ Processing | J51: Jeddah | K51: Check with Eng. Mayar on pricing | L51: 46154 | M51: Get quotation
A52: 46148 | B52: =WEEKNUM(A52) -> 19 | C52: KIX Futsal | D52: Mohamed Hanifa | E52: 10:00-11:00AM | F52: Call | G52: Follow up | H52: Tender | I52: Send to Client | J52: Jeddah | K52: Final decision on 337K project | L52: 46154 | M52: Close or extend
A53: 46148 | B53: =WEEKNUM(A53) -> 19 | C53: Hexagon | D53: Mohamed Abudagga | E53: 11:00-12:00PM | F53: Call | G53: Follow up | H53: In Hand | I53: RFQ Processing | J53: Khobar | K53: Check payment 200K+ owed | L53: 46154 | M53: Get payment schedule
A54: 46148 | B54: =WEEKNUM(A54) -> 19 | C54: Jash - صالة الفنون | D54: Hussni | E54: 11:00-12:00PM | F54: Call | G54: Follow up | H54: In Hand | I54: Gather Info. | J54: Riyadh | K54: Coordinate with Hamdy for site visit | L54: 46154 | M54: Schedule Riyadh visit
A55: 46148 | B55: =WEEKNUM(A55) -> 19 | C55: ORC - Madinah | D55: Amira Ibrahim | E55: 11:00-12:00PM | F55: Call | G55: Follow up | H55: Tender | I55: RFQ Processing | J55: Madinah | K55: Get quotation status update | L55: 46154 | M55: Submit pricing
A56: 46148 | B56: =WEEKNUM(A56) -> 19 | C56: واحة الرفاع Hotel | D56: Ahmed Yasser | E56: 12:00-1:00PM | F56: F2F Meeting | G56: Follow up | H56: In Hand | I56: Gather Info. | J56: Makkah | K56: Visit hotel - multiple renovation projects | L56: 46154 | M56: Get requirements
A57: 46148 | B57: =WEEKNUM(A57) -> 19 | C57: Fairmont Makkah | D57: Mohamed Elkholy | E57: 1:00-2:00PM | F57: F2F Meeting | G57: Follow up | H57: In Hand | I57: RFQ Processing | J57: Makkah | K57: Second visit - finalize requirements | L57: 46154 | M57: Send quotation
A58: 46148 | B58: =WEEKNUM(A58) -> 19 | C58: Hotel Hunting - Makkah | E58: 2:00-3:00PM | F58: Hunting | G58: New Lead | H58: - | I58: - | J58: Makkah | K58: Visit hotels - Al Aziziya area | L58: 46154 | M58: Add new contacts
A59: 46148 | B59: =WEEKNUM(A59) -> 19 | C59: V-Yard Project | D59: Sohail | E59: 3:00-4:00PM | F59: Call | G59: Follow up | H59: In Hand | I59: Gather Info. | J59: Makkah | K59: Get MEP engineer contact for V-Yard | L59: 46154 | M59: Meet engineers
A60: 46148 | B60: =WEEKNUM(A60) -> 19 | C60: Roshan Makkah | E60: 3:00-4:00PM | F60: Call | G60: New Lead | H60: - | I60: - | J60: Makkah | K60: Coordinate with Abdelrahman on Roshan | L60: 46154 | M60: Get contact
A61: 46148 | B61: =WEEKNUM(A61) -> 19 | C61: Daily Summary | E61: 4:00-5:00PM | F61: Office Stuff | G61: - | H61: - | I61: - | J61: Office | K61: Update Master Report + prepare tomorrow
A62: 46149 | B62: =WEEKNUM(A62) -> 19 | C62: IMC - Freyssinet | D62: Sameh Saber | E62: 9:00-10:00AM | F62: Call | G62: Follow up | H62: - | I62: - | J62: Jeddah | K62: Follow up after Sunday meeting | L62: 46154 | M62: Get project share
A63: 46149 | B63: =WEEKNUM(A63) -> 19 | C63: IMC - Vision | D63: Mazen Abdelghany | E63: 9:00-10:00AM | F63: Call | G63: Follow up | H63: Tender | I63: RFQ Processing | J63: Jeddah | K63: Final check on 35M project pricing | L63: 46154 | M63: Submit quotation
A64: 46149 | B64: =WEEKNUM(A64) -> 19 | C64: ORC - Madinah | D64: Amira Ibrahim | E64: 9:00-10:00AM | F64: Call | G64: Follow up | H64: Tender | I64: RFQ Processing | J64: Madinah | K64: Final quotation submission | L64: 46156 | M64: Close tender
A65: 46149 | B65: =WEEKNUM(A65) -> 19 | C65: Sedra Electric | D65: Ibrahim Sabry | E65: 10:00-11:00AM | F65: Call | G65: Follow up | H65: In Hand | I65: Negotiation | J65: Makkah | K65: Final push on 1.6M project | L65: 46152 | M65: Get PO
A66: 46149 | B66: =WEEKNUM(A66) -> 19 | C66: AlShamela | D66: Helmy Abdelrazeq | E66: 10:00-11:00AM | F66: Call | G66: Follow up | H66: - | I66: - | J66: Jeddah | K66: Check response on Pre-Qualification | L66: 46156 | M66: Book meeting
A67: 46149 | B67: =WEEKNUM(A67) -> 19 | C67: Fairmont Makkah | D67: Mohamed Elkholy | E67: 10:00-11:00AM | F67: Call | G67: Follow up | H67: In Hand | I67: RFQ Processing | J67: Makkah | K67: Follow up on hotel project | L67: 46156 | M67: Send quotation
A68: 46149 | B68: =WEEKNUM(A68) -> 19 | C68: انجاز - King Salman | D68: Ahmed Abo Saif | E68: 11:00-12:00PM | F68: Call | G68: Follow up | H68: In Hand | I68: Gather Info. | J68: Makkah | K68: Get King Salman Gate requirements | L68: 46156 | M68: Site visit
A69: 46149 | B69: =WEEKNUM(A69) -> 19 | C69: Afrina - 4 Projects | D69: Ashraf Gadallah | E69: 11:00-12:00PM | F69: Call | G69: Follow up | H69: In Hand | I69: Gather Info. | J69: Jeddah | K69: Get BOQs for 4 in-hand projects | L69: 46156 | M69: Start pricing
A70: 46149 | B70: =WEEKNUM(A70) -> 19 | C70: Zedca Project | D70: Omar Alsaad | E70: 11:00-12:00PM | F70: Call | G70: Follow up | H70: In Hand | I70: Gather Info. | J70: RedSea | K70: Weekly follow up on border project | L70: 46156 | M70: Track progress
A71: 46149 | B71: =WEEKNUM(A71) -> 19 | C71: New Account Hunting | E71: 12:00-1:00PM | F71: Hunting | G71: New Lead | H71: - | I71: - | J71: Jeddah | K71: Visit construction sites on Makkah Road | L71: 46156 | M71: Add 3 new contacts
A72: 46149 | B72: =WEEKNUM(A72) -> 19 | C72: New Account Hunting | E72: 1:00-2:00PM | F72: Hunting | G72: New Lead | H72: - | I72: - | J72: Jeddah | K72: Visit industrial area companies | L72: 46156 | M72: Add 2 new contacts
A73: 46149 | B73: =WEEKNUM(A73) -> 19 | C73: VIP Client Visit | E73: 2:00-3:00PM | F73: F2F Meeting | G73: Visit | H73: - | I73: - | J73: Jeddah | K73: Visit potential VIP client (TBD) | L73: 46156 | M73: Build relationship
A74: 46149 | B74: =WEEKNUM(A74) -> 19 | C74: Weekly Review | E74: 3:00-4:00PM | F74: Office Stuff | G74: - | H74: - | I74: - | J74: Office | K74: Review all KPIs - F2F, Calls, Projects
A75: 46149 | B75: =WEEKNUM(A75) -> 19 | C75: Weekly Planning | E75: 4:00-5:00PM | F75: Office Stuff | G75: - | H75: - | I75: - | J75: Office | K75: Plan next week activities + priorities
A76: 46151 | B76: =WEEKNUM(A76) -> 19 | C76: Sedra Electric | D76: Ibrahim Sabry | E76: 9:00-10:00AM | F76: Call | G76: Follow up | H76: In Hand | I76: Negotiation | J76: Makkah | K76: Weekly priority - Push for 1.6M SAR decision! | L76: 46154 | M76: Get PO
A77: 46151 | B77: =WEEKNUM(A77) -> 19 | C77: IMC Project | D77: Mazen Abdelghany | E77: 9:00-10:00AM | F77: Call | G77: Follow up | H77: Tender | I77: RFQ Processing | J77: Jeddah | K77: Check 35M project pricing with Eng. Mayar | L77: 46154 | M77: Get quotation
A78: 46151 | B78: =WEEKNUM(A78) -> 19 | C78: Alsalama Hospital | D78: Yasser Bahussin | E78: 9:00-10:00AM | F78: Call | G78: Follow up | H78: In Hand | I78: Gather Info. | J78: Jeddah | K78: Follow up on technical proposal | L78: 46154 | M78: Get feedback
A79: 46151 | B79: =WEEKNUM(A79) -> 19 | C79: KIX Futsal | D79: Mohamed Hanifa | E79: 10:00-11:00AM | F79: Call | G79: Follow up | H79: Tender | I79: Send to Client | J79: Jeddah | K79: Get final decision on 337K project | L79: 46154 | M79: Close deal
A80: 46151 | B80: =WEEKNUM(A80) -> 19 | C80: Hexagon | D80: Mohamed Abudagga | E80: 10:00-11:00AM | F80: Call | G80: Follow up | H80: In Hand | I80: RFQ Processing | J80: Khobar | K80: Payment follow up - 200K+ owed | L80: 46154 | M80: Get schedule
A81: 46151 | B81: =WEEKNUM(A81) -> 19 | C81: ORC - Madinah | D81: Amira Ibrahim | E81: 10:00-11:00AM | F81: Call | G81: Follow up | H81: Tender | I81: RFQ Processing | J81: Madinah | K81: Check Al Alyaa quotation status | L81: 46154 | M81: Submit quote
A82: 46151 | B82: =WEEKNUM(A82) -> 19 | C82: Afrina - Projects | D82: Ashraf Gadallah | E82: 11:00-12:00PM | F82: Call | G82: Follow up | H82: In Hand | I82: Gather Info. | J82: Jeddah | K82: Schedule visit for next week | L82: 46153 | M82: Book meeting
A83: 46151 | B83: =WEEKNUM(A83) -> 19 | C83: Zedca Project | D83: Omar Alsaad | E83: 11:00-12:00PM | F83: Call | G83: Follow up | H83: In Hand | I83: Gather Info. | J83: RedSea | K83: Weekly border project check | L83: 46156 | M83: Track progress
A84: 46151 | B84: =WEEKNUM(A84) -> 19 | C84: Creet Factory | D84: Mohamed Hussain | E84: 11:00-12:00PM | F84: Call | G84: Follow up | H84: In Hand | I84: Lost | J84: Riyadh | K84: Check for new opportunities | L84: 46156 | M84: Rebuild relationship
A85: 46151 | B85: =WEEKNUM(A85) -> 19 | C85: Fairmont Makkah | D85: Mohamed Elkholy | E85: 12:00-1:00PM | F85: F2F Meeting | G85: Follow up | H85: In Hand | I85: RFQ Processing | J85: Makkah | K85: Visit hotel - discuss system project | L85: 46156 | M85: Send quotation
A86: 46151 | B86: =WEEKNUM(A86) -> 19 | C86: Hotel Hunting | E86: 1:00-2:00PM | F86: Hunting | G86: New Lead | H86: - | I86: - | J86: Makkah | K86: Visit hotels - Al Aziziya area | L86: 46156 | M86: Add new contacts
A87: 46151 | B87: =WEEKNUM(A87) -> 19 | C87: AlShamela | D87: Helmy Abdelrazeq | E87: 3:00-4:00PM | F87: Call | G87: Follow up | H87: - | I87: - | J87: Jeddah | K87: Follow up on Pre-Qualification | L87: 46154 | M87: Book meeting
A88: 46151 | B88: =WEEKNUM(A88) -> 19 | C88: Daily Summary | E88: 4:00-5:00PM | F88: Office Stuff | G88: - | H88: - | I88: - | J88: Office | K88: Update Master Report + plan Sunday
A89: 46152 | B89: =WEEKNUM(A89) -> 20 | C89: Sedra Electric | D89: Ibrahim Sabry | E89: 9:00-10:00AM | F89: Call | G89: Follow up | H89: In Hand | I89: Negotiation | J89: Makkah | K89: Push for final decision - 1.6M SAR project! | L89: 46154 | M89: Get PO or update
A90: 46152 | B90: =WEEKNUM(A90) -> 20 | C90: Alsalama Hospital | D90: Yasser Bahussin | E90: 9:00-10:00AM | F90: Call | G90: Follow up | H90: In Hand | I90: Gather Info. | J90: Jeddah | K90: Follow up on technical proposal sent | L90: 46154 | M90: Get approval
A91: 46152 | B91: =WEEKNUM(A91) -> 20 | C91: IMC Project | D91: Mazen Abdelghany | E91: 9:00-10:00AM | F91: Call | G91: Follow up | H91: Tender | I91: RFQ Processing | J91: Jeddah | K91: Check 35M project pricing status | L91: 46156 | M91: Get quotation
A92: 46152 | B92: =WEEKNUM(A92) -> 20 | C92: Hexagon - Payment | D92: Mohamed Abudagga | E92: 10:00-11:00AM | F92: Call | G92: Follow up | H92: In Hand | I92: RFQ Processing | J92: Khobar | K92: Follow up on 200K+ payment | L92: 46156 | M92: Get payment schedule
A93: 46152 | B93: =WEEKNUM(A93) -> 20 | C93: ORC - Madinah | D93: Amira Ibrahim | E93: 10:00-11:00AM | F93: Call | G93: Follow up | H93: Tender | I93: RFQ Processing | J93: Madinah | K93: Check Al Alyaa project quotation status | L93: 46156 | M93: Submit quote
A94: 46152 | B94: =WEEKNUM(A94) -> 20 | C94: Zedca Project | D94: Omar Alsaad | E94: 10:00-11:00AM | F94: Call | G94: Follow up | H94: In Hand | I94: Gather Info. | J94: RedSea | K94: Weekly follow up on border project | L94: 46159 | M94: Track progress
A95: 46152 | B95: =WEEKNUM(A95) -> 20 | C95: IHCC - Bab Al Khair | D95: Youssef Adwi | E95: 11:00-12:00PM | F95: Call | G95: Follow up | H95: In Hand | I95: RFQ Processing | J95: Makkah | K95: Check quotation status | L95: 46156 | M95: Get pricing
A96: 46152 | B96: =WEEKNUM(A96) -> 20 | C96: MACC - KAUST | D96: Omar El Hanoun | E96: 11:00-12:00PM | F96: Call | G96: Follow up | H96: In Hand | I96: RFQ Processing | J96: Jeddah | K96: Follow up on FA project | L96: 46156 | M96: Get update
A97: 46152 | B97: =WEEKNUM(A97) -> 20 | C97: Afrina - Rosemond | D97: Khaled ElShiekh | E97: 11:00-12:00PM | F97: Call | G97: Follow up | H97: In Hand | I97: RFQ Processing | J97: Jeddah | K97: Check Rosemond Hotel quotation | L97: 46154 | M97: Get quote ready
A98: 46152 | B98: =WEEKNUM(A98) -> 20 | C98: Honeywell | D98: Mohamed 3essa | E98: 12:00-1:00PM | F98: F2F Meeting | G98: Follow up | H98: - | I98: - | J98: Jeddah | K98: Monthly check-in + discuss new projects | L98: 46159 | M98: Send project leads
A99: 46152 | B99: =WEEKNUM(A99) -> 20 | C99: Afrina - 4 Projects | D99: Ashraf Gadallah | E99: 1:00-2:00PM | F99: F2F Meeting | G99: Follow up | H99: In Hand | I99: Gather Info. | J99: Jeddah | K99: Visit office - discuss all in-hand projects | L99: 46156 | M99: Get BOQs
A100: 46152 | B100: =WEEKNUM(A100) -> 20 | C100: GRC Villas | D100: Ehab GRC | E100: 3:00-4:00PM | F100: Call | G100: Follow up | H100: In Hand | I100: RFQ Processing | J100: Riyadh | K100: Urgent follow up - deadline passed! | L100: 46154 | M100: Close deal
A101: 46152 | B101: =WEEKNUM(A101) -> 20 | C101: AlShamela | D101: Helmy Abdelrazeq | E101: 3:00-4:00PM | F101: Call | G101: Follow up | H101: - | I101: - | J101: Jeddah | K101: Follow up on Pre-Qualification | L101: 46156 | M101: Book meeting
...

Sheet Master Report
A1: Date | B1: Week | C1: Opportunity | D1: Contact | E1: Period | F1: Type | G1: Visit Type | H1: Project Stage | I1: Project Status | J1: Project Location | K1: Action | L1: Follow Up Date | M1: Follow Up Action
A2: 46139 | B2: =WEEKNUM(A2) -> 18 | D2: Mohamed Abodagga | E2: 9:10AM | F2: Call | G2: Cold Call | H2: - | I2: - | J2: Neom | K2: كان بيقولي انه محتاج يدينا مشروع نيوم بتاعهم عشان نبدأ نشتغل فيه و قولتله ان انتم عليكم فلوس لسة للشركة و محتاجين نقسمهم على دفعات | L2: 46140 | M2: بجيب كشف الحساب بتاعهم و هكلمه تاني عشان اخد التفاصيل منه
A3: 46139 | B3: =WEEKNUM(A3) -> 18 | C3: فندق الادلاء | D3: Mohamed Khalifah | E3: 9:10AM | F3: Call | G3: Follow up | H3: In Hand | I3: RFQ Processing | J3: Madinah | K3: المشروع ده in hand معاهم و محتاجين يسعروا ال BOQ فقط | L3: 46142 | M3: هتابعه اول ما الكوتيشن تطلع
A4: 46139 | B4: =WEEKNUM(A4) -> 18 | C4: مشروع فلل سكن خاص لعبدالعزيز حبيب | D4: عبد العزيز حبيب | E4: 11:12AM | F4: F2F Meeting | G4: New Lead | H4: In Hand | I4: Gather Info. | J4: Makkah | K4: لسة هكلمه نزلت شوفت اليافطة و انا معدي في الزايدي
A5: 46139 | B5: =WEEKNUM(A5) -> 18 | C5: مشروع فلل سكن خاص | D5: مسار العقارية | E5: 11:12AM | F5: F2F Meeting | G5: New Lead | H5: In Hand | I5: Gather Info. | J5: Makkah | K5: لسة هكلمه نزلت شوفت اليافطة و انا معدي في الزايدي
A6: 46139 | B6: =WEEKNUM(A6) -> 18 | C6: V-Yard | D6: Sohail | E6: 12:1PM | F6: F2F Meeting | G6: New Lead | H6: In Hand | I6: Gather Info. | J6: Makkah | K6: ده مشروع مجمع المنار عبارة عن سكني و تجاري و المفروض اتابع مع عبدالرحمن محمد و اعرف التفاصيل
A7: 46139 | B7: =WEEKNUM(A7) -> 18 | C7: بوابة الملك سلمان | D7: Ahmed Abo Saif | E7: 1:2PM | F7: F2F Meeting | G7: New Lead | H7: In Hand | I7: Gather Info. | J7: Makkah | K7: خدت رقم احمد ابو سيف ده MEP Manager في شركة انجاز و دي شركة MEP Sub Contactor في المشروع و كلمته و لسة مردش عليا بخصوص مشروع بوابة الملك سلمان
A8: 46139 | B8: =WEEKNUM(A8) -> 18 | C8: فندق واحة الرفاع | D8: Ahmed Yasser | E8: 2:3:PM | F8: Call | G8: New Lead | H8: In Hand | I8: Gather Info. | J8: Makkah | K8: ده فندق واحة الرفاع بيعملوا تجديدات من وقت للتاني و تحتيهم اكثر من فندق شغالين عليه و كلمته و مردش و هكلمه تاني انهاردة
A9: 46139 | B9: =WEEKNUM(A9) -> 18 | E9: 3:4PM | F9: Hunting | H9: - | I9: - | J9: Makkah | K9: مجمع المنار - روشن
A10: 46139 | B10: =WEEKNUM(A10) -> 18 | D10: Mohamed Radwan | E10: 4:5PM | F10: Call | K10: دخلنا ميتنج عشان نخلص باقي الشيت بتاع ال Follow Up
B11: =WEEKNUM(A11) -> 0
A12: 46140 | B12: =WEEKNUM(A12) -> 18 | C12: Al-Salama Hospital | D12: Yasser Bahussin | E12: 9:10AM | F12: Call | G12: Follow up | H12: In Hand | I12: Gather Info. | J12: Jeddah | K12: كنت بتابع معاه السيستم الي هو محتاجه في المستشفى عنده و اتفقت اني هروحله بكره الاربعاء في جدة عشان اعمل معاينه للي هو محتاجة بالظبط لانه مش عارف يشرح في التليفون | L12: 46141
A13: 46140 | B13: =WEEKNUM(A13) -> 18 | C13: Al-Salama Hospital | D13: Komar Morgan | E13: 9:10AM | F13: Call | G13: Follow up | H13: In Hand | I13: Gather Info. | J13: Jeddah | K13: كنت بتابع معاه السيستم الي هو محتاجه في المستشفى عنده و اتفقت اني هروحله بكره الاربعاء في جدة عشان اعمل معاينه للي هو محتاجة بالظبط لانه مش عارف يشرح في التليفون | L13: 46141
A14: 46140 | B14: =WEEKNUM(A14) -> 18 | C14: ابراج موطن المسار | D14: Ashraf Gadallah | E14: 10:11AM | F14: Call | G14: New Lead | H14: In Hand | I14: Gather Info. | J14: Jeddah | K14: دي شركة عفرينا Afrina معاهم 4 مشاريع in hand و منهم مشروع ابراج موطن المسار و ده مهم جدا على طريق مكة قالي ابعتلي Pre Qualification و بعدها نحدد ميعاد نتقابل في المكتب | L14: 46142 | M14: بعت الي هو محتاجة و مستني الرد
A15: 46140 | B15: =WEEKNUM(A15) -> 18 | C15: Honeywell | D15: Mohamed 3essa | E15: 1:2PM | F15: Call | G15: Follow up | H15: - | I15: - | J15: Jeddah | K15: م/ عمير اداني رقمه اكلمه عشان انزل اقابله و اتعرف عليه و م اخد منه مشاريع الميتنج يوم الاحد القادم و هأكد عليه السبت | L15: 46145 | M15: ميتنج الاحد القادم
A16: 46140 | B16: =WEEKNUM(A16) -> 18 | C16: رؤى الحرم المكي | E16: 2:3:PM | F16: Hunting | G16: Visit | H16: - | I16: - | J16: Makkah | K16: روحت الشركة نفسها عشان اقابل حد بس للاسف لازم ميعاد من الاول و مش عارف اوصل لاي حد
A17: 46140 | B17: =WEEKNUM(A17) -> 18 | E17: 2:3:PM | F17: Office Stuff | K17: تعديل شيت الاكسيل
B18: =WEEKNUM(A18) -> 0
A19: 46141 | B19: =WEEKNUM(A19) -> 18 | C19: Al-Salama Hospital | D19: Yasser Bahussin | E19: 9:10AM | F19: F2F Meeting | G19: Follow up | H19: In Hand | I19: Gather Info. | J19: Jeddah | K19: روح المستشفى عشان اشوف السيستم نفسه محتاج تعديل ازاي و قعدت مع تيم المهندسين عشان اعرف هم محتاجين ايه بالظبط | L19: 46144 | M19: معرفه هل يمكن عمل السيستم ام لا
A20: 46141 | B20: =WEEKNUM(A20) -> 18 | C20: Bits Arabia | D20: Mohamed Kahla | E20: 11:12AM | F20: F2F Meeting | G20: New Lead | H20: - | I20: - | J20: Jeddah | K20: اتعرفت عليه في الايفنت و ممكن يكون فيه تواصل بينا مستمر عشان المشاريع لو ينفع نبدل مع بعض المشاريع دي
A21: 46141 | B21: =WEEKNUM(A21) -> 18 | C21: HPE Aruba Event | D21: Abdallah Lutf | E21: 12:1PM | F21: Event | G21: Visit | H21: - | I21: - | J21: Jeddah | K21: ايفنت خاص ب HPE - Al Jammaz Tech. كان بيتكلم على منتجات Aruba الجديدة و ازاي هي بتقدر تتوقع بالمشاكل الي ممكن تحصل من Latency & Hacking و الى اخره
A22: 46141 | B22: =WEEKNUM(A22) -> 18 | C22: Honeywell Meeting | D22: Hassan Samir Zino | E22: 4:5PM | F22: F2F Meeting | G22: Visit | H22: - | I22: - | J22: Jeddah | K22: كان ميتنج تعارف بيني و بين مهندس حسن و علاء من Honeywell و و ان شاء الله يكون فيه بينا شغل دايما | L22: 46139
B23: =WEEKNUM(A23) -> 0
A24: 46142 | B24: =WEEKNUM(A24) -> 18 | C24: Al-Salama Hospital | D24: Yasser Bahussin | E24: 9:10AM | F24: Call | G24: Follow up | H24: In Hand | I24: Gather Info. | J24: Jeddah | K24: حددت ميتنج معاه يوم الاحد الساعة 1 | L24: 46145 | M24: Team Meeting
A25: 46142 | B25: =WEEKNUM(A25) -> 18 | C25: Call with Taha and Omnia | E25: 10:11AM | K25: كنت بتابع معاهم المشاريع بتاعتي وصلت لفين
A26: 46142 | B26: =WEEKNUM(A26) -> 18 | E26: 3:4PM | F26: Office Stuff | K26: كنت بخلص اخر ابديت فالشيت و خلاص بقا جاهز عشان نشتغل عليه الحمد لله
A27: 46142 | B27: =WEEKNUM(A27) -> 18 | C27: Alawalat | D27: Mohamed Atef | E27: 3:4PM | F27: Call | G27: Cold Call | H27: - | I27: - | K27: بعتله على الواتساب الميل بتاعي و البزنس كارد و قالي انه هيتابع معايا لو فيه اي مشاريع جديدة جاتله و ساب شركة الشاملة و راح شركة الرياض | L27: 46149
A28: 46142 | B28: =WEEKNUM(A28) -> 18 | C28: ALmawel Contracting | D28: Ahmed Naserallah | E28: 3:4PM | F28: Call | G28: Cold Call | H28: - | I28: - | K28: اكونت جديد كلمته و مكانش يعرفنا سألته على المشاريع بس دلوقتي مفيش حاجة و الاسبوع الجي هيكون فيه مشروع | L28: 46149 | M28: Call again
A29: 46142 | B29: =WEEKNUM(A29) -> 18 | C29: KAMC | D29: Abdelrahman Rubei | E29: 3:4PM | F29: Call | G29: Cold Call | H29: - | I29: - | K29: كلمته و مردش و بعتله على الواتساب عشان اتابع معاه لو فيه مشاريع
A30: 46142 | B30: =WEEKNUM(A30) -> 18 | C30: IMC Hospital | D30: Sameh Saber | E30: 3:4PM | F30: Call | G30: Cold Call | H30: - | I30: - | J30: Jeddah | K30: لسة متصل بيا دلوقتي و قالي ابعتلي Pre و هنتكلم تاني نتعرف على بعض اكتر | L30: 46145 | M30: Send Pre then Follow up
B31: =WEEKNUM(A31) -> 0
A32: 46144 | B32: =WEEKNUM(A32) -> 18 | C32: Kix Futsal Complex | D32: Mohamed Hanifa | E32: 9:10AM | F32: Call | G32: Follow up | H32: Tender | I32: Send to Client | J32: Jeddah | K32: متابعة | L32: 46145 | M32: هيقولي ايه الجديد الي حصل فالمشروع
A33: 46144 | B33: =WEEKNUM(A33) -> 18 | C33: IMC Hospital | D33: Ibrahim Ahmed | E33: 9:10AM | F33: Call | G33: Follow up | H33: Tender | I33: RFQ Processing | J33: Jeddah | K33: متابعة | L33: 46146 | M33: كنت بسأله على المشروع و قالي انه ميعرفش ايه الجديد فيه لسة و هيقولي الابديت يوم الاتنين
A34: 46144 | B34: =WEEKNUM(A34) -> 18 | C34: Honeywell | D34: Hassan Samir Zino | E34: 9:10AM | F34: Call | G34: Follow up | H34: - | I34: - | J34: Jeddah | K34: كنت بتابعه كده من وقت للتاني عشان اشوف لو فيه مشروع محتاج اروح ازوره | L34: 46147
A35: 46144 | B35: =WEEKNUM(A35) -> 18 | C35: Code 03 | D35: Abdelrahman Al-Shibi | E35: 10:11AM | F35: Call | G35: Cold Call | H35: In Hand | I35: Technically Approved | J35: Khobar | K35: فيه مشروع اسمه Code 3 اتبعتلهم Technical Submittal و خلاص الاستشاري وافق عليه و مستني الابديت الاخير | L35: 46145 | M35: اكلمه بكرة اتابع معاه عشان يبعتلي الميل بتاع ال Follow sheet
A36: 46144 | B36: =WEEKNUM(A36) -> 18 | C36: IKK Group | D36: Mohamed IKK | E36: 10:11AM | F36: Call | G36: Cold Call | H36: - | I36: - | K36: مش شغال السبت كنت بسأله على المشاريع بس قالي كلمني الاحد | L36: 46145 | M36: كلمه تاني يوم الاحد
A37: 46144 | B37: =WEEKNUM(A37) -> 18 | C37: صالة الامير فيصل للفنون | D37: Hussni | E37: 11:12AM | F37: Call | G37: Follow up | H37: In Hand | I37: Gather Info. | J37: Riyadh | K37: كان متضايق من ان اسعارنا غالية بس هندلته و قالي روح اعمل معاينة للمشروع فيه هناك Barriers , CCTV , BMS و كمان فيه Fire بس مش عاوز يديهولنا | M37: المشروع ده هيروحه بشمهندس حمدي
A38: 46144 | B38: =WEEKNUM(A38) -> 18 | C38: Creet | D38: Mo2nes Amr | E38: 11:12AM | F38: Call | G38: Follow up | H38: In Hand | I38: Won | K38: بحاول على قد ما اقدر احصل منهم الفلوس الي موجودة على الشركة بس فيه مشكلة في كشف الحساب و بتابعها | L38: 46145 | M38: مستني من مصطفى هزاع انه يقولي الكاميرات و البضاعه هتوصل امتى عشان اخلي الراجل يحول الفلوس
A39: 46144 | B39: =WEEKNUM(A39) -> 18 | E39: 11:12AM | F39: Office Stuff | K39: متابعة مع مصطفى هزاع و متابعة مع امل في الحسابات عشان اعرف وصلنا لفين في مديونية الشركات كلمت Hexagon و كلمت Creet
A40: 46144 | B40: =WEEKNUM(A40) -> 18 | C40: Hexagon | D40: Mohamed Abodagga | E40: 12:1PM | F40: Call | G40: Follow up | H40: - | I40: - | K40: كلمته عشان اتابع معاه المشروع الي عاوزنا نخلص فيه و كمان عشان اعرف الفلوس ايه اخبارها و قالي هرد عليك خلال اليوم و مستني مني عرض السعر | L40: 46145 | M40: هيرد عليا يقولي الباقي
A41: 46144 | B41: =WEEKNUM(A41) -> 18 | C41: Western Tower Jeddah | D41: Mohamed Youssef | E41: 12:1PM | F41: Call | G41: Cold Call | H41: In Hand | I41: Gather Info. | J41: Jeddah | K41: قالي ان مشروع Western Tower ده مع المشتريات خلاص و هيبعتلي رقم حد منهم بكرة | L41: 46145 | M41: عاوز رقم حد من المشتريات
A42: 46144 | B42: =WEEKNUM(A42) -> 18 | C42: Zedca منافذ حدودية | D42: Omar Alsaad | E42: 1:2PM | F42: Call | G42: Follow up | H42: In Hand | I42: Gather Info. | J42: RedSea | K42: قالي انه هيجيبلي تفاصيل IMC بكرة و كمان فيه مشروع من سنتين و نص على حدود الاردن اسمه Zedca ده عبارة عن منافذ حدودية | L42: 46145 | M42: هديني اخر ابديت IMC و يقولي تفاصيل مشروع Zedca
A43: 46144 | B43: =WEEKNUM(A43) -> 18 | C43: Onity Project | D43: Ibrahim Sabry | E43: 1:2PM | F43: Call | G43: Follow up | H43: In Hand | I43: Send to Client | J43: Makkah | K43: سألته على المشروع بتاع onity بس مفيش رد جديد لسة الراجل مش بيرد علينا | L43: 46147 | M43: هكلمه كمان 3 ايام كده اشوف ايه الجديد معاه
A44: 46144 | B44: =WEEKNUM(A44) -> 18 | E44: 3:4PM | F44: Online Meeting | G44: Follow up | H44: - | I44: - | K44: تجهيز الشيت الاخير و عملت شير مع الشباب و كمان شرحتلهم كل حاجة تاني من الاول يقدروا يستخدموه دلوقتي
A45: 46144 | B45: =WEEKNUM(A45) -> 18 | E45: 4:5PM | F45: Online Meeting | G45: Follow up | H45: - | I45: -
B46: =WEEKNUM(A46) -> 0
A47: 46145 | B47: =WEEKNUM(A47) -> 19 | C47: Kix Futsal Complex | D47: Mohamed Hanifa | E47: 9:10AM | F47: Call | G47: Follow up | H47: Tender | I47: Negotiation | J47: Jeddah | K47: طلب مني ديسكاونت كويس عشان هو بيجهز ال submittal بتاعه الاخير خلاص و ان شاء الله يكون المشروع معانا | L47: 46145 | M47: كلم عمير هات منه ديسكاونت
A48: 46145 | B48: =WEEKNUM(A48) -> 19 | C48: IMC Hospital | D48: Sameh Saber | E48: 9:10AM | F48: Call | G48: Follow up | H48: Tender | I48: Send to Client | J48: Jeddah | K48: كنت بسأله لو فيه مشاريع تاني قالي المشاريع بتيجي كل شهر ولا اتنين مش كل اسبوع ف تابعني كل شهر | L48: 46166 | M48: شوف حد تاني من هناك تابعه افضل عشان الراجل ده قليل الذوق
A49: 46145 | B49: =WEEKNUM(A49) -> 19 | C49: RIC | D49: Abdelrahman Al-Shibi | E49: 9:10AM | F49: Call | G49: Follow up | H49: In Hand | I49: Technically Approved | J49: Riyadh | K49: كلمته عشان يبعتلي الشيت الي قالي عليه بتاع المشروع بس عرفت ان المشروع اصلا مع عبدالرحمن عبدالعليم
A50: 46145 | B50: =WEEKNUM(A50) -> 19 | D50: Mohamed IKK | E50: 10:11AM | F50: Call | G50: Cold Call | H50: - | I50: - | J50: Jeddah | K50: قالي ابعتلي ميل عشان احطك في ال CC في اي مشروع بعد كده و بعتله البروفايل و يومين كده و اكلمه تاني ااكد عليه | L50: 46148 | M50: كلمه اكد عليه انه شاف البروفايل و حاول تحدد معاه ميعاد
A51: 46145 | B51: =WEEKNUM(A51) -> 19 | D51: Mohamed Arif | E51: 10:11AM | F51: Call | G51: Cold Call | H51: In Hand | I51: Technical Submission | K51: فيه كوتيشن مسعرينها معانا رقمها : q969.16.lcu و بيقولي انهم بعتوا ال submittal خلاص و مستنيين الفيدباك خلال اسبوعين | L51: 46156 | M51: كلمه كمان اسبوعين اعرف ايه الدنيا في المشروع ده
A52: 46145 | B52: =WEEKNUM(A52) -> 19 | C52: Honeywell | D52: Mohamed 3essa | E52: 11:12AM | F52: Call | G52: Follow up | J52: Jeddah | K52: هروح لمهندس محمد عيسى جدة نقعد مع بعض و نشوف المشاريع الي نقدر نشتغل عليها و هيشرحلي عن البراند اكتر كمان | L52: 46146 | M52: بكرة ميتنج جدة
A53: 46145 | B53: =WEEKNUM(A53) -> 19 | C53: IHCC | D53: Zubair | E53: 11:12AM | F53: Call | G53: Follow up | H53: - | I53: - | J53: Jeddah | K53: قالي انه مفيش مشاريع في الوقت الحالي و بخصوص ال BMS واحد من صحابة في الشغل هو الي ماشي في الحتة دي | L53: 46152 | M53: عاوز منه رقم صاحبه بتاع ال BMS و عاوز اتابع معاه كل اسبوع
A54: 46145 | B54: =WEEKNUM(A54) -> 19 | C54: Al-Salama Hospital | D54: Yasser Bahussin | E54: 12:1PM | F54: Online Meeting | G54: Follow up | H54: In Hand | I54: RFQ Processing | J54: Jeddah
A55: 46145 | B55: =WEEKNUM(A55) -> 19 | C55: Al-Salama Hospital | D55: Yasser Bahussin | E55: 1:2PM | F55: Online Meeting | G55: Follow up
A56: 46145 | B56: =WEEKNUM(A56) -> 19 | E56: 2:3:PM | F56: Hunting | K56: لفيت في العزايزية و طريق الملك فهد
A57: 46145 | B57: =WEEKNUM(A57) -> 19 | E57: 3:4PM | F57: Hunting
A58: 46145 | B58: =WEEKNUM(A58) -> 19 | E58: 4:5PM | F58: Hunting
B59: =WEEKNUM(A59) -> 0
A60: 46146 | B60: =WEEKNUM(A60) -> 19 | C60: Honeywell | D60: Mohamed 3essa | E60: 9:10AM | F60: F2F Meeting | G60: Follow up | H60: - | I60: -
A61: 46146 | B61: =WEEKNUM(A61) -> 19 | C61: Honeywell | D61: Mohamed 3essa | E61: 10:11AM | G61: Follow up | H61: - | I61: -
A62: 46146 | B62: =WEEKNUM(A62) -> 19 | C62: Honeywell | D62: Mohamed 3essa | E62: 11:12AM | G62: Follow up | H62: - | I62: -
A63: 46146 | B63: =WEEKNUM(A63) -> 19 | E63: 12:1PM | F63: Hunting | K63: لفيت ابحر الشمالية بالكامل
B64: =WEEKNUM(A64) -> 0
B65: =WEEKNUM(A65) -> 0
B66: =WEEKNUM(A66) -> 0
B67: =WEEKNUM(A67) -> 0
B68: =WEEKNUM(A68) -> 0
B69: =WEEKNUM(A69) -> 0
B70: =WEEKNUM(A70) -> 0
B71: =WEEKNUM(A71) -> 0
B72: =WEEKNUM(A72) -> 0
B73: =WEEKNUM(A73) -> 0
B74: =WEEKNUM(A74) -> 0
B75: =WEEKNUM(A75) -> 0
... B313: =WEEKNUM(A313) -> 0
A314: 46146 | B314: =WEEKNUM(A314) -> 19 | E314: 1:2PM | F314: Hunting
A315: 46146 | B315: =WEEKNUM(A315) -> 19 | E315: 2:3:PM | F315: Hunting
A316: 46146 | B316: =WEEKNUM(A316) -> 19 | E316: 3:4PM | F316: Hunting
A317: 46146 | B317: =WEEKNUM(A317) -> 19 | E317: 4:5PM | F317: Hunting
A318: 46146 | B318: =WEEKNUM(A318) -> 19 | C318: IHCC | D318: Azazuddin Mohamed | E318: After 5PM | F318: Call | G318: Cold Call | H318: - | I318: - | K318: الراجل ده بيكون ماسك كل مشاريع ال BMS كلمته و رايحله الاربع ميتنج | L318: 46148 | M318: الاربعاء ميتنج
A319: 46146 | B319: =WEEKNUM(A319) -> 19 | C319: GRC | D319: Ehab GRC | E319: After 5PM | F319: Call | G319: Cold Call | H319: In Hand | I319: Gather Info. | J319: Riyadh | K319: معاه مشروعين in hand ده تبع مهندس فراس الي عندنا في الشركة ومحتاج اتابع معاه كمان يومين اعرف الداتا وصلت لفين | L319: 46148 | M319: Follow Up
B320: =WEEKNUM(A320) -> 0
A321: 46147 | B321: =WEEKNUM(A321) -> 19 | C321: Creet | D321: Khaled Hussain | E321: 9:10AM | F321: Call | G321: Cold Call | H321: In Hand | I321: RFQ Processing | J321: Jeddah | K321: معاه مشروع فندق Renovation و محتاج Low Current Systems و كمان GRMS وصلت معاه لاني بجيب سعر من Legrand , Schneider , EAE , Incomm و مستعجل على المشروع جدا اخر يوم هو يوم الاحد و ده هو عاوز كوميشن لنفسه عشان المشروع ده بره شركة Creet | L321: 46149 | M321: Follow up
A322: 46147 | B322: =WEEKNUM(A322) -> 19 | C322: Mini Market in KAUST | D322: Omar El Hanoun | E322: 9:10AM | F322: Call | G322: Follow up | H322: In Hand | I322: RFQ Processing | J322: Jeddah | K322: بيبعتلي في الاول مقطوعيات بس و دلوقتي معاه مشاريع و بتابع معاه كل اسبوع لو فيه حاجة جديدة و قالي انه مستعجل على مشروع ال Mini Market Kaust و محتاجه في اقرب وقت | L322: 46151 | M322: Follow up
A323: 46147 | B323: =WEEKNUM(A323) -> 19 | C323: Bab Al Khair Hospital | D323: Youssef Adwi | E323: 10:11AM | F323: Call | G323: New Lead | H323: In Hand | I323: RFQ Processing | J323: Makkah | K323: المشروع ده مشروع خيري في مكة و محتاجين اقل سعر في كل حاجة و هو بيقولي اول ما تخلص اي تسعير لاي نظام ابعتلي على طول السعر لانه هيخش مع اقل سعر في اي نظام | L323: 46151 | M323: Follow Up
A324: 46147 | B324: =WEEKNUM(A324) -> 19 | C324: New Multistory Storage | D324: Mohamed Hussain | E324: 10:11AM | F324: Call | G324: Follow up | H324: In Hand | I324: Lost | J324: Riyadh | K324: خسرنا المشروع بسبب السعر و التأخير في الرد على سعر الكوتيشن
A325: 46147 | B325: =WEEKNUM(A325) -> 19 | C325: Catrion Creet | D325: Mo2nes Amr | E325: 11:12AM | F325: Call | G325: Follow up | H325: In Hand | I325: Won | J325: Jeddah | K325: بتابع معاه الفلوس المدفوعات و المستحقات المالية بينا و بينه و بظبط الضمانات الي هو محتاجها عشان ناخد فلوسنا كلها | L325: 46151 | M325: لازم ابعتله الضمان بتاع كل item و كمان اعرف الكاميرات ال 8 Mega Pixels هتوصل امتى
A326: 46147 | B326: =WEEKNUM(A326) -> 19 | C326: Stock on Fire | E326: 12:1PM | F326: Office Stuff | K326: كنت بحاول اشرف موزع تاني للكاميرات ال 8 ميجا بيكسل و فعلا لقيت سعر اقل بس لسة مدة التوريد طويلة
A327: 46147 | B327: =WEEKNUM(A327) -> 19 | C327: IMC Hospital | D327: Omar Alsaad | E327: 12:1PM | F327: Call | G327: Follow up | H327: Tender | I327: RFQ Processing | J327: Jeddah | K327: مفيش جديد في مشروع IMC لسة اصلا احنا مطلعناش عروض الاسعار بتاعتنا لحد دلوقتي ف بتابع معاه عشان لو رسي على حد | L327: 46152 | M327: Follow Up
A328: 46147 | B328: =WEEKNUM(A328) -> 19 | C328: Mawten Masar | D328: Khaled ElShiekh | E328: 1:2PM | F328: Call | G328: Follow up | H328: In Hand | I328: Gather Info. | J328: Makkah | K328: معاه مشروع موطن مسار و بحاول اخد منه الباكدج بأي شكل من الاشكال و اداني حد من المشتريات
A329: 46147 | B329: =WEEKNUM(A329) -> 19 | C329: Mawten Masar | D329: Mohamed Ramadan | E329: 1:2PM | F329: Call | G329: Follow up | H329: In Hand | I329: Gather Info. | J329: Makkah | K329: ده معاه الباكدج بتاعت مشروع موطن مسار و بعتله ال Pre Qualification بتاعتنا و قالي اول ما هبص عليها هبعتلك الباكدج عشان تسعرها على طول | L329: 46149 | M329: Follow Up
A330: 46147 | B330: =WEEKNUM(A330) -> 19 | C330: Al-Shamela | D330: Helmy Abdelrazeq | E330: 2:3:PM | F330: Call | G330: Follow up | H330: - | I330: Lost | J330: Jeddah | K330: بعتله تاني عشان ااكد عليه يبعتلي مشاريعه ال in hand و لسة مستنيه يبعتهالي | L330: 46149 | M330: Follow Up
A331: 46147 | B331: =WEEKNUM(A331) -> 19 | C331: Honeywell | D331: Mohamed 3essa | E331: 3:4PM | F331: Call | G331: Follow up | H331: - | K331: كنت بسأله لو يقدر يوفر الكاميرات بتاعت مشروع Catrion
A332: 46147 | B332: =WEEKNUM(A332) -> 19 | E332: 4:5PM | F332: Office Stuff | K332: Fill Follow up Sheet and update notes on the projects
B333: =WEEKNUM(A333) -> 0
A334: 46148 | B334: =WEEKNUM(A334) -> 19 | C334: GRC | D334: Ehab GRC | E334: 9:10AM | F334: Call | G334: Follow up | H334: In Hand | I334: RFQ Processing | J334: Riyadh | K334: معاه مشروع فيلات و مشروع al Qiddya و بعتلي الملفات و رفعتهم للشباب و لسة شغالين عليهم و المفروض ان حاجة فيهم هتخلص يوم السبت او الاحد بالكتير | L334: 46149 | M334: مستني الكوتيشن تخلص
A335: 46148 | B335: =WEEKNUM(A335) -> 19 | C335: Mawten Masar | D335: Mohamed Ramadan | E335: 9:10AM | F335: Call | G335: Follow up | H335: In Hand | I335: Gather Info. | J335: Makkah | K335: لسة برضه مستني منه المشروع مش عاوز يبعته | L335: 46151 | M335: هكلمه تاني عشان يبعت الباكدج
A336: 46148 | B336: =WEEKNUM(A336) -> 19 | C336: IHCC | D336: Azazuddin Mohamed | E336: 10:11AM | F336: Call | G336: Follow up | H336: - | I336: - | J336: Jeddah | K336: كلمته عشان احدد ميتنج معاه تاني عشان طلع مش فاضي في اليوم ده و قالي كلمني على اول الاسبوع الجي | L336: 46152 | M336: حدد معاه ميتنج
A337: 46148 | B337: =WEEKNUM(A337) -> 19 | C337: MHM | D337: Mohamed Hanifa | E337: 10:11AM | F337: Call | G337: Follow up | H337: Tender | I337: Negotiation | J337: Jeddah | K337: المشروع كان عاوز عليه ديسكاونت و لسة لحد دلوقتي مردش عليا في الجديد بتاعه | L337: 46151 | M337: محتاج اتابع معاه اخبار المشروع عشان كان بيقدم اخر حاجة
...

Sheet Data Validation
A1: Project Stage | B1: Project Status | C1: Project Location | E1: Visit Type | F1: Period | K1: Type Weekly Plan
A2: In Hand | B2: Gather Info. | C2: Makkah | E2: New Lead | F2: 9:10AM | H2: New Lead | K2: Call
A3: Tender | B3: RFQ Processing | C3: Jeddah | E3: Follow up | F3: 10:11AM | H3: Follow up | K3: F2F Meeting
A4: - | B4: Send to Client | C4: Madinah | E4: Visit from Cold Call | F4: 11:12AM | H4: Visit from Cold Call | K4: Hunting
B5: Technical Submission | C5: Riyadh | E5: Consultant Visit | F5: 12:1PM | H5: Consultant Visit | K5: Office Stuff
B6: Technically Approved | C6: Dammam | E6: Cold Call | F6: 1:2PM | H6: Visit | K6: Event
B7: Negotiation | C7: Abha | E7: Visit | F7: 2:3:PM | K7: Online Meeting
B8: Won | C8: Jizan | F8: 3:4PM
B9: Lost | C9: Khobar | F9: 4:5PM
B10: Hold | C10: Najran | F10: After 5PM
B11: - | C11: Qassim
C12: Rabigh
C13: Yanbu
C14: Jubail
C15: Dhahran
C16: Arar
C17: Kharj
C18: Tabouk
C19: Neom
C20: RedSea
C21: Tanajib
C22: Al Ahsa
C23: Ras Alkhair
... C27: Al Khafji

Sheet Won Deals
A1: PR | B1: Quotation Number | C1: Company | D1: Engineer | E1: Date | F1: Descreption / Project | G1: Amount
A2: PR-60745 | B2: Q2032-726-BMS | C2: MACC | D2: Omar Hanoun | E2: 28/7/2026 | F2: V4 Actuated Lug Type Butterfly Valve, Cast Iron, PN16, DN350, Modulating, Ductile Iron, 220V AC, 527x1055x385mm | G2: 15962
